Workbook
Name _Hlk175215188: 'MR13 1'!#REF!

Sheet ZLP 1
V1: List Price Sheet 6ZL-V
U2: 46143
C3: AFC COST | D3: 35% Margin | E3: 30% Margin | F3: 25% Margin | V3: Section 6
V4: Product Bulletin 6 ZLINE
B6: The Z-Line Series ZL
C8: 1 | N8: 2
B9: PART | C9: STANDARD | D9: LIST | E9: Multiplier | J9: CARTON | K9: CARTON | M9: PART | N9: STANDARD | O9: LIST | P9: Multiplier | U9: CARTON | V9: CARTON
B10: NUMBER | C10: SIZES | D10: PRICE | E10: 0.4 | F10: 35% Margin | G10: 30% Margin | H10: 25% Margin | J10: QUANTITY | K10: WEIGHT | M10: NUMBER | N10: SIZES | O10: PRICE | P10: 0.38 | Q10: 35% Margin | R10: 30% Margin | S10: 25% Margin | U10: QUANTITY | V10: WEIGHT
B11: ZLP10101 | C11: 10x10x1 | D11: 6.85 | E11: =D11*$E$10 -> 2.74 | F11: =(E11/0.65)+0.3 -> 4.5153846 | G11: =(E11/0.7)+0.3 -> 4.2142857 | H11: =(E11/0.75)+0.3 -> 3.9533333 | I11: =(E11/0.8)+0.3 -> 3.725 | J11: 12 | K11: 4 LB. | M11: ZLP10202 | N11: 10x20x2 | O11: 7.52 | P11: =O11*$P$10 -> 2.8576 | Q11: =(P11/0.65)+0.3 -> 4.6963077 | R11: =(P11/0.7)+0.3 -> 4.3822857 | S11: =(P11/0.75)+0.3 -> 4.1101333 | T11: =(P11/0.8)+0.3 -> 3.872 | U11: 12 | V11: 9 LB.
B12: ZLP10201 | C12: 10x20x1 | D12: 7.24 | E12: =D12*$E$10 -> 2.896 | F12: =(E12/0.65)+0.3 -> 4.7553846 | G12: =(E12/0.7)+0.3 -> 4.4371429 | H12: =(E12/0.75)+0.3 -> 4.1613333 | I12: =(E12/0.8)+0.3 -> 3.92 | J12: 12 | K12: 6 LB. | M12: ZLP12122 | N12: 12x12x2 | O12: 10.07 | P12: =O12*$P$10 -> 3.8266 | Q12: =(P12/0.65)+0.3 -> 6.1870769 | R12: =(P12/0.7)+0.3 -> 5.7665714 | S12: =(P12/0.75)+0.3 -> 5.4021333 | T12: =(P12/0.8)+0.3 -> 5.08325 | U12: 12 | V12: 8 LB.
B13: ZLP10241 | C13: 10x24x1 | D13: 14.24 | E13: =D13*$E$10 -> 5.696 | F13: =(E13/0.65)+0.3 -> 9.0630769 | G13: =(E13/0.7)+0.3 -> 8.4371429 | H13: =(E13/0.75)+0.3 -> 7.8946667 | I13: =(E13/0.8)+0.3 -> 7.42 | J13: 12 | K13: 6 LB. | M13: ZLP12202 | N13: 12x20x2 | O13: 8.02 | P13: =O13*$P$10 -> 3.0476 | Q13: =(P13/0.65)+0.3 -> 4.9886154 | R13: =(P13/0.7)+0.3 -> 4.6537143 | S13: =(P13/0.75)+0.3 -> 4.3634667 | T13: =(P13/0.8)+0.3 -> 4.1095 | U13: 12 | V13: 10 LB.
B14: ZLP10301 | C14: 10x30x1 | D14: 14.62 | E14: =D14*$E$10 -> 5.848 | F14: =(E14/0.65)+0.3 -> 9.2969231 | G14: =(E14/0.7)+0.3 -> 8.6542857 | H14: =(E14/0.75)+0.3 -> 8.0973333 | I14: =(E14/0.8)+0.3 -> 7.61 | J14: 12 | K14: 7 LB. | M14: ZLP12242 | N14: 12x24x2 | O14: 7.74 | P14: =O14*$P$10 -> 2.9412 | Q14: =(P14/0.65)+0.3 -> 4.8249231 | R14: =(P14/0.7)+0.3 -> 4.5017143 | S14: =(P14/0.75)+0.3 -> 4.2216 | T14: =(P14/0.8)+0.3 -> 3.9765 | U14: 12 | V14: 9 LB.
B15: ZLP12121 | C15: 12x12x1 | D15: 8.79 | E15: =D15*$E$10 -> 3.516 | F15: =(E15/0.65)+0.3 -> 5.7092308 | G15: =(E15/0.7)+0.3 -> 5.3228571 | H15: =(E15/0.75)+0.3 -> 4.988 | I15: =(E15/0.8)+0.3 -> 4.695 | J15: 12 | K15: 5 LB. | M15: ZLP14202 | N15: 14x20x2 | O15: 8.24 | P15: =O15*$P$10 -> 3.1312 | Q15: =(P15/0.65)+0.3 -> 5.1172308 | R15: =(P15/0.7)+0.3 -> 4.7731429 | S15: =(P15/0.75)+0.3 -> 4.4749333 | T15: =(P15/0.8)+0.3 -> 4.214 | U15: 12 | V15: 9 LB.
B16: ZLP12201 | C16: 12x20x1 | D16: 7.44 | E16: =D16*$E$10 -> 2.976 | F16: =(E16/0.65)+0.3 -> 4.8784615 | G16: =(E16/0.7)+0.3 -> 4.5514286 | H16: =(E16/0.75)+0.3 -> 4.268 | I16: =(E16/0.8)+0.3 -> 4.02 | J16: 12 | K16: 7 LB. | M16: ZLP14252 | N16: 14x25x2 | O16: 9.09 | P16: =O16*$P$10 -> 3.4542 | Q16: =(P16/0.65)+0.3 -> 5.6141538 | R16: =(P16/0.7)+0.3 -> 5.2345714 | S16: =(P16/0.75)+0.3 -> 4.9056 | T16: =(P16/0.8)+0.3 -> 4.61775 | U16: 12 | V16: 11 LB.
B17: ZLP12241 | C17: 12x24x1 | D17: 7.24 | E17: =D17*$E$10 -> 2.896 | F17: =(E17/0.65)+0.3 -> 4.7553846 | G17: =(E17/0.7)+0.3 -> 4.4371429 | H17: =(E17/0.75)+0.3 -> 4.1613333 | I17: =(E17/0.8)+0.3 -> 3.92 | J17: 12 | K17: 6 LB. | M17: ZLP15202 | N17: 15x20x2 | O17: 8.24 | P17: =O17*$P$10 -> 3.1312 | Q17: =(P17/0.65)+0.3 -> 5.1172308 | R17: =(P17/0.7)+0.3 -> 4.7731429 | S17: =(P17/0.75)+0.3 -> 4.4749333 | T17: =(P17/0.8)+0.3 -> 4.214 | U17: 12 | V17: 9 LB.
B18: ZLP12251 | C18: 12x25x1 | D18: 7.74 | E18: =D18*$E$10 -> 3.096 | F18: =(E18/0.65)+0.3 -> 5.0630769 | G18: =(E18/0.7)+0.3 -> 4.7228571 | H18: =(E18/0.75)+0.3 -> 4.428 | I18: =(E18/0.8)+0.3 -> 4.17 | J18: 12 | K18: 6 LB. | M18: ZLP16162 | N18: 16x16x2 | O18: 10.56 | P18: =O18*$P$10 -> 4.0128 | Q18: =(P18/0.65)+0.3 -> 6.4735385 | R18: =(P18/0.7)+0.3 -> 6.0325714 | S18: =(P18/0.75)+0.3 -> 5.6504 | T18: =(P18/0.8)+0.3 -> 5.316 | U18: 12 | V18: 10 LB.
B19: ZLP12301 | C19: 12x30x1 | D19: 14.62 | E19: =D19*$E$10 -> 5.848 | F19: =(E19/0.65)+0.3 -> 9.2969231 | G19: =(E19/0.7)+0.3 -> 8.6542857 | H19: =(E19/0.75)+0.3 -> 8.0973333 | I19: =(E19/0.8)+0.3 -> 7.61 | J19: 12 | K19: 7 LB. | M19: ZLP16202 | N19: 16x20x2 | O19: 7.76 | P19: =O19*$P$10 -> 2.9488 | Q19: =(P19/0.65)+0.3 -> 4.8366154 | R19: =(P19/0.7)+0.3 -> 4.5125714 | S19: =(P19/0.75)+0.3 -> 4.2317333 | T19: =(P19/0.8)+0.3 -> 3.986 | U19: 12 | V19: 10 LB.
B20: ZLP14141 | C20: 14x14x1 | D20: 10.43 | E20: =D20*$E$10 -> 4.172 | F20: =(E20/0.65)+0.3 -> 6.7184615 | G20: =(E20/0.7)+0.3 -> 6.26 | H20: =(E20/0.75)+0.3 -> 5.8626667 | I20: =(E20/0.8)+0.3 -> 5.515 | J20: 12 | K20: 6 LB. | M20: ZLP16242 | N20: 16x24x2 | O20: 10.41 | P20: =O20*$P$10 -> 3.9558 | Q20: =(P20/0.65)+0.3 -> 6.3858462 | R20: =(P20/0.7)+0.3 -> 5.9511429 | S20: =(P20/0.75)+0.3 -> 5.5744 | T20: =(P20/0.8)+0.3 -> 5.24475 | U20: 12 | V20: 11 LB.
B21: ZLP14201 | C21: 14x20x1 | D21: 7.44 | E21: =D21*$E$10 -> 2.976 | F21: =(E21/0.65)+0.3 -> 4.8784615 | G21: =(E21/0.7)+0.3 -> 4.5514286 | H21: =(E21/0.75)+0.3 -> 4.268 | I21: =(E21/0.8)+0.3 -> 4.02 | J21: 12 | K21: 6 LB. | M21: ZLP16252 | N21: 16x25x2 | O21: 8.84 | P21: =O21*$P$10 -> 3.3592 | Q21: =(P21/0.65)+0.3 -> 5.468 | R21: =(P21/0.7)+0.3 -> 5.0988571 | S21: =(P21/0.75)+0.3 -> 4.7789333 | T21: =(P21/0.8)+0.3 -> 4.499 | U21: 12 | V21: 11 LB.
B22: ZLP14241 | C22: 14x24x1 | D22: 12.12 | E22: =D22*$E$10 -> 4.848 | F22: =(E22/0.65)+0.3 -> 7.7584615 | G22: =(E22/0.7)+0.3 -> 7.2257143 | H22: =(E22/0.75)+0.3 -> 6.764 | I22: =(E22/0.8)+0.3 -> 6.36 | J22: 12 | K22: 7 LB. | M22: ZLP18182 | N22: 18x18x2 | O22: 15.6 | P22: =O22*$P$10 -> 5.928 | Q22: =(P22/0.65)+0.3 -> 9.42 | R22: =(P22/0.7)+0.3 -> 8.7685714 | S22: =(P22/0.75)+0.3 -> 8.204 | T22: =(P22/0.8)+0.3 -> 7.71 | U22: 12 | V22: 11 LB.
... B31: ZLP16301 | C31: 16x30x1 | D31: 15.77 | E31: =D31*$E$10 -> 6.308 | F31: =(E31/0.65)+0.3 -> 10.004615 | G31: =(E31/0.7)+0.3 -> 9.3114286 | H31: =(E31/0.75)+0.3 -> 8.7106667 | I31: =(E31/0.8)+0.3 -> 8.185 | J31: 12 | K31: 9 LB. | M31: ZLP25252 | N31: 25x25x2 | O31: 13.86 | P31: =O31*$P$10 -> 5.2668 | Q31: =(P31/0.65)+0.3 -> 8.4027692 | R31: =(P31/0.7)+0.3 -> 7.824 | S31: =(P31/0.75)+0.3 -> 7.3224 | T31: =(P31/0.8)+0.3 -> 6.8835 | U31: 12 | V31: 20 LB.
B32: ZLP18181 | C32: 18x18x1 | D32: 14.62 | E32: =D32*$E$10 -> 5.848 | F32: =(E32/0.65)+0.3 -> 9.2969231 | G32: =(E32/0.7)+0.3 -> 8.6542857 | H32: =(E32/0.75)+0.3 -> 8.0973333 | I32: =(E32/0.8)+0.3 -> 7.61 | J32: 12 | K32: 8 LB.
B33: ZLP18201 | C33: 18x20x1 | D33: 10.19 | E33: =D33*$E$10 -> 4.076 | F33: =(E33/0.65)+0.3 -> 6.5707692 | G33: =(E33/0.7)+0.3 -> 6.1228571 | H33: =(E33/0.75)+0.3 -> 5.7346667 | I33: =(E33/0.8)+0.3 -> 5.395 | J33: 12 | K33: 8 LB. | N33: 4
B34: ZLP18241 | C34: 18x24x1 | D34: 9.77 | E34: =D34*$E$10 -> 3.908 | F34: =(E34/0.65)+0.3 -> 6.3123077 | G34: =(E34/0.7)+0.3 -> 5.8828571 | H34: =(E34/0.75)+0.3 -> 5.5106667 | I34: =(E34/0.8)+0.3 -> 5.185 | J34: 12 | K34: 8 LB. | M34: PART | N34: STANDARD | O34: LIST | P34: Multiplier | U34: CARTON | V34: CARTON
B35: ZLP18251 | C35: 18x25x1 | D35: 9.52 | E35: =D35*$E$10 -> 3.808 | F35: =(E35/0.65)+0.3 -> 6.1584615 | G35: =(E35/0.7)+0.3 -> 5.74 | H35: =(E35/0.75)+0.3 -> 5.3773333 | I35: =(E35/0.8)+0.3 -> 5.06 | J35: 12 | K35: 11 LB. | M35: NUMBER | N35: SIZES | O35: PRICE | P35: 0.4 | Q35: 35% Margin | R35: 30% Margin | S35: 25% Margin | U35: QUANTITY | V35: WEIGHT
B36: ZLP18301 | C36: 18x30x1 | D36: 17.45 | E36: =D36*$E$10 -> 6.98 | F36: =(E36/0.65)+0.3 -> 11.038462 | G36: =(E36/0.7)+0.3 -> 10.271429 | H36: =(E36/0.75)+0.3 -> 9.6066667 | I36: =(E36/0.8)+0.3 -> 9.025 | J36: 12 | K36: 11 LB. | M36: ZLP12244 | N36: 12x24x4 | O36: 12.13 | P36: =O36*$P$35 -> 4.852 | Q36: =(P36/0.65)+0.3 -> 7.7646154 | R36: =(P36/0.7)+0.3 -> 7.2314286 | S36: =(P36/0.75)+0.3 -> 6.7693333 | U36: 6 | V36: 8 LB.
B37: ZLP20201 | C37: 20x20x1 | D37: 7.95 | E37: =D37*$E$10 -> 3.18 | F37: =(E37/0.65)+0.3 -> 5.1923077 | G37: =(E37/0.7)+0.3 -> 4.8428571 | H37: =(E37/0.75)+0.3 -> 4.54 | I37: =(E37/0.8)+0.3 -> 4.275 | J37: 12 | K37: 7 LB. | M37: ZLP16204 | N37: 16x20x4 | O37: 13.02 | P37: =O37*$P$35 -> 5.208 | Q37: =(P37/0.65)+0.3 -> 8.3123077 | R37: =(P37/0.7)+0.3 -> 7.74 | S37: =(P37/0.75)+0.3 -> 7.244 | U37: 6 | V37: 9 LB.
B38: ZLP20221 | C38: 20x22x1 | D38: 14.62 | E38: =D38*$E$10 -> 5.848 | F38: =(E38/0.65)+0.3 -> 9.2969231 | G38: =(E38/0.7)+0.3 -> 8.6542857 | H38: =(E38/0.75)+0.3 -> 8.0973333 | I38: =(E38/0.8)+0.3 -> 7.61 | J38: 12 | K38: 8 LB. | M38: ZLP16244 | N38: 16x24x4 | O38: 16.96 | P38: =O38*$P$35 -> 6.784 | Q38: =(P38/0.65)+0.3 -> 10.736923 | R38: =(P38/0.7)+0.3 -> 9.9914286 | S38: =(P38/0.75)+0.3 -> 9.3453333 | U38: 6 | V38: 11 LB.
B39: ZLP20241 | C39: 20x24x1 | D39: 9.31 | E39: =D39*$E$10 -> 3.724 | F39: =(E39/0.65)+0.3 -> 6.0292308 | G39: =(E39/0.7)+0.3 -> 5.62 | H39: =(E39/0.75)+0.3 -> 5.2653333 | I39: =(E39/0.8)+0.3 -> 4.955 | J39: 12 | K39: 9 LB. | M39: ZLP16254 | N39: 16x25x4 | O39: 13.99 | P39: =O39*$P$35 -> 5.596 | Q39: =(P39/0.65)+0.3 -> 8.9092308 | R39: =(P39/0.7)+0.3 -> 8.2942857 | S39: =(P39/0.75)+0.3 -> 7.7613333 | U39: 6 | V39: 11 LB.
B40: ZLP20251 | C40: 20x25x1 | D40: 9.09 | E40: =D40*$E$10 -> 3.636 | F40: =(E40/0.65)+0.3 -> 5.8938462 | G40: =(E40/0.7)+0.3 -> 5.4942857 | H40: =(E40/0.75)+0.3 -> 5.148 | I40: =(E40/0.8)+0.3 -> 4.845 | J40: 12 | K40: 9 LB. | M40: ZLP18244 | N40: 18x24x4 | O40: 16.15 | P40: =O40*$P$35 -> 6.46 | Q40: =(P40/0.65)+0.3 -> 10.238462 | R40: =(P40/0.7)+0.3 -> 9.5285714 | S40: =(P40/0.75)+0.3 -> 8.9133333 | U40: 6 | V40: 11 LB.
B41: ZLP20301 | C41: 20x30x1 | D41: 11.85 | E41: =D41*$E$10 -> 4.74 | F41: =(E41/0.65)+0.3 -> 7.5923077 | G41: =(E41/0.7)+0.3 -> 7.0714286 | H41: =(E41/0.75)+0.3 -> 6.62 | I41: =(E41/0.8)+0.3 -> 6.225 | J41: 12 | K41: 10 LB. | M41: ZLP20204 | N41: 20x20x4 | O41: 13.92 | P41: =O41*$P$35 -> 5.568 | Q41: =(P41/0.65)+0.3 -> 8.8661538 | R41: =(P41/0.7)+0.3 -> 8.2542857 | S41: =(P41/0.75)+0.3 -> 7.724 | U41: 6 | V41: 11 LB.
B42: ZLP22221 | C42: 22x22x1 | D42: 16.29 | E42: =D42*$E$10 -> 6.516 | F42: =(E42/0.65)+0.3 -> 10.324615 | G42: =(E42/0.7)+0.3 -> 9.6085714 | H42: =(E42/0.75)+0.3 -> 8.988 | I42: =(E42/0.8)+0.3 -> 8.445 | J42: 12 | K42: 8 LB. | M42: ZLP20244 | N42: 20x24x4 | O42: 16.08 | P42: =O42*$P$35 -> 6.432 | Q42: =(P42/0.65)+0.3 -> 10.195385 | R42: =(P42/0.7)+0.3 -> 9.4885714 | S42: =(P42/0.75)+0.3 -> 8.876 | U42: 6 | V42: 13 LB.
B43: ZLP24241 | C43: 24x24x1 | D43: 10.3 | E43: =D43*$E$10 -> 4.12 | F43: =(E43/0.65)+0.3 -> 6.6384615 | G43: =(E43/0.7)+0.3 -> 6.1857143 | H43: =(E43/0.75)+0.3 -> 5.7933333 | I43: =(E43/0.8)+0.3 -> 5.45 | J43: 12 | K43: 10 LB. | M43: ZLP20254 | N43: 20x25x4 | O43: 15.99 | P43: =O43*$P$35 -> 6.396 | Q43: =(P43/0.65)+0.3 -> 10.14 | R43: =(P43/0.7)+0.3 -> 9.4371429 | S43: =(P43/0.75)+0.3 -> 8.828 | U43: 6 | V43: 13 LB.
B44: ZLP24301 | C44: 24x30x1 | D44: 19.25 | E44: =D44*$E$10 -> 7.7 | F44: =(E44/0.65)+0.3 -> 12.146154 | G44: =(E44/0.7)+0.3 -> 11.3 | H44: =(E44/0.75)+0.3 -> 10.566667 | I44: =(E44/0.8)+0.3 -> 9.925 | J44: 12 | K44: 14 LB. | M44: ZLP24244 | N44: 24x24x4 | O44: 18.29 | P44: =O44*$P$35 -> 7.316 | Q44: =(P44/0.65)+0.3 -> 11.555385 | R44: =(P44/0.7)+0.3 -> 10.751429 | S44: =(P44/0.75)+0.3 -> 10.054667 | U44: 6 | V44: 14 LB.
B45: ZLP25251 | C45: 25x25x1 | D45: 11.55 | E45: =D45*$E$10 -> 4.62 | F45: =(E45/0.65)+0.3 -> 7.4076923 | G45: =(E45/0.7)+0.3 -> 6.9 | H45: =(E45/0.75)+0.3 -> 6.46 | I45: =(E45/0.8)+0.3 -> 6.075 | J45: 12 | K45: 14 LB. | M45: Semi-Standard Sizes | Q45: =(P45/0.65)+0.3 -> 0.3 | R45: =(P45/0.7)+0.3 -> 0.3 | S45: =(P45/0.75)+0.3 -> 0.3
M46: ZLP25294 | N46: 25x29x4 | O46: 23.62 | P46: 23.62 | Q46: =(P46/0.65)+0.3 -> 36.638462 | R46: =(P46/0.7)+0.3 -> 34.042857 | S46: =(P46/0.75)+0.3 -> 31.793333 | U46: 6 | V46: 11 LB.
M47: ZLP28304 | N47: 28x30x4 | O47: 30.91 | P47: 30.91 | Q47: =(P47/0.65)+0.3 -> 47.853846 | R47: =(P47/0.7)+0.3 -> 44.457143 | S47: =(P47/0.75)+0.3 -> 41.513333 | U47: 6 | V47: 22 LB.

Sheet ZLP2
M2: SIZES | N2: H | O2: L | P2: W | Q2: TOTAL | R2: PRICE 1" | S2: PRICE 2" | T2: PRICE 4" | Y2: PRICE 1" | Z2: PRICE 2" | AA2: PRICE 4"
C3: AFC COST | D3: 35% Margin | E3: 30% Margin | F3: 25% Margin | N3: 13 | O3: 27 | P3: 1 | Q3: =N3*O3 -> 351 | R3: =_xlfn.XLOOKUP($N$3*$O$3, $D$11:$D$20, $I$11:$I$20, $I$10, -1) -> 13.599231 | S3: =_xlfn.XLOOKUP(N3*O3, $D$11:$D$20, $S$11:$S$20, $S$10, -1) -> 14.852308 | T3: =_xlfn.XLOOKUP(N3*O3, $D$11:$D$20, $AB$11:$AB$20, $AB$10, -1) -> 29.619231 | U3: 0.35 | Y3: =IF(OR(AND($N$3>28, $O$3>28), $N$3>35, $O$3>35),_xlfn.XLOOKUP(($N$3*$O$3)/2, $D$11:$D$20, $I$11:$I$20, $I$10, -1) * 2,"N/A") -> N/A | Z3: =IF(OR(AND($N$3>28, $O$3>28), $N$3>35, $O$3>35),_xlfn.XLOOKUP(($N$3*$O$3)/2, $D$11:$D$20, $S$11:$S$20, $S$10, -1) * 2,"N/A") -> N/A | AA3: =IF(OR(AND($N$3>28, $O$3>28), $N$3>35, $O$3>35),_xlfn.XLOOKUP(($N$3*$O$3)/2, $D$11:$D$20, $AB$11:$AB$20, $AB$10, -1) * 2,"N/A") -> N/A | AB3: 0.35
Q4: 77 | R4: =_xlfn.XLOOKUP($N$3*$O$3, $D$10:$D$20, $J$10:$J$20, $J$10, -1) -> 12.649286 | S4: =_xlfn.XLOOKUP($N$3*$O$3, $D$10:$D$20, $T$10:$T$20, $T$10, -1) -> 13.812857 | T4: =_xlfn.XLOOKUP($N$3*$O$3, $D$10:$D$20, $AC$10:$AC$20, $AC$10, -1) -> 27.525 | U4: 0.3 | Y4: =IF(OR(AND($N$3>28, $O$3>28), $N$3>35, $O$3>35),_xlfn.XLOOKUP(($N$3*$O$3)/2, $D$11:$D$20, $J$11:$J$20, $J$10, -1) * 2,"N/A") -> N/A | Z4: =IF(OR(AND($N$3>28, $O$3>28), $N$3>35, $O$3>35),_xlfn.XLOOKUP(($N$3*$O$3)/2, $D$11:$D$20, $T$11:$T$20, $T$10, -1) * 2,"N/A") -> N/A | AA4: =IF(OR(AND($N$3>28, $O$3>28), $N$3>35, $O$3>35),_xlfn.XLOOKUP(($N$3*$O$3)/2, $D$11:$D$20, $AC$11:$AC$20, $AC$10, -1) * 2,"N/A") -> N/A | AB4: 0.3
C5: The Z-Line Series | R5: =_xlfn.XLOOKUP($N$3*$O$3, $D$10:$D$20, $K$10:$K$20, $K$10, -1) -> 11.826 | S5: =_xlfn.XLOOKUP($N$3*$O$3, $D$10:$D$20, $U$10:$U$20, $U$10, -1) -> 12.912 | T5: =_xlfn.XLOOKUP($N$3*$O$3, $D$10:$D$20, $AD$10:$AD$20, $AD$10, -1) -> 25.71 | U5: 0.25 | Y5: =IF(OR(AND($N$3>28, $O$3>28), $N$3>35, $O$3>35),_xlfn.XLOOKUP(($N$3*$O$3)/2, $D$11:$D$20, $K$11:$K$20, $K$10, -1) * 2,"N/A") -> N/A | Z5: =IF(OR(AND($N$3>28, $O$3>28), $N$3>35, $O$3>35),_xlfn.XLOOKUP(($N$3*$O$3)/2, $D$11:$D$20, $U$11:$U$20, $U$10, -1) * 2,"N/A") -> N/A | AA5: =IF(OR(AND($N$3>28, $O$3>28), $N$3>35, $O$3>35),_xlfn.XLOOKUP(($N$3*$O$3)/2, $D$11:$D$20, $AD$11:$AD$20, $AD$10, -1) * 2,"N/A") -> N/A | AB5: 0.25
C6: MADE-TO-ORDER SIZES | Y6: DOUBLE SIZE PRICING
C7: ZL 1 | M7: ZL 2 | V7: ZL 4
C8: Gross Area | F8: Part | G8: List | H8: Multiplier | M8: Gross Area | P8: Part | Q8: List | R8: Multiplier | V8: Gross Area | Y8: Part | Z8: List | AA8: Multiplier
C9: Square Inches | D9: inches h | E9: inches l | F9: Number | G9: Price | H9: 0.45 | I9: 0.35 | J9: 0.3 | K9: 0.25 | L9: 0.2 | M9: Square Inches | P9: Number | Q9: Price | R9: 0.45 | S9: 0.35 | T9: 0.3 | U9: 0.25 | V9: Square Inches | Y9: Number | Z9: Price | AA9: 0.45 | AB9: 0.35 | AC9: 0.3 | AD9: 0.25
C10: Less than 150 | D10: 0 | E10: 150 | F10: ZLPSP1A | G10: 11.65 | H10: =G10*$H$9 -> 5.2425 | I10: =(H10/0.65)+0.3 -> 8.3653846 | J10: =(H10/0.7)+0.3 -> 7.7892857 | K10: =(H10/0.75)+0.3 -> 7.29 | L10: =(H10/0.8)+0.3 -> 6.853125 | M10: Less than 150 | N10: 0 | O10: 150 | P10: ZLPSP2A | Q10: 13.57 | R10: =Q10*$R$9 -> 6.1065 | S10: =(R10/0.65)+0.3 -> 9.6946154 | T10: =(R10/0.7)+0.3 -> 9.0235714 | U10: =(R10/0.75)+0.3 -> 8.442 | V10: Less than 150 | W10: 0 | X10: 150 | Y10: ZLPSP4A | Z10: 27.05 | AA10: =Z10*$AA$9 -> 12.1725 | AB10: =(AA10/0.65)+0.3 -> 19.026923 | AC10: =(AA10/0.7)+0.3 -> 17.689286 | AD10: =(AA10/0.75)+0.3 -> 16.53 | AE10: =(AA10/0.8)+0.3 -> 15.515625
C11: 150-199 | D11: 150 | E11: 199 | F11: ZLPSP1B | G11: 13.79 | H11: =G11*$H$9 -> 6.2055 | I11: =(H11/0.65)+0.3 -> 9.8469231 | J11: =(H11/0.7)+0.3 -> 9.165 | K11: =(H11/0.75)+0.3 -> 8.574 | L11: =(H11/0.8)+0.3 -> 8.056875 | M11: 150-199 | N11: 150 | O11: 199 | P11: ZLPSP2B | Q11: 15.08 | R11: =Q11*$R$9 -> 6.786 | S11: =(R11/0.65)+0.3 -> 10.74 | T11: =(R11/0.7)+0.3 -> 9.9942857 | U11: =(R11/0.75)+0.3 -> 9.348 | V11: 150-199 | W11: 150 | X11: 199 | Y11: ZLPSP4B | Z11: 30.56 | AA11: =Z11*$AA$9 -> 13.752 | AB11: =(AA11/0.65)+0.3 -> 21.456923 | AC11: =(AA11/0.7)+0.3 -> 19.945714 | AD11: =(AA11/0.75)+0.3 -> 18.636
C12: 200-249 | D12: 200 | E12: 249 | F12: ZLPSP1C | G12: 15.47 | H12: =G12*$H$9 -> 6.9615 | I12: =(H12/0.65)+0.3 -> 11.01 | J12: =(H12/0.7)+0.3 -> 10.245 | K12: =(H12/0.75)+0.3 -> 9.582 | L12: =(H12/0.8)+0.3 -> 9.001875 | M12: 200-249 | N12: 200 | O12: 249 | P12: ZLPSP2C | Q12: 16.95 | R12: =Q12*$R$9 -> 7.6275 | S12: =(R12/0.65)+0.3 -> 12.034615 | T12: =(R12/0.7)+0.3 -> 11.196429 | U12: =(R12/0.75)+0.3 -> 10.47 | V12: 200-249 | W12: 200 | X12: 249 | Y12: ZLPSP4C | Z12: 34.09 | AA12: =Z12*$AA$9 -> 15.3405 | AB12: =(AA12/0.65)+0.3 -> 23.900769 | AC12: =(AA12/0.7)+0.3 -> 22.215 | AD12: =(AA12/0.75)+0.3 -> 20.754
C13: 250-299 | D13: 250 | E13: 299 | F13: ZLPSP1D | G13: 17.07 | H13: =G13*$H$9 -> 7.6815 | I13: =(H13/0.65)+0.3 -> 12.117692 | J13: =(H13/0.7)+0.3 -> 11.273571 | K13: =(H13/0.75)+0.3 -> 10.542 | L13: =(H13/0.8)+0.3 -> 9.901875 | M13: 250-299 | N13: 250 | O13: 299 | P13: ZLPSP2D | Q13: 18.68 | R13: =Q13*$R$9 -> 8.406 | S13: =(R13/0.65)+0.3 -> 13.232308 | T13: =(R13/0.7)+0.3 -> 12.308571 | U13: =(R13/0.75)+0.3 -> 11.508 | V13: 250-299 | W13: 250 | X13: 299 | Y13: ZLPSP4D | Z13: 37.57 | AA13: =Z13*$AA$9 -> 16.9065 | AB13: =(AA13/0.65)+0.3 -> 26.31 | AC13: =(AA13/0.7)+0.3 -> 24.452143 | AD13: =(AA13/0.75)+0.3 -> 22.842
C14: 300-399 | D14: 300 | E14: 399 | F14: ZLPSP1E | G14: 19.21 | H14: =G14*$H$9 -> 8.6445 | I14: =(H14/0.65)+0.3 -> 13.599231 | J14: =(H14/0.7)+0.3 -> 12.649286 | K14: =(H14/0.75)+0.3 -> 11.826 | L14: =(H14/0.8)+0.3 -> 11.105625 | M14: 300-399 | N14: 300 | O14: 399 | P14: ZLPSP2E | Q14: 21.02 | R14: =Q14*$R$9 -> 9.459 | S14: =(R14/0.65)+0.3 -> 14.852308 | T14: =(R14/0.7)+0.3 -> 13.812857 | U14: =(R14/0.75)+0.3 -> 12.912 | V14: 300-399 | W14: 300 | X14: 399 | Y14: ZLPSP4E | Z14: 42.35 | AA14: =Z14*$AA$9 -> 19.0575 | AB14: =(AA14/0.65)+0.3 -> 29.619231 | AC14: =(AA14/0.7)+0.3 -> 27.525 | AD14: =(AA14/0.75)+0.3 -> 25.71
C15: 400-499 | D15: 400 | E15: 499 | F15: ZLPSP1F | G15: 21.39 | H15: =G15*$H$9 -> 9.6255 | I15: =(H15/0.65)+0.3 -> 15.108462 | J15: =(H15/0.7)+0.3 -> 14.050714 | K15: =(H15/0.75)+0.3 -> 13.134 | L15: =(H15/0.8)+0.3 -> 12.331875 | M15: 400-499 | N15: 400 | O15: 499 | P15: ZLPSP2F | Q15: 23.38 | R15: =Q15*$R$9 -> 10.521 | S15: =(R15/0.65)+0.3 -> 16.486154 | T15: =(R15/0.7)+0.3 -> 15.33 | U15: =(R15/0.75)+0.3 -> 14.328 | V15: 400-499 | W15: 400 | X15: 499 | Y15: ZLPSP4F | Z15: 47 | AA15: =Z15*$AA$9 -> 21.15 | AB15: =(AA15/0.65)+0.3 -> 32.838462 | AC15: =(AA15/0.7)+0.3 -> 30.514286 | AD15: =(AA15/0.75)+0.3 -> 28.5
C16: 500-599 | D16: 500 | E16: 599 | F16: ZLPSP1G | G16: 22.95 | H16: =G16*$H$9 -> 10.3275 | I16: =(H16/0.65)+0.3 -> 16.188462 | J16: =(H16/0.7)+0.3 -> 15.053571 | K16: =(H16/0.75)+0.3 -> 14.07 | L16: =(H16/0.8)+0.3 -> 13.209375 | M16: 500-599 | N16: 500 | O16: 599 | P16: ZLPSP2G | Q16: 25.11 | R16: =Q16*$R$9 -> 11.2995 | S16: =(R16/0.65)+0.3 -> 17.683846 | T16: =(R16/0.7)+0.3 -> 16.442143 | U16: =(R16/0.75)+0.3 -> 15.366 | V16: 500-599 | W16: 500 | X16: 599 | Y16: ZLPSP4G | Z16: 50.5 | AA16: =Z16*$AA$9 -> 22.725 | AB16: =(AA16/0.65)+0.3 -> 35.261538 | AC16: =(AA16/0.7)+0.3 -> 32.764286 | AD16: =(AA16/0.75)+0.3 -> 30.6
C17: 600-699 | D17: 600 | E17: 699 | F17: ZLPSP1H | G17: 24.72 | H17: =G17*$H$9 -> 11.124 | I17: =(H17/0.65)+0.3 -> 17.413846 | J17: =(H17/0.7)+0.3 -> 16.191429 | K17: =(H17/0.75)+0.3 -> 15.132 | L17: =(H17/0.8)+0.3 -> 14.205 | M17: 600-699 | N17: 600 | O17: 699 | P17: ZLPSP2H | Q17: 27.02 | R17: =Q17*$R$9 -> 12.159 | S17: =(R17/0.65)+0.3 -> 19.006154 | T17: =(R17/0.7)+0.3 -> 17.67 | U17: =(R17/0.75)+0.3 -> 16.512 | V17: 600-699 | W17: 600 | X17: 699 | Y17: ZLPSP4H | Z17: 54.01 | AA17: =Z17*$AA$9 -> 24.3045 | AB17: =(AA17/0.65)+0.3 -> 37.691538 | AC17: =(AA17/0.7)+0.3 -> 35.020714 | AD17: =(AA17/0.75)+0.3 -> 32.706
C18: 700-799 | D18: 700 | E18: 799 | F18: ZLPSP1I | G18: 26.12 | H18: =G18*$H$9 -> 11.754 | I18: =(H18/0.65)+0.3 -> 18.383077 | J18: =(H18/0.7)+0.3 -> 17.091429 | K18: =(H18/0.75)+0.3 -> 15.972 | L18: =(H18/0.8)+0.3 -> 14.9925 | M18: 700-799 | N18: 700 | O18: 799 | P18: ZLPSP2I | Q18: 28.57 | R18: =Q18*$R$9 -> 12.8565 | S18: =(R18/0.65)+0.3 -> 20.079231 | T18: =(R18/0.7)+0.3 -> 18.666429 | U18: =(R18/0.75)+0.3 -> 17.442 | V18: 700-799 | W18: 700 | X18: 799 | Y18: ZLPSP4I | Z18: 58.33 | AA18: =Z18*$AA$9 -> 26.2485 | AB18: =(AA18/0.65)+0.3 -> 40.682308 | AC18: =(AA18/0.7)+0.3 -> 37.797857 | AD18: =(AA18/0.75)+0.3 -> 35.298
C19: 800-899 | D19: 800 | E19: 899 | F19: ZLPSP1J | G19: 28.72 | H19: =G19*$H$9 -> 12.924 | I19: =(H19/0.65)+0.3 -> 20.183077 | J19: =(H19/0.7)+0.3 -> 18.762857 | K19: =(H19/0.75)+0.3 -> 17.532 | L19: =(H19/0.8)+0.3 -> 16.455 | M19: 800-899 | N19: 800 | O19: 899 | P19: ZLPSP2J | Q19: 31.44 | R19: =Q19*$R$9 -> 14.148 | S19: =(R19/0.65)+0.3 -> 22.066154 | T19: =(R19/0.7)+0.3 -> 20.511429 | U19: =(R19/0.75)+0.3 -> 19.164 | V19: 800-899 | W19: 800 | X19: 899 | Y19: ZLPSP4J | Z19: 66.79 | AA19: =Z19*$AA$9 -> 30.0555 | AB19: =(AA19/0.65)+0.3 -> 46.539231 | AC19: =(AA19/0.7)+0.3 -> 43.236429 | AD19: =(AA19/0.75)+0.3 -> 40.374
C20: 900-999 | D20: 900 | E20: 999 | F20: ZLPSP1K | G20: 31.57 | H20: =G20*$H$9 -> 14.2065 | I20: =(H20/0.65)+0.3 -> 22.156154 | J20: =(H20/0.7)+0.3 -> 20.595 | K20: =(H20/0.75)+0.3 -> 19.242 | L20: =(H20/0.8)+0.3 -> 18.058125 | M20: 900-999 | N20: 900 | O20: 999 | P20: ZLPSP2K | Q20: 34.61 | R20: =Q20*$R$9 -> 15.5745 | S20: =(R20/0.65)+0.3 -> 24.260769 | T20: =(R20/0.7)+0.3 -> 22.549286 | U20: =(R20/0.75)+0.3 -> 21.066 | V20: 900-999 | W20: 900 | X20: 999 | Y20: ZLPSP4K | Z20: 73.46 | AA20: =Z20*$AA$9 -> 33.057 | AB20: =(AA20/0.65)+0.3 -> 51.156923 | AC20: =(AA20/0.7)+0.3 -> 47.524286 | AD20: =(AA20/0.75)+0.3 -> 44.376
C22: * MINIMUM: | P22: * DOUBLE SIZE: Z-Line ZL pleated filters
P23: If both dimensions are larger that 28, or if either dimension is larger than 35, it is considered a double size filter.
C24: 12 Per size; Less than 12 per size add +40% to each filter. | P24: To figure the price on a double size ZL, calculate 1/2 of the square inches for the desired size and then double the list price. The maximum length dimension is 96.
C25: Made to order filters are bulk packed.
C26: * The minimum dimensions of a special size is 4 x 4.
C28: * OPTIONS: For higher efficiency media use the following to calculate list price: | P28: * DOUBLE SIZE: Z-Line Optional 65%, 85% & 95% pleated filters.
P29: Optional Made to Order 65%, 85% & 95% filters are if both dimensions are larger than 24 3/4, or if either dimension is larger than 35 it is considered a double size filter. To figure the price on a double size size optional efficiency, calculate 1/2 of the square inches for the desired size and double the list price.
C30: a) 65% Filters: take list price x 2.75 for standard or special sizes.
C31: b) 85% Filters: take list price x 4.35 for standard or special sizes. | P31: *Note. Insert sizes in their appropiate size cells, use the result based on the depth (width) inches
C32: c) 95% Filters: take list price x 4.75 for standard or special sizes.
Q41: 83280.26 | R41: 6940.0217 | T41: 83280.26 | U41: 6940.0217 | AA41: 83280.26 | AB41: 20820.065
Q42: =Q41-R41 -> 76340.238 | R42: 6940.0217 | T42: =T41-U41 -> 76340.238 | U42: 6940.0217 | AA42: =AA41-AB41 -> 62460.195 | AB42: 20820.065
Q43: =Q42-R42 -> 69400.217 | R43: 6940.0217 | T43: =T42-U42 -> 69400.217 | U43: 6940.0217 | AA43: =AA42-AB42 -> 41640.13 | AB43: 20820.065
Q44: =Q43-R43 -> 62460.195 | R44: 6940.0217 | T44: =T43-U43 -> 62460.195 | U44: 6940.0217 | AA44: =AA43-AB43 -> 20820.065 | AB44: 20820.065
Q45: =Q44-R44 -> 55520.173 | R45: 6940.0217 | T45: =T44-U44 -> 55520.173 | U45: 6940.0217
Q46: =Q45-R45 -> 48580.152 | R46: 6940.0217 | T46: =T45-U45 -> 48580.152 | U46: 6940.0217 | AA46: cent
Q47: =Q46-R46 -> 41640.13 | R47: 6940.0217 | T47: =T46-U46 -> 41640.13 | U47: 6940.0217 | AA47: 78677.14 | AB47: 19669.285
Q48: =Q47-R47 -> 34700.108 | R48: 6940.0217 | T48: =T47-U47 -> 34700.108 | U48: 6940.0217 | AA48: =AA47-AB47 -> 59007.855 | AB48: 19669.285
Q49: =Q48-R48 -> 27760.087 | R49: 6940.0217 | T49: =T48-U48 -> 27760.087 | U49: 6940.0217 | AA49: =AA48-AB48 -> 39338.57 | AB49: 19669.285
Q50: =Q49-R49 -> 20820.065 | R50: 6940.0217 | T50: =T49-U49 -> 20820.065 | U50: 6940.0217 | AA50: =AA49-AB49 -> 19669.285 | AB50: 19669.285
Q51: =Q50-R50 -> 13880.043 | R51: 6940.0217 | T51: =T50-U50 -> 13880.043 | U51: 6940.0217
Q52: =Q51-R51 -> 6940.0217 | R52: 6940.0217 | T52: =T51-U51 -> 6940.0217 | U52: 6940.0217 | AA52: gg
Q53: =Q52-R52 -> -1.2732926e-11 | R53: 6940.0217 | T53: =T52-U52 -> -1.2732926e-11 | U53: 6940.0217 | AA53: 36985.64 | AB53: 9246.41
AA54: =AA53-$AB$53 -> 27739.23 | AB54: 9246.41
AA55: =AA54-$AB$53 -> 18492.82 | AB55: 9246.41
AA56: =AA55-$AB$53 -> 9246.41 | AB56: 9246.41
AA58: hbh
AA59: 47974.95 | AB59: 11993.737
AA60: =AA59-AB59 -> 35981.212 | AB60: 11993.737
AA61: =AA60-AB60 -> 23987.475 | AB61: 11993.737
AA62: =AA61-AB61 -> 11993.737 | AB62: 11993.737
AA64: 49012.21 | AB64: 12253.052
AA65: =AA64-AB64 -> 36759.158 | AB65: 12253.052
AA66: =AA65-AB65 -> 24506.105 | AB66: 12253.052
AA67: =AA66-AB66 -> 12253.053 | AB67: 12253.052
AA69: 18064.85 | AB69: 4516.2125
AA70: =AA69-AB69 -> 13548.637 | AB70: 4516.2125
AA71: =AA70-AB70 -> 9032.425 | AB71: 4516.2125
AA72: =AA71-AB71 -> 4516.2125 | AB72: 4516.2125

Sheet HVP1
V1: List Price Sheet 6HV-W
P2: 46143
C3: AFC COST | D3: 35% Margin | E3: 30% Margin | F3: 25% Margin | V3: Section 6
V4: Product Bulletin 6 ZLINE
B6: The Z-Line Series HV
B8: PART # | C8: 1 STANDARD | D8: LIST | E8: Multiplier | J8: CTN | K8: CTN | M8: PART # | N8: 2 STANDARD | O8: LIST | P8: Multiplier | U8: CTN | V8: CTN
C9: SIZES | D9: PRICE | E9: 0.34 | F9: 35% Margin | G9: 30% Margin | H9: 25% Margin | J9: QTY | K9: WT | N9: SIZES | O9: PRICE | P9: 0.34 | Q9: 35% Margin | R9: 30% Margin | S9: 25% Margin | T9: 20% Margin | U9: QTY | V9: WT
B10: HVP10101 | C10: 10x10x1 | D10: 9.09 | E10: =D10*$E$9 -> 3.0906 | F10: =(E10/0.65)+0.3 -> 5.0547692 | G10: =(E10/0.7)+0.3 -> 4.7151429 | H10: =(E10/0.75)+0.3 -> 4.4208 | I10: =(E10/0.8)+0.3 -> 4.16325 | J10: 12 | K10: 5 LB. | M10: HVP10202 | N10: 10x20x2 | O10: 11.38 | P10: =O10*$P$9 -> 3.8692 | Q10: =(P10/0.65)+0.3 -> 6.2526154 | R10: =(P10/0.7)+0.3 -> 5.8274286 | S10: =(P10/0.75)+0.3 -> 5.4589333 | T10: =(P10/0.8)+0.3 -> 5.1365 | U10: 12 | V10: 10 LB.
B11: HVP10201 | C11: 10x20x1 | D11: 9.58 | E11: =D11*$E$9 -> 3.2572 | F11: =(E11/0.65)+0.3 -> 5.3110769 | G11: =(E11/0.7)+0.3 -> 4.9531429 | H11: =(E11/0.75)+0.3 -> 4.6429333 | I11: =(E11/0.8)+0.3 -> 4.3715 | J11: 12 | K11: 7 LB. | M11: HVP12122 | N11: 12x12x2 | O11: 11.87 | P11: =O11*$P$9 -> 4.0358 | Q11: =(P11/0.65)+0.3 -> 6.5089231 | R11: =(P11/0.7)+0.3 -> 6.0654286 | S11: =(P11/0.75)+0.3 -> 5.6810667 | T11: =(P11/0.8)+0.3 -> 5.34475 | U11: 12 | V11: 9 LB.
B12: HVP10241 | C12: 10x24x1 | D12: 16.36 | E12: =D12*$E$9 -> 5.5624 | F12: =(E12/0.65)+0.3 -> 8.8575385 | G12: =(E12/0.7)+0.3 -> 8.2462857 | H12: =(E12/0.75)+0.3 -> 7.7165333 | I12: =(E12/0.8)+0.3 -> 7.253 | J12: 12 | K12: 8 LB. | M12: HVP12202 | N12: 12x20x2 | O12: 12.06 | P12: =O12*$P$9 -> 4.1004 | Q12: =(P12/0.65)+0.3 -> 6.6083077 | R12: =(P12/0.7)+0.3 -> 6.1577143 | S12: =(P12/0.75)+0.3 -> 5.7672 | T12: =(P12/0.8)+0.3 -> 5.4255 | U12: 12 | V12: 11 LB.
B13: HVP10301 | C13: 10x30x1 | D13: 16.73 | E13: =D13*$E$9 -> 5.6882 | F13: =(E13/0.65)+0.3 -> 9.0510769 | G13: =(E13/0.7)+0.3 -> 8.426 | H13: =(E13/0.75)+0.3 -> 7.8842667 | I13: =(E13/0.8)+0.3 -> 7.41025 | J13: 12 | K13: 8 LB. | M13: HVP12242 | N13: 12x24x2 | O13: 11.35 | P13: =O13*$P$9 -> 3.859 | Q13: =(P13/0.65)+0.3 -> 6.2369231 | R13: =(P13/0.7)+0.3 -> 5.8128571 | S13: =(P13/0.75)+0.3 -> 5.4453333 | T13: =(P13/0.8)+0.3 -> 5.12375 | U13: 12 | V13: 10 LB.
B14: HVP12121 | C14: 12x12x1 | D14: 11.62 | E14: =D14*$E$9 -> 3.9508 | F14: =(E14/0.65)+0.3 -> 6.3781538 | G14: =(E14/0.7)+0.3 -> 5.944 | H14: =(E14/0.75)+0.3 -> 5.5677333 | I14: =(E14/0.8)+0.3 -> 5.2385 | J14: 12 | K14: 5 LB. | M14: HVP14202 | N14: 14x20x2 | O14: 11.55 | P14: =O14*$P$9 -> 3.927 | Q14: =(P14/0.65)+0.3 -> 6.3415385 | R14: =(P14/0.7)+0.3 -> 5.91 | S14: =(P14/0.75)+0.3 -> 5.536 | T14: =(P14/0.8)+0.3 -> 5.20875 | U14: 12 | V14: 10 LB.
B15: HVP12201 | C15: 12x20x1 | D15: 9.83 | E15: =D15*$E$9 -> 3.3422 | F15: =(E15/0.65)+0.3 -> 5.4418462 | G15: =(E15/0.7)+0.3 -> 5.0745714 | H15: =(E15/0.75)+0.3 -> 4.7562667 | I15: =(E15/0.8)+0.3 -> 4.47775 | J15: 12 | K15: 8 LB. | M15: HVP14252 | N15: 14x25x2 | O15: 12.64 | P15: =O15*$P$9 -> 4.2976 | Q15: =(P15/0.65)+0.3 -> 6.9116923 | R15: =(P15/0.7)+0.3 -> 6.4394286 | S15: =(P15/0.75)+0.3 -> 6.0301333 | T15: =(P15/0.8)+0.3 -> 5.672 | U15: 12 | V15: 13 LB.
B16: HVP12241 | C16: 12x24x1 | D16: 10.08 | E16: =D16*$E$9 -> 3.4272 | F16: =(E16/0.65)+0.3 -> 5.5726154 | G16: =(E16/0.7)+0.3 -> 5.196 | H16: =(E16/0.75)+0.3 -> 4.8696 | I16: =(E16/0.8)+0.3 -> 4.584 | J16: 12 | K16: 7 LB. | M16: HVP15202 | N16: 15x20x2 | O16: 11.95 | P16: =O16*$P$9 -> 4.063 | Q16: =(P16/0.65)+0.3 -> 6.5507692 | R16: =(P16/0.7)+0.3 -> 6.1042857 | S16: =(P16/0.75)+0.3 -> 5.7173333 | T16: =(P16/0.8)+0.3 -> 5.37875 | U16: 12 | V16: 11 LB.
B17: HVP12251 | C17: 12x25x1 | D17: 10.79 | E17: =D17*$E$9 -> 3.6686 | F17: =(E17/0.65)+0.3 -> 5.944 | G17: =(E17/0.7)+0.3 -> 5.5408571 | H17: =(E17/0.75)+0.3 -> 5.1914667 | I17: =(E17/0.8)+0.3 -> 4.88575 | J17: 12 | K17: 7 LB. | M17: HVP16162 | N17: 16x16x2 | O17: 15.38 | P17: =O17*$P$9 -> 5.2292 | Q17: =(P17/0.65)+0.3 -> 8.3449231 | R17: =(P17/0.7)+0.3 -> 7.7702857 | S17: =(P17/0.75)+0.3 -> 7.2722667 | T17: =(P17/0.8)+0.3 -> 6.8365 | U17: 12 | V17: 12 LB.
B18: HVP12301 | C18: 12x30x1 | D18: 16.73 | E18: =D18*$E$9 -> 5.6882 | F18: =(E18/0.65)+0.3 -> 9.0510769 | G18: =(E18/0.7)+0.3 -> 8.426 | H18: =(E18/0.75)+0.3 -> 7.8842667 | I18: =(E18/0.8)+0.3 -> 7.41025 | J18: 12 | K18: 8 LB. | M18: HVP16202 | N18: 16x20x2 | O18: 11.48 | P18: =O18*$P$9 -> 3.9032 | Q18: =(P18/0.65)+0.3 -> 6.3049231 | R18: =(P18/0.7)+0.3 -> 5.876 | S18: =(P18/0.75)+0.3 -> 5.5042667 | T18: =(P18/0.8)+0.3 -> 5.179 | U18: 12 | V18: 12 LB.
B19: HVP14141 | C19: 14x14x1 | D19: 12.01 | E19: =D19*$E$9 -> 4.0834 | F19: =(E19/0.65)+0.3 -> 6.5821538 | G19: =(E19/0.7)+0.3 -> 6.1334286 | H19: =(E19/0.75)+0.3 -> 5.7445333 | I19: =(E19/0.8)+0.3 -> 5.40425 | J19: 12 | K19: 6 LB. | M19: HVP16242 | N19: 16x24x2 | O19: 14.71 | P19: =O19*$P$9 -> 5.0014 | Q19: =(P19/0.65)+0.3 -> 7.9944615 | R19: =(P19/0.7)+0.3 -> 7.4448571 | S19: =(P19/0.75)+0.3 -> 6.9685333 | T19: =(P19/0.8)+0.3 -> 6.55175 | U19: 12 | V19: 14 LB.
B20: HVP14201 | C20: 14x20x1 | D20: 10.26 | E20: =D20*$E$9 -> 3.4884 | F20: =(E20/0.65)+0.3 -> 5.6667692 | G20: =(E20/0.7)+0.3 -> 5.2834286 | H20: =(E20/0.75)+0.3 -> 4.9512 | I20: =(E20/0.8)+0.3 -> 4.6605 | J20: 12 | K20: 7 LB. | M20: HVP16252 | N20: 16x25x2 | O20: 13.24 | P20: =O20*$P$9 -> 4.5016 | Q20: =(P20/0.65)+0.3 -> 7.2255385 | R20: =(P20/0.7)+0.3 -> 6.7308571 | S20: =(P20/0.75)+0.3 -> 6.3021333 | T20: =(P20/0.8)+0.3 -> 5.927 | U20: 12 | V20: 14 LB.
B21: HVP14241 | C21: 14x24x1 | D21: 16.61 | E21: =D21*$E$9 -> 5.6474 | F21: =(E21/0.65)+0.3 -> 8.9883077 | G21: =(E21/0.7)+0.3 -> 8.3677143 | H21: =(E21/0.75)+0.3 -> 7.8298667 | I21: =(E21/0.8)+0.3 -> 7.35925 | J21: 12 | K21: 8 LB. | M21: HVP18182 | N21: 18x18x2 | O21: 19.13 | P21: =O21*$P$9 -> 6.5042 | Q21: =(P21/0.65)+0.3 -> 10.306462 | R21: =(P21/0.7)+0.3 -> 9.5917143 | S21: =(P21/0.75)+0.3 -> 8.9722667 | T21: =(P21/0.8)+0.3 -> 8.43025 | U21: 12 | V21: 12 LB.
... B30: HVP16301 | C30: 16x30x1 | D30: 18.08 | E30: =D30*$E$9 -> 6.1472 | F30: =(E30/0.65)+0.3 -> 9.7572308 | G30: =(E30/0.7)+0.3 -> 9.0817143 | H30: =(E30/0.75)+0.3 -> 8.4962667 | I30: =(E30/0.8)+0.3 -> 7.984 | J30: 12 | K30: 9 LB. | M30: HVP25252 | N30: 25x25x2 | O30: 20.79 | P30: =O30*$P$9 -> 7.0686 | Q30: =(P30/0.65)+0.3 -> 11.174769 | R30: =(P30/0.7)+0.3 -> 10.398 | S30: =(P30/0.75)+0.3 -> 9.7248 | T30: =(P30/0.8)+0.3 -> 9.13575 | U30: 12 | V30: 21 LB.
B31: HVP18181 | C31: 18x18x1 | D31: 16.73 | E31: =D31*$E$9 -> 5.6882 | F31: =(E31/0.65)+0.3 -> 9.0510769 | G31: =(E31/0.7)+0.3 -> 8.426 | H31: =(E31/0.75)+0.3 -> 7.8842667 | I31: =(E31/0.8)+0.3 -> 7.41025 | J31: 12 | K31: 7 LB.
B32: HVP18201 | C32: 18x20x1 | D32: 15.3 | E32: =D32*$E$9 -> 5.202 | F32: =(E32/0.65)+0.3 -> 8.3030769 | G32: =(E32/0.7)+0.3 -> 7.7314286 | H32: =(E32/0.75)+0.3 -> 7.236 | I32: =(E32/0.8)+0.3 -> 6.8025 | J32: 12 | K32: 11 LB.
B33: HVP18241 | C33: 18x24x1 | D33: 12.58 | E33: =D33*$E$9 -> 4.2772 | F33: =(E33/0.65)+0.3 -> 6.8803077 | G33: =(E33/0.7)+0.3 -> 6.4102857 | H33: =(E33/0.75)+0.3 -> 6.0029333 | I33: =(E33/0.8)+0.3 -> 5.6465 | J33: 12 | K33: 9 LB. | M33: PART # | N33: 4 STANDARD | O33: LIST | P33: Multiplier | U33: CTN | V33: CTN
B34: HVP18251 | C34: 18x25x1 | D34: 12.57 | E34: =D34*$E$9 -> 4.2738 | F34: =(E34/0.65)+0.3 -> 6.8750769 | G34: =(E34/0.7)+0.3 -> 6.4054286 | H34: =(E34/0.75)+0.3 -> 5.9984 | I34: =(E34/0.8)+0.3 -> 5.64225 | J34: 12 | K34: 12 LB. | N34: SIZES | O34: PRICE | P34: 0.34 | Q34: 35% Margin | R34: 30% Margin | S34: 25% Margin | T34: 20% Margin | U34: QTY | V34: WT
B35: HVP18301 | C35: 18x30x1 | D35: 19.96 | E35: =D35*$E$9 -> 6.7864 | F35: =(E35/0.65)+0.3 -> 10.740615 | G35: =(E35/0.7)+0.3 -> 9.9948571 | H35: =(E35/0.75)+0.3 -> 9.3485333 | I35: =(E35/0.8)+0.3 -> 8.783 | J35: 12 | K35: 9 LB. | M35: HVP12244 | N35: 12x24x4 | O35: 19.73 | P35: =O35*$P$34 -> 6.7082 | Q35: =(P35/0.65)+0.3 -> 10.620308 | R35: =(P35/0.7)+0.3 -> 9.8831429 | S35: =(P35/0.75)+0.3 -> 9.2442667 | T35: =(P35/0.8)+0.3 -> 8.68525 | U35: 6 | V35: 9 LB.
B36: HVP20201 | C36: 20x20x1 | D36: 10.99 | E36: =D36*$E$9 -> 3.7366 | F36: =(E36/0.65)+0.3 -> 6.0486154 | G36: =(E36/0.7)+0.3 -> 5.638 | H36: =(E36/0.75)+0.3 -> 5.2821333 | I36: =(E36/0.8)+0.3 -> 4.97075 | J36: 12 | K36: 8 LB. | M36: HVP16204 | N36: 16x20x4 | O36: 19.71 | P36: =O36*$P$34 -> 6.7014 | Q36: =(P36/0.65)+0.3 -> 10.609846 | R36: =(P36/0.7)+0.3 -> 9.8734286 | S36: =(P36/0.75)+0.3 -> 9.2352 | T36: =(P36/0.8)+0.3 -> 8.67675 | U36: 6 | V36: 10 LB.
B37: HVP20221 | C37: 20x22x1 | D37: 16.73 | E37: =D37*$E$9 -> 5.6882 | F37: =(E37/0.65)+0.3 -> 9.0510769 | G37: =(E37/0.7)+0.3 -> 8.426 | H37: =(E37/0.75)+0.3 -> 7.8842667 | I37: =(E37/0.8)+0.3 -> 7.41025 | J37: 12 | K37: 8 LB. | M37: HVP16254 | N37: 16x25x4 | O37: 22.96 | P37: =O37*$P$34 -> 7.8064 | Q37: =(P37/0.65)+0.3 -> 12.309846 | R37: =(P37/0.7)+0.3 -> 11.452 | S37: =(P37/0.75)+0.3 -> 10.708533 | T37: =(P37/0.8)+0.3 -> 10.058 | U37: 6 | V37: 12 LB.
B38: HVP20241 | C38: 20x24x1 | D38: 12.48 | E38: =D38*$E$9 -> 4.2432 | F38: =(E38/0.65)+0.3 -> 6.828 | G38: =(E38/0.7)+0.3 -> 6.3617143 | H38: =(E38/0.75)+0.3 -> 5.9576 | I38: =(E38/0.8)+0.3 -> 5.604 | J38: 12 | K38: 9 LB. | M38: HVP18244 | N38: 18x24x4 | O38: 25.15 | P38: =O38*$P$34 -> 8.551 | Q38: =(P38/0.65)+0.3 -> 13.455385 | R38: =(P38/0.7)+0.3 -> 12.515714 | S38: =(P38/0.75)+0.3 -> 11.701333 | T38: =(P38/0.8)+0.3 -> 10.98875 | U38: 6 | V38: 13 LB.
B39: HVP20251 | C39: 20x25x1 | D39: 12.21 | E39: =D39*$E$9 -> 4.1514 | F39: =(E39/0.65)+0.3 -> 6.6867692 | G39: =(E39/0.7)+0.3 -> 6.2305714 | H39: =(E39/0.75)+0.3 -> 5.8352 | I39: =(E39/0.8)+0.3 -> 5.48925 | J39: 12 | K39: 9 LB. | M39: HVP20204 | N39: 20x20x4 | O39: 23.51 | P39: =O39*$P$34 -> 7.9934 | Q39: =(P39/0.65)+0.3 -> 12.597538 | R39: =(P39/0.7)+0.3 -> 11.719143 | S39: =(P39/0.75)+0.3 -> 10.957867 | T39: =(P39/0.8)+0.3 -> 10.29175 | U39: 6 | V39: 11 LB.
B40: HVP20301 | C40: 20x30x1 | D40: 16.46 | E40: =D40*$E$9 -> 5.5964 | F40: =(E40/0.65)+0.3 -> 8.9098462 | G40: =(E40/0.7)+0.3 -> 8.2948571 | H40: =(E40/0.75)+0.3 -> 7.7618667 | I40: =(E40/0.8)+0.3 -> 7.2955 | J40: 12 | K40: 10 LB. | M40: HVP20244 | N40: 20x24x4 | O40: 26.57 | P40: =O40*$P$34 -> 9.0338 | Q40: =(P40/0.65)+0.3 -> 14.198154 | R40: =(P40/0.7)+0.3 -> 13.205429 | S40: =(P40/0.75)+0.3 -> 12.345067 | T40: =(P40/0.8)+0.3 -> 11.59225 | U40: 6 | V40: 14 LB.
B41: HVP22221 | C41: 22x22x1 | D41: 18.62 | E41: =D41*$E$9 -> 6.3308 | F41: =(E41/0.65)+0.3 -> 10.039692 | G41: =(E41/0.7)+0.3 -> 9.344 | H41: =(E41/0.75)+0.3 -> 8.7410667 | I41: =(E41/0.8)+0.3 -> 8.2135 | J41: 12 | K41: 8 LB. | M41: HVP20254 | N41: 20x25x4 | O41: 26.16 | P41: =O41*$P$34 -> 8.8944 | Q41: =(P41/0.65)+0.3 -> 13.983692 | R41: =(P41/0.7)+0.3 -> 13.006286 | S41: =(P41/0.75)+0.3 -> 12.1592 | T41: =(P41/0.8)+0.3 -> 11.418 | U41: 6 | V41: 13 LB.
B42: HVP24241 | C42: 24x24x1 | D42: 14.26 | E42: =D42*$E$9 -> 4.8484 | F42: =(E42/0.65)+0.3 -> 7.7590769 | G42: =(E42/0.7)+0.3 -> 7.2262857 | H42: =(E42/0.75)+0.3 -> 6.7645333 | I42: =(E42/0.8)+0.3 -> 6.3605 | J42: 12 | K42: 11 LB. | M42: HVP24244 | N42: 24x24x4 | O42: 29.76 | P42: =O42*$P$34 -> 10.1184 | Q42: =(P42/0.65)+0.3 -> 15.866769 | R42: =(P42/0.7)+0.3 -> 14.754857 | S42: =(P42/0.75)+0.3 -> 13.7912 | T42: =(P42/0.8)+0.3 -> 12.948 | U42: 6 | V42: 16 LB.
B43: HVP24301 | C43: 24x30x1 | D43: 22.06 | E43: =D43*$E$9 -> 7.5004 | F43: =(E43/0.65)+0.3 -> 11.839077 | G43: =(E43/0.7)+0.3 -> 11.014857 | H43: =(E43/0.75)+0.3 -> 10.300533 | I43: =(E43/0.8)+0.3 -> 9.6755 | J43: 12 | K43: 15 LB. | M43: Semi-Std. Sizes
B44: HVP25251 | C44: 25x25x1 | D44: 15.32 | E44: =D44*$E$9 -> 5.2088 | F44: =(E44/0.65)+0.3 -> 8.3135385 | G44: =(E44/0.7)+0.3 -> 7.7411429 | H44: =(E44/0.75)+0.3 -> 7.2450667 | I44: =(E44/0.8)+0.3 -> 6.811 | J44: 12 | K44: 15 LB. | M44: HVP25294 | N44: 25x29x4 | O44: 36.22 | U44: 6 | V44: 12 LB.
N45: (24 1/2x28 1/2) | O45: 0 | P45: 14.49
M46: HVP28304 | N46: 28x30x4 | O46: 47.45 | P46: 18.98 | U46: 6 | V46: 23 LB.
M47: Peripheral header available on: 12x24x4 & 24x24x4;
M48: placed on the air entering side
M49: Add +35% to List Price. Add HDR to the end of
M50: Part Number; minimum of 12 per size.
M53: PART # | N53: 6 STANDARD | O53: LIST | P53: Multiplier | U53: CTN | V53: CTN
N54: SIZES | O54: PRICE | P54: 1 | U54: QTY | V54: WT
M55: HVP12246 | N55: 12x24x6 | O55: 27.22 | P55: 27.22 | U55: 4 | V55: 16 LB.
M56: HVP16206 | N56: 16x20x6 | O56: 27.22 | P56: 27.22 | U56: 4 | V56: 7 LB.
M57: HVP16256 | N57: 16x25x6 | O57: 31.7 | P57: 31.7 | U57: 4 | V57: 8 LB.
M58: HVP18246 | N58: 18x24x6 | O58: 34.73 | P58: 34.73 | U58: 4 | V58: 8 LB.
M59: HVP20206 | N59: 20x20x6 | O59: 32.45 | P59: 32.45 | U59: 4 | V59: 7 LB.
M60: HVP20246 | N60: 20x24x6 | O60: 36.66 | P60: 36.66 | U60: 4 | V60: 10 LB.
M61: HVP20256 | N61: 20x25x6 | O61: 36.12 | P61: 36.12 | U61: 4 | V61: 10 LB.
M62: HVP24246 | N62: 24x24x6 | O62: 41.09 | P62: 41.09 | U62: 4 | V62: 11 LB.

Sheet HVP2
H2: SIZES | I2: H | J2: L | K2: W | L2: TOTAL | M2: PRICE 1" | N2: PRICE 2" | O2: PRICE 4" | R2: PRICE 1" | S2: PRICE 2" | T2: PRICE 4"
C3: AFC COST | D3: 35% Margin | E3: 30% Margin | F3: 25% Margin | I3: 16 | J3: 33 | K3: 1 | L3: =I3*J3 -> 528 | M3: =_xlfn.XLOOKUP($I$3*$J$3, $C$11:$C$21, $H$11:$H$21, $H$11, -1) -> 18.473077 | N3: =_xlfn.XLOOKUP(I3*J3, $C$11:$C$21, $S$11:$S$21, $S$11, -1) -> 21.588462 | O3: =_xlfn.XLOOKUP(I3*J3, $C$24:$C$34, $H$24:$H$34, $H$24, -1) -> 40.772308 | P3: 0.35 | R3: =IF(OR(AND($I$3>28, $J$3>28), $I$3>35, $J$3>35),_xlfn.XLOOKUP(($I$3*$J$3)/2, $C$11:$C$21, $H$11:$H$21, $H$11, -1) * 2,"N/A") -> N/A | S3: =IF(OR(AND($I$3>28, $J$3>28), $I$3>35, $J$3>35),_xlfn.XLOOKUP(($I$3*$J$3)/2, $C$11:$C$21, $S$11:$S$21, $S$11, -1) * 2,"N/A") -> N/A | T3: =IF(OR(AND($I$3>28, $J$3>28), $I$3>35, $J$3>35),_xlfn.XLOOKUP(($I$3*$J$3)/2, $C$11:$C$21, $H$24:$H$34, $H$24, -1) * 2,"N/A") -> N/A | U3: 0.35
M4: =_xlfn.XLOOKUP($I$3*$J$3, $C$11:$C$21, $I$11:$I$21, $I$11, -1) -> 17.175 | N4: =_xlfn.XLOOKUP($I$3*$J$3, $C$11:$C$21, $T$11:$T$21, $T$11, -1) -> 20.067857 | O4: =_xlfn.XLOOKUP($I$3*$J$3, $C$11:$C$21, $I$24:$I$34, $I$24, -1) -> 37.881429 | P4: 0.3 | R4: =IF(OR(AND($I$3>28, $J$3>28), $I$3>35, $J$3>35),_xlfn.XLOOKUP(($I$3*$J$3)/2, $C$11:$C$21, $I$11:$I$21, $I$11, -1) * 2,"N/A") -> N/A | S4: =IF(OR(AND($I$3>28, $J$3>28), $I$3>35, $J$3>35),_xlfn.XLOOKUP(($I$3*$J$3)/2, $C$11:$C$21, $T$11:$T$21, $T$11, -1) * 2,"N/A") -> N/A | T4: =IF(OR(AND($I$3>28, $J$3>28), $I$3>35, $J$3>35),_xlfn.XLOOKUP(($I$3*$J$3)/2, $C$11:$C$21, $I$24:$I$34, $I$24, -1) * 2,"N/A") -> N/A | U4: 0.3
M5: =_xlfn.XLOOKUP($I$3*$J$3, $C$11:$C$21, $J$11:$J$21, $J$11, -1) -> 16.05 | N5: =_xlfn.XLOOKUP($I$3*$J$3, $C$11:$C$21, $U$11:$U$21, $U$11, -1) -> 18.75 | O5: =_xlfn.XLOOKUP($I$3*$J$3, $C$11:$C$21, $J$24:$J$34, $J$24, -1) -> 35.376 | P5: 0.25 | R5: =IF(OR(AND($I$3>28, $J$3>28), $I$3>35, $J$3>35),_xlfn.XLOOKUP(($I$3*$J$3)/2, $C$11:$C$21, $J$11:$J$21, $J$11, -1) * 2,"N/A") -> N/A | S5: =IF(OR(AND($I$3>28, $J$3>28), $I$3>35, $J$3>35),_xlfn.XLOOKUP(($I$3*$J$3)/2, $C$11:$C$21, $U$11:$U$21, $U$11, -1) * 2,"N/A") -> N/A | T5: =IF(OR(AND($I$3>28, $J$3>28), $I$3>35, $J$3>35),_xlfn.XLOOKUP(($I$3*$J$3)/2, $C$11:$C$21, $J$24:$J$34, $J$24, -1) * 2,"N/A") -> N/A | U5: 0.25
B6: The Z-Line Series | R6: DOUBLE SIZE PRICING
B7: MADE-TO-ORDER SIZES
B8: HV 1 | G8: Multiplier
B9: Gross Area | E9: Part | F9: List | G9: 0.45
B10: Square Inches | E10: Number | F10: Price | G10: AFC COST | H10: 35% Margin | I10: 30% Margin | J10: 25% Margin | M10: HV 2 | R10: AFC COST | S10: 35% Margin | T10: 30% Margin | U10: 25% Margin | V10: 20% Margin
B11: Less than 150 | C11: 0 | D11: 150 | E11: HVPSP1A | F11: 13.36 | G11: =F11*$G$9 -> 6.012 | H11: =(G11/0.65)+0.3 -> 9.5492308 | I11: =(G11/0.7)+0.3 -> 8.8885714 | J11: =(G11/0.75)+0.3 -> 8.316 | K11: =(G11/0.8)+0.3 -> 7.815 | M11: Less than 150 | N11: 0 | O11: 150 | P11: HVPSP2A | Q11: 16.03 | R11: =Q11*$G$9 -> 7.2135 | S11: =(R11/0.65)+0.3 -> 11.397692 | T11: =(R11/0.7)+0.3 -> 10.605 | U11: =(R11/0.75)+0.3 -> 9.918 | V11: =(R11/0.8)+0.3 -> 9.316875
B12: 150-199 | C12: 150 | D12: 199 | E12: HVPSP1B | F12: 15.76 | G12: =F12*$G$9 -> 7.092 | H12: =(G12/0.65)+0.3 -> 11.210769 | I12: =(G12/0.7)+0.3 -> 10.431429 | J12: =(G12/0.75)+0.3 -> 9.756 | K12: =(G12/0.8)+0.3 -> 9.165 | M12: 150-199 | N12: {=_xlfn.TEXTSPLIT(M12,"-")} -> 150 | O12: 199 | P12: HVPSP2B | Q12: 18.44 | R12: =Q12*$G$9 -> 8.298 | S12: =(R12/0.65)+0.3 -> 13.066154 | T12: =(R12/0.7)+0.3 -> 12.154286 | U12: =(R12/0.75)+0.3 -> 11.364 | V12: =(R12/0.8)+0.3 -> 10.6725
B13: 200-249 | C13: 200 | D13: 249 | E13: HVPSP1C | F13: 17.77 | G13: =F13*$G$9 -> 7.9965 | H13: =(G13/0.65)+0.3 -> 12.602308 | I13: =(G13/0.7)+0.3 -> 11.723571 | J13: =(G13/0.75)+0.3 -> 10.962 | K13: =(G13/0.8)+0.3 -> 10.295625 | M13: 200-249 | N13: {=_xlfn.TEXTSPLIT(M13,"-")} -> 200 | O13: 249 | P13: HVPSP2C | Q13: 20.8 | R13: =Q13*$G$9 -> 9.36 | S13: =(R13/0.65)+0.3 -> 14.7 | T13: =(R13/0.7)+0.3 -> 13.671429 | U13: =(R13/0.75)+0.3 -> 12.78 | V13: =(R13/0.8)+0.3 -> 12
B14: 250-299 | C14: 250 | D14: 299 | E14: HVPSP1D | F14: 19.6 | G14: =F14*$G$9 -> 8.82 | H14: =(G14/0.65)+0.3 -> 13.869231 | I14: =(G14/0.7)+0.3 -> 12.9 | J14: =(G14/0.75)+0.3 -> 12.06 | K14: =(G14/0.8)+0.3 -> 11.325 | M14: 250-299 | N14: {=_xlfn.TEXTSPLIT(M14,"-")} -> 250 | O14: 299 | P14: HVPSP2D | Q14: 22.9 | R14: =Q14*$G$9 -> 10.305 | S14: =(R14/0.65)+0.3 -> 16.153846 | T14: =(R14/0.7)+0.3 -> 15.021429 | U14: =(R14/0.75)+0.3 -> 14.04 | V14: =(R14/0.8)+0.3 -> 13.18125
B15: 300-399 | C15: 300 | D15: 399 | E15: HVPSP1E | F15: 22.04 | G15: =F15*$G$9 -> 9.918 | H15: =(G15/0.65)+0.3 -> 15.558462 | I15: =(G15/0.7)+0.3 -> 14.468571 | J15: =(G15/0.75)+0.3 -> 13.524 | K15: =(G15/0.8)+0.3 -> 12.6975 | M15: 300-399 | N15: {=_xlfn.TEXTSPLIT(M15,"-")} -> 300 | O15: 399 | P15: HVPSP2E | Q15: 25.8 | R15: =Q15*$G$9 -> 11.61 | S15: =(R15/0.65)+0.3 -> 18.161538 | T15: =(R15/0.7)+0.3 -> 16.885714 | U15: =(R15/0.75)+0.3 -> 15.78 | V15: =(R15/0.8)+0.3 -> 14.8125
B16: 400-499 | C16: 400 | D16: 499 | E16: HVPSP1F | F16: 24.48 | G16: =F16*$G$9 -> 11.016 | H16: =(G16/0.65)+0.3 -> 17.247692 | I16: =(G16/0.7)+0.3 -> 16.037143 | J16: =(G16/0.75)+0.3 -> 14.988 | K16: =(G16/0.8)+0.3 -> 14.07 | M16: 400-499 | N16: {=_xlfn.TEXTSPLIT(M16,"-")} -> 400 | O16: 499 | P16: HVPSP2F | Q16: 28.67 | R16: =Q16*$G$9 -> 12.9015 | S16: =(R16/0.65)+0.3 -> 20.148462 | T16: =(R16/0.7)+0.3 -> 18.730714 | U16: =(R16/0.75)+0.3 -> 17.502 | V16: =(R16/0.8)+0.3 -> 16.426875
B17: 500-599 | C17: 500 | D17: 599 | E17: HVPSP1G | F17: 26.25 | G17: =F17*$G$9 -> 11.8125 | H17: =(G17/0.65)+0.3 -> 18.473077 | I17: =(G17/0.7)+0.3 -> 17.175 | J17: =(G17/0.75)+0.3 -> 16.05 | K17: =(G17/0.8)+0.3 -> 15.065625 | M17: 500-599 | N17: {=_xlfn.TEXTSPLIT(M17,"-")} -> 500 | O17: 599 | P17: HVPSP2G | Q17: 30.75 | R17: =Q17*$G$9 -> 13.8375 | S17: =(R17/0.65)+0.3 -> 21.588462 | T17: =(R17/0.7)+0.3 -> 20.067857 | U17: =(R17/0.75)+0.3 -> 18.75 | V17: =(R17/0.8)+0.3 -> 17.596875
B18: 600-699 | C18: 600 | D18: 699 | E18: HVPSP1H | F18: 28.25 | G18: =F18*$G$9 -> 12.7125 | H18: =(G18/0.65)+0.3 -> 19.857692 | I18: =(G18/0.7)+0.3 -> 18.460714 | J18: =(G18/0.75)+0.3 -> 17.25 | K18: =(G18/0.8)+0.3 -> 16.190625 | M18: 600-699 | N18: {=_xlfn.TEXTSPLIT(M18,"-")} -> 600 | O18: 699 | P18: HVPSP2H | Q18: 33.04 | R18: =Q18*$G$9 -> 14.868 | S18: =(R18/0.65)+0.3 -> 23.173846 | T18: =(R18/0.7)+0.3 -> 21.54 | U18: =(R18/0.75)+0.3 -> 20.124 | V18: =(R18/0.8)+0.3 -> 18.885
B19: 700-799 | C19: 700 | D19: 799 | E19: HVPSP1I | F19: 29.92 | G19: =F19*$G$9 -> 13.464 | H19: =(G19/0.65)+0.3 -> 21.013846 | I19: =(G19/0.7)+0.3 -> 19.534286 | J19: =(G19/0.75)+0.3 -> 18.252 | K19: =(G19/0.8)+0.3 -> 17.13 | M19: 700-799 | N19: {=_xlfn.TEXTSPLIT(M19,"-")} -> 700 | O19: 799 | P19: HVPSP2I | Q19: 34.96 | R19: =Q19*$G$9 -> 15.732 | S19: =(R19/0.65)+0.3 -> 24.503077 | T19: =(R19/0.7)+0.3 -> 22.774286 | U19: =(R19/0.75)+0.3 -> 21.276 | V19: =(R19/0.8)+0.3 -> 19.965
B20: 800-899 | C20: 800 | D20: 899 | E20: HVPSP1J | F20: 32.88 | G20: =F20*$G$9 -> 14.796 | H20: =(G20/0.65)+0.3 -> 23.063077 | I20: =(G20/0.7)+0.3 -> 21.437143 | J20: =(G20/0.75)+0.3 -> 20.028 | K20: =(G20/0.8)+0.3 -> 18.795 | M20: 800-899 | N20: {=_xlfn.TEXTSPLIT(M20,"-")} -> 800 | O20: 899 | P20: HVPSP2J | Q20: 38.48 | R20: =Q20*$G$9 -> 17.316 | S20: =(R20/0.65)+0.3 -> 26.94 | T20: =(R20/0.7)+0.3 -> 25.037143 | U20: =(R20/0.75)+0.3 -> 23.388 | V20: =(R20/0.8)+0.3 -> 21.945
B21: 900-999 | C21: 900 | D21: 999 | E21: HVPSP1K | F21: 36.16 | G21: =F21*$G$9 -> 16.272 | H21: =(G21/0.65)+0.3 -> 25.333846 | I21: =(G21/0.7)+0.3 -> 23.545714 | J21: =(G21/0.75)+0.3 -> 21.996 | K21: =(G21/0.8)+0.3 -> 20.64 | M21: 900-999 | N21: {=_xlfn.TEXTSPLIT(M21,"-")} -> 900 | O21: 999 | P21: HVPSP2K | Q21: 42.29 | R21: =Q21*$G$9 -> 19.0305 | S21: =(R21/0.65)+0.3 -> 29.577692 | T21: =(R21/0.7)+0.3 -> 27.486429 | U21: =(R21/0.75)+0.3 -> 25.674 | V21: =(R21/0.8)+0.3 -> 24.088125
B23: HV 4 | G23: AFC COST | H23: 35% Margin | I23: 30% Margin | J23: 25% Margin
B24: Square Inches | C24: 0 | D24: 150 | E24: HVPSP4A | F24: 31.31 | G24: =F24*$G$9 -> 14.0895 | H24: =(G24/0.65)+0.3 -> 21.976154 | I24: =(G24/0.7)+0.3 -> 20.427857 | J24: =(G24/0.75)+0.3 -> 19.086 | K24: =(G24/0.8)+0.3 -> 17.911875
B25: 150-199 | C25: 150 | D25: 199 | E25: HVPSP4B | F25: 35.38 | G25: =F25*$G$9 -> 15.921 | H25: =(G25/0.65)+0.3 -> 24.793846 | I25: =(G25/0.7)+0.3 -> 23.044286 | J25: =(G25/0.75)+0.3 -> 21.528 | K25: =(G25/0.8)+0.3 -> 20.20125
B26: 200-249 | C26: 200 | D26: 249 | E26: HVPSP4C | F26: 39.43 | G26: =F26*$G$9 -> 17.7435 | H26: =(G26/0.65)+0.3 -> 27.597692 | I26: =(G26/0.7)+0.3 -> 25.647857 | J26: =(G26/0.75)+0.3 -> 23.958 | K26: =(G26/0.8)+0.3 -> 22.479375
B27: 250-299 | C27: 250 | D27: 299 | E27: HVPSP4D | F27: 43.49 | G27: =F27*$G$9 -> 19.5705 | H27: =(G27/0.65)+0.3 -> 30.408462 | I27: =(G27/0.7)+0.3 -> 28.257857 | J27: =(G27/0.75)+0.3 -> 26.394 | K27: =(G27/0.8)+0.3 -> 24.763125
B28: 300-399 | C28: 300 | D28: 399 | E28: HVPSP4E | F28: 49.05 | G28: =F28*$G$9 -> 22.0725 | H28: =(G28/0.65)+0.3 -> 34.257692 | I28: =(G28/0.7)+0.3 -> 31.832143 | J28: =(G28/0.75)+0.3 -> 29.73 | K28: =(G28/0.8)+0.3 -> 27.890625
B29: 400-499 | C29: 400 | D29: 499 | E29: HVPSP4F | F29: 54.49 | G29: =F29*$G$9 -> 24.5205 | H29: =(G29/0.65)+0.3 -> 38.023846 | I29: =(G29/0.7)+0.3 -> 35.329286 | J29: =(G29/0.75)+0.3 -> 32.994 | K29: =(G29/0.8)+0.3 -> 30.950625
B30: 500-599 | C30: 500 | D30: 599 | E30: HVPSP4G | F30: 58.46 | G30: =F30*$G$9 -> 26.307 | H30: =(G30/0.65)+0.3 -> 40.772308 | I30: =(G30/0.7)+0.3 -> 37.881429 | J30: =(G30/0.75)+0.3 -> 35.376 | K30: =(G30/0.8)+0.3 -> 33.18375
B31: 600-699 | C31: 600 | D31: 699 | E31: HVPSP4H | F31: 62.52 | G31: =F31*$G$9 -> 28.134 | H31: =(G31/0.65)+0.3 -> 43.583077 | I31: =(G31/0.7)+0.3 -> 40.491429 | J31: =(G31/0.75)+0.3 -> 37.812 | K31: =(G31/0.8)+0.3 -> 35.4675
B32: 700-799 | C32: 700 | D32: 799 | E32: HVPSP4I | F32: 66.92 | G32: =F32*$G$9 -> 30.114 | H32: =(G32/0.65)+0.3 -> 46.629231 | I32: =(G32/0.7)+0.3 -> 43.32 | J32: =(G32/0.75)+0.3 -> 40.452 | K32: =(G32/0.8)+0.3 -> 37.9425
B33: 800-899 | C33: 800 | D33: 899 | E33: HVPSP4J | F33: 73.63 | G33: =F33*$G$9 -> 33.1335 | H33: =(G33/0.65)+0.3 -> 51.274615 | I33: =(G33/0.7)+0.3 -> 47.633571 | J33: =(G33/0.75)+0.3 -> 44.478 | K33: =(G33/0.8)+0.3 -> 41.716875
B34: 900-999 | C34: 900 | D34: 999 | E34: HVPSP4K | F34: 81.04 | G34: =F34*$G$9 -> 36.468 | H34: =(G34/0.65)+0.3 -> 56.404615 | I34: =(G34/0.7)+0.3 -> 52.397143 | J34: =(G34/0.75)+0.3 -> 48.924 | K34: =(G34/0.8)+0.3 -> 45.885
L42: montclair
L43: 0 | M43: 0
L44: 962-2ply | M44: 32
L45: F8V4-2424-GWB | M45: 13
L46: FP 200 | M46: 8
L47: FP-H13HEPA-2424115-WG | M47: 5
L48: HVP10241 | M48: 188
B49: MINIMUM: | L49: HVP16202 | M49: 8 | Q49: la palma
B50: 12 Per size; Less than 12 per size add +40% to each filter. | L50: HVP16242 | M50: 16
B51: Made to order filters are bulk packed. | L51: HVP16252 | M51: 16 | Z51: {=_xlfn.UNIQUE('[1]MAIN BUILDING'!H6:H221)} -> ZLP15202 | AA51: =SUMIF('[1]MAIN BUILDING'!$H$6:$H$221,Z51,'[1]MAIN BUILDING'!$L$6:$L$221) -> #VALUE!
B52: *The minimum size of special size HV pleats is 4 x 4. | L52: HVP18181 | M52: 8 | Z52: F8V4-2424-GWB | AA52: =SUMIF('[1]MAIN BUILDING'!$H$6:$H$221,Z52,'[1]MAIN BUILDING'!$L$6:$L$221) -> #VALUE!
B53: DOUBLE SIZE: | L53: HVP18242 | M53: 24 | R53: 2027-2028 | V53: 2026-2027 | Z53: 0 | AA53: =SUMIF('[1]MAIN BUILDING'!$H$6:$H$221,Z53,'[1]MAIN BUILDING'!$L$6:$L$221) -> #VALUE!
B54: If both dimensions are larger than 28, or if either dimension is larger | L54: HVP20201 | M54: 12 | R54: 36985.64 | V54: 31112.28 | W54: =R54-V54 -> 5873.36 | Z54: ZLP20252 | AA54: =SUMIF('[1]MAIN BUILDING'!$H$6:$H$221,Z54,'[1]MAIN BUILDING'!$L$6:$L$221) -> #VALUE!
B55: than 35 it is considered a double size filter. To figure the price on a | L55: HVP20202 | M55: 96 | R55: 47974.95 | V55: 46982.99 | W55: =R55-V55 -> 991.96 | Z55: ZLP14302 | AA55: =SUMIF('[1]MAIN BUILDING'!$H$6:$H$221,Z55,'[1]MAIN BUILDING'!$L$6:$L$221) -> #VALUE!
B56: double size HV, calculate 1/2 of the square inches for the desired size | L56: HVP20242 | M56: 36 | R56: 78676.14 | V56: 77740.83 | W56: =R56-V56 -> 935.31 | Z56: ZLP16242 | AA56: =SUMIF('[1]MAIN BUILDING'!$H$6:$H$221,Z56,'[1]MAIN BUILDING'!$L$6:$L$221) -> #VALUE!
B57: and then double the list price. The maximum length dimension is 96. | L57: HVP20244 | M57: 32 | R57: 48766.21 | V57: 47621.56 | W57: =R57-V57 -> 1144.65 | Z57: F8V4-1224-GWB | AA57: =SUMIF('[1]MAIN BUILDING'!$H$6:$H$221,Z57,'[1]MAIN BUILDING'!$L$6:$L$221) -> #VALUE!
L58: HVP20252 | M58: 56 | R58: 18064.85 | V58: 18122.1 | W58: =R58-V58 -> -57.25 | Z58: ZLP16252 | AA58: =SUMIF('[1]MAIN BUILDING'!$H$6:$H$221,Z58,'[1]MAIN BUILDING'!$L$6:$L$221) -> #VALUE!
B59: 6 Special-Size HV Pleats: add 55% to the 4 list price. | L59: HVP20254 | M59: 16 | R59: 32813.89 | V59: 32184.42 | W59: =R59-V59 -> 629.47 | Z59: ZLP16202 | AA59: =SUMIF('[1]MAIN BUILDING'!$H$6:$H$221,Z59,'[1]MAIN BUILDING'!$L$6:$L$221) -> #VALUE!
L60: HVP24241 | M60: 8 | Q60: WA | R60: 46975.27 | V60: 42071.65 | W60: =R60-V60 -> 4903.62 | Z60: ZLP20202 | AA60: =SUMIF('[1]MAIN BUILDING'!$H$6:$H$221,Z60,'[1]MAIN BUILDING'!$L$6:$L$221) -> #VALUE!
L61: HVP24242 | M61: 48 | R61: 36885.85 | V61: 34193.1 | W61: =R61-V61 -> 2692.75 | Z61: PUPSLRB242449O | AA61: =SUMIF('[1]MAIN BUILDING'!$H$6:$H$221,Z61,'[1]MAIN BUILDING'!$L$6:$L$221) -> #VALUE!
L62: HVP-SPECIAL | M62: 12 | R62: 13798.51 | V62: 13374.81 | W62: =R62-V62 -> 423.7 | Z62: PUPSLRB122449O | AA62: =SUMIF('[1]MAIN BUILDING'!$H$6:$H$221,Z62,'[1]MAIN BUILDING'!$L$6:$L$221) -> #VALUE!
L63: SBG202021-95 | M63: 16 | R63: 11939.98 | V63: 11239.91 | W63: =R63-V63 -> 700.07 | Z63: ZLP24242 | AA63: =SUMIF('[1]MAIN BUILDING'!$H$6:$H$221,Z63,'[1]MAIN BUILDING'!$L$6:$L$221) -> #VALUE!
L64: SBG202421-95 | M64: 12 | R64: 17697.5 | V64: 17516.95 | W64: =R64-V64 -> 180.55 | Z64: ZLP1201 | AA64: =SUMIF('[1]MAIN BUILDING'!$H$6:$H$221,Z64,'[1]MAIN BUILDING'!$L$6:$L$221) -> #VALUE!
L65: SMP-98AT20252 | M65: 8 | R65: 14415.47 | V65: 14042.11 | W65: =R65-V65 -> 373.36 | Z65: ZLP16162 | AA65: =SUMIF('[1]MAIN BUILDING'!$H$6:$H$221,Z65,'[1]MAIN BUILDING'!$L$6:$L$221) -> #VALUE!
Z66: ZLP20204 | AA66: =SUMIF('[1]MAIN BUILDING'!$H$6:$H$221,Z66,'[1]MAIN BUILDING'!$L$6:$L$221) -> #VALUE!
Z67: F8V4GL-2424-GWB | AA67: =SUMIF('[1]MAIN BUILDING'!$H$6:$H$221,Z67,'[1]MAIN BUILDING'!$L$6:$L$221) -> #VALUE!
Z68: ZLP18312SP | AA68: =SUMIF('[1]MAIN BUILDING'!$H$6:$H$221,Z68,'[1]MAIN BUILDING'!$L$6:$L$221) -> #VALUE!
Z69: ZLP20201 | AA69: =SUMIF('[1]MAIN BUILDING'!$H$6:$H$221,Z69,'[1]MAIN BUILDING'!$L$6:$L$221) -> #VALUE!
Z70: ZLP-SPECIAL | AA70: =SUMIF('[1]MAIN BUILDING'!$H$6:$H$221,Z70,'[1]MAIN BUILDING'!$L$6:$L$221) -> #VALUE!
Z71: ZLP12162 | AA71: =SUMIF('[1]MAIN BUILDING'!$H$6:$H$221,Z71,'[1]MAIN BUILDING'!$L$6:$L$221) -> #VALUE!

Sheet MR11 1
T1: List Price Sheet 6MR11-Z
S2: 46143
C3: AFC COST | D3: 35% Margin | E3: 30% Margin | F3: 25% Margin | T3: Section 6
T4: Product Bulletin 6 MR11
B7: The Z-Line Series MR-11
C9: 1 | M9: 2
B10: PART | C10: STANDARD | D10: LIST | E10: Multiplier | I10: CARTON | J10: CARTON | L10: PART | M10: STANDARD | N10: LIST | O10: Multiplier | S10: CARTON | T10: CARTON
B11: NUMBER | C11: SIZES | D11: PRICE | E11: 0.34 | F11: 35% Margin | G11: 30% Margin | H11: 25% Margin | I11: QUANTITY | J11: WEIGHT | L11: NUMBER | M11: SIZES | N11: PRICE | O11: 0.34 | P11: 35% Margin | Q11: 30% Margin | R11: 25% Margin | S11: QUANTITY | T11: WEIGHT
B12: M1110101 | C12: 10x10x1 | D12: 13.83 | E12: =D12*$E$11 -> 4.7022 | F12: =(E12/0.65)+0.3 -> 7.5341538 | G12: =(E12/0.7)+0.3 -> 7.0174286 | H12: =(E12/0.75)+0.3 -> 6.5696 | I12: 12 | J12: 3 LB. | L12: M1110202 | M12: 10x20x2 | N12: 14.98 | O12: =N12*$O$11 -> 5.0932 | P12: =(O12/0.65)+0.3 -> 8.1356923 | Q12: =(O12/0.7)+0.3 -> 7.576 | R12: =(O12/0.75)+0.3 -> 7.0909333 | S12: 12 | T12: 8 LB.
B13: M1110201 | C13: 10x20x1 | D13: 14.55 | E13: =D13*$E$11 -> 4.947 | F13: =(E13/0.65)+0.3 -> 7.9107692 | G13: =(E13/0.7)+0.3 -> 7.3671429 | H13: =(E13/0.75)+0.3 -> 6.896 | I13: 12 | J13: 5 LB. | L13: M1112122 | M13: 12x12x2 | N13: 15.48 | O13: =N13*$O$11 -> 5.2632 | P13: =(O13/0.65)+0.3 -> 8.3972308 | Q13: =(O13/0.7)+0.3 -> 7.8188571 | R13: =(O13/0.75)+0.3 -> 7.3176 | S13: 12 | T13: 6 LB.
B14: M1110241 | C14: 10x24x1 | D14: 21.25 | E14: =D14*$E$11 -> 7.225 | F14: =(E14/0.65)+0.3 -> 11.415385 | G14: =(E14/0.7)+0.3 -> 10.621429 | H14: =(E14/0.75)+0.3 -> 9.9333333 | I14: 12 | J14: 6 LB. | L14: M1112202 | M14: 12x20x2 | N14: 15.88 | O14: =N14*$O$11 -> 5.3992 | P14: =(O14/0.65)+0.3 -> 8.6064615 | Q14: =(O14/0.7)+0.3 -> 8.0131429 | R14: =(O14/0.75)+0.3 -> 7.4989333 | S14: 12 | T14: 9 LB.
B15: M1110301 | C15: 10x30x1 | D15: 21.75 | E15: =D15*$E$11 -> 7.395 | F15: =(E15/0.65)+0.3 -> 11.676923 | G15: =(E15/0.7)+0.3 -> 10.864286 | H15: =(E15/0.75)+0.3 -> 10.16 | I15: 12 | J15: 8 LB. | L15: M1112242 | M15: 12x24x2 | N15: 15.11 | O15: =N15*$O$11 -> 5.1374 | P15: =(O15/0.65)+0.3 -> 8.2036923 | Q15: =(O15/0.7)+0.3 -> 7.6391429 | R15: =(O15/0.75)+0.3 -> 7.1498667 | S15: 12 | T15: 11 LB.
B16: M1112121 | C16: 12x12x1 | D16: 15.71 | E16: =D16*$E$11 -> 5.3414 | F16: =(E16/0.65)+0.3 -> 8.5175385 | G16: =(E16/0.7)+0.3 -> 7.9305714 | H16: =(E16/0.75)+0.3 -> 7.4218667 | I16: 12 | J16: 4 LB. | L16: M1114202 | M16: 14x20x2 | N16: 15.48 | O16: =N16*$O$11 -> 5.2632 | P16: =(O16/0.65)+0.3 -> 8.3972308 | Q16: =(O16/0.7)+0.3 -> 7.8188571 | R16: =(O16/0.75)+0.3 -> 7.3176 | S16: 12 | T16: 11 LB.
B17: M1112201 | C17: 12x20x1 | D17: 14.98 | E17: =D17*$E$11 -> 5.0932 | F17: =(E17/0.65)+0.3 -> 8.1356923 | G17: =(E17/0.7)+0.3 -> 7.576 | H17: =(E17/0.75)+0.3 -> 7.0909333 | I17: 12 | J17: 6 LB. | L17: M1114252 | M17: 14x25x2 | N17: 16.81 | O17: =N17*$O$11 -> 5.7154 | P17: =(O17/0.65)+0.3 -> 9.0929231 | Q17: =(O17/0.7)+0.3 -> 8.4648571 | R17: =(O17/0.75)+0.3 -> 7.9205333 | S17: 12 | T17: 12 LB.
B18: M1112241 | C18: 12x24x1 | D18: 13.65 | E18: =D18*$E$11 -> 4.641 | F18: =(E18/0.65)+0.3 -> 7.44 | G18: =(E18/0.7)+0.3 -> 6.93 | H18: =(E18/0.75)+0.3 -> 6.488 | I18: 12 | J18: 7 LB. | L18: M1115202 | M18: 15x20x2 | N18: 15.98 | O18: =N18*$O$11 -> 5.4332 | P18: =(O18/0.65)+0.3 -> 8.6587692 | Q18: =(O18/0.7)+0.3 -> 8.0617143 | R18: =(O18/0.75)+0.3 -> 7.5442667 | S18: 12 | T18: 11 LB.
B19: M1112251 | C19: 12x25x1 | D19: 14.62 | E19: =D19*$E$11 -> 4.9708 | F19: =(E19/0.65)+0.3 -> 7.9473846 | G19: =(E19/0.7)+0.3 -> 7.4011429 | H19: =(E19/0.75)+0.3 -> 6.9277333 | I19: 12 | J19: 7 LB. | L19: M1116162 | M19: 16x16x2 | N19: 20.46 | O19: =N19*$O$11 -> 6.9564 | P19: =(O19/0.65)+0.3 -> 11.002154 | Q19: =(O19/0.7)+0.3 -> 10.237714 | R19: =(O19/0.75)+0.3 -> 9.5752 | S19: 12 | T19: 11 LB.
B20: M1112301 | C20: 12x30x1 | D20: 21.75 | E20: =D20*$E$11 -> 7.395 | F20: =(E20/0.65)+0.3 -> 11.676923 | G20: =(E20/0.7)+0.3 -> 10.864286 | H20: =(E20/0.75)+0.3 -> 10.16 | I20: 12 | J20: 8 LB. | L20: M1116202 | M20: 16x20x2 | N20: 15.32 | O20: =N20*$O$11 -> 5.2088 | P20: =(O20/0.65)+0.3 -> 8.3135385 | Q20: =(O20/0.7)+0.3 -> 7.7411429 | R20: =(O20/0.75)+0.3 -> 7.2450667 | S20: 12 | T20: 12 LB.
B21: M1114141 | C21: 14x14x1 | D21: 15.6 | E21: =D21*$E$11 -> 5.304 | F21: =(E21/0.65)+0.3 -> 8.46 | G21: =(E21/0.7)+0.3 -> 7.8771429 | H21: =(E21/0.75)+0.3 -> 7.372 | I21: 12 | J21: 5 LB. | L21: M1116242 | M21: 16x24x2 | N21: 19.7 | O21: =N21*$O$11 -> 6.698 | P21: =(O21/0.65)+0.3 -> 10.604615 | Q21: =(O21/0.7)+0.3 -> 9.8685714 | R21: =(O21/0.75)+0.3 -> 9.2306667 | S21: 12 | T21: 13 LB.
B22: M1114201 | C22: 14x20x1 | D22: 13.96 | E22: =D22*$E$11 -> 4.7464 | F22: =(E22/0.65)+0.3 -> 7.6021538 | G22: =(E22/0.7)+0.3 -> 7.0805714 | H22: =(E22/0.75)+0.3 -> 6.6285333 | I22: 12 | J22: 6 LB. | L22: M1116252 | M22: 16x25x2 | N22: 17.73 | O22: =N22*$O$11 -> 6.0282 | P22: =(O22/0.65)+0.3 -> 9.5741538 | Q22: =(O22/0.7)+0.3 -> 8.9117143 | R22: =(O22/0.75)+0.3 -> 8.3376 | S22: 12 | T22: 14 LB.
B23: M1114241 | C23: 14x24x1 | D23: 22.51 | E23: =D23*$E$11 -> 7.6534 | F23: =(E23/0.65)+0.3 -> 12.074462 | G23: =(E23/0.7)+0.3 -> 11.233429 | H23: =(E23/0.75)+0.3 -> 10.504533 | I23: 12 | J23: 7 LB. | L23: M1118182 | M23: 18x18x2 | N23: 24.82 | O23: =N23*$O$11 -> 8.4388 | P23: =(O23/0.65)+0.3 -> 13.282769 | Q23: =(O23/0.7)+0.3 -> 12.355429 | R23: =(O23/0.75)+0.3 -> 11.551733 | S23: 12 | T23: 12 LB.
... B32: M1116301 | C32: 16x30x1 | D32: 23.48 | E32: =D32*$E$11 -> 7.9832 | F32: =(E32/0.65)+0.3 -> 12.581846 | G32: =(E32/0.7)+0.3 -> 11.704571 | H32: =(E32/0.75)+0.3 -> 10.944267 | I32: 12 | J32: 10 LB. | L32: M1125252 | M32: 25x25x2 | N32: 27.39 | O32: =N32*$O$11 -> 9.3126 | P32: =(O32/0.65)+0.3 -> 14.627077 | Q32: =(O32/0.7)+0.3 -> 13.603714 | R32: =(O32/0.75)+0.3 -> 12.7168 | S32: 12 | T32: 20 LB.
B33: M1118181 | C33: 18x18x1 | D33: 21.75 | E33: =D33*$E$11 -> 7.395 | F33: =(E33/0.65)+0.3 -> 11.676923 | G33: =(E33/0.7)+0.3 -> 10.864286 | H33: =(E33/0.75)+0.3 -> 10.16 | I33: 12 | J33: 7 LB.
B34: M1118201 | C34: 18x20x1 | D34: 20.39 | E34: =D34*$E$11 -> 6.9326 | F34: =(E34/0.65)+0.3 -> 10.965538 | G34: =(E34/0.7)+0.3 -> 10.203714 | H34: =(E34/0.75)+0.3 -> 9.5434667 | I34: 12 | J34: 8 LB. | L34: Geo-Thermal Replacement Sizes
B35: M1118241 | C35: 18x24x1 | D35: 17.13 | E35: =D35*$E$11 -> 5.8242 | F35: =(E35/0.65)+0.3 -> 9.2603077 | G35: =(E35/0.7)+0.3 -> 8.6202857 | H35: =(E35/0.75)+0.3 -> 8.0656 | I35: 12 | J35: 9 LB. | L35: PART | M35: Actual | N35: LIST | O35: Multiplier | S35: CARTON | T35: CARTON
B36: M1118251 | C36: 18x25x1 | D36: 19.1 | E36: =D36*$E$11 -> 6.494 | F36: =(E36/0.65)+0.3 -> 10.290769 | G36: =(E36/0.7)+0.3 -> 9.5771429 | H36: =(E36/0.75)+0.3 -> 8.9586667 | I36: 12 | J36: 9 LB. | L36: NUMBER | M36: SIZES | N36: PRICE | O36: 0.511 | S36: QUANTITY | T36: WEIGHT
B37: M1118301 | C37: 18x30x1 | D37: 26 | E37: =D37*$E$11 -> 8.84 | F37: =(E37/0.65)+0.3 -> 13.9 | G37: =(E37/0.7)+0.3 -> 12.928571 | H37: =(E37/0.75)+0.3 -> 12.086667 | I37: 12 | J37: 11 LB. | L37: M1124282 | M37: 23-1/2 x 27-3/4 x 2 | N37: 41.71 | O37: =N37*$O$36 -> 21.31381 | P37: =(O37/0.65)+0.3 -> 33.090477 | Q37: =(O37/0.7)+0.3 -> 30.7483 | R37: =(O37/0.75)+0.3 -> 28.718413 | S37: 6 | T37: 14 LB.
B38: M1120201 | C38: 20x20x1 | D38: 14.9 | E38: =D38*$E$11 -> 5.066 | F38: =(E38/0.65)+0.3 -> 8.0938462 | G38: =(E38/0.7)+0.3 -> 7.5371429 | H38: =(E38/0.75)+0.3 -> 7.0546667 | I38: 12 | J38: 8 LB. | L38: M1128302 | M38: 27-3/4 x 29-3/8 x 2 | N38: 72.41 | O38: =N38*$O$36 -> 37.00151 | P38: =(O38/0.65)+0.3 -> 57.2254 | Q38: =(O38/0.7)+0.3 -> 53.1593 | R38: =(O38/0.75)+0.3 -> 49.635347 | S38: 6 | T38: 16 LB.
B39: M1120221 | C39: 20x22x1 | D39: 20.77 | E39: =D39*$E$11 -> 7.0618 | F39: =(E39/0.65)+0.3 -> 11.164308 | G39: =(E39/0.7)+0.3 -> 10.388286 | H39: =(E39/0.75)+0.3 -> 9.7157333 | I39: 12 | J39: 9 LB. | L39: M1130322 | M39: 29-3/8 x 31-3/4 x 2 | N39: 72.41 | O39: =N39*$O$36 -> 37.00151 | P39: =(O39/0.65)+0.3 -> 57.2254 | Q39: =(O39/0.7)+0.3 -> 53.1593 | R39: =(O39/0.75)+0.3 -> 49.635347 | S39: 6 | T39: 17 LB.
B40: M1120241 | C40: 20x24x1 | D40: 16.93 | E40: =D40*$E$11 -> 5.7562 | F40: =(E40/0.65)+0.3 -> 9.1556923 | G40: =(E40/0.7)+0.3 -> 8.5231429 | H40: =(E40/0.75)+0.3 -> 7.9749333 | I40: 12 | J40: 10 LB. | L40: M1130362 | M40: 29-3/8 x 35-3/4 x 2 | N40: 77.71 | O40: =N40*$O$36 -> 39.70981 | P40: =(O40/0.65)+0.3 -> 61.392015 | Q40: =(O40/0.7)+0.3 -> 57.0283 | R40: =(O40/0.75)+0.3 -> 53.246413 | S40: 6 | T40: 18 LB.
B41: M1120251 | C41: 20x25x1 | D41: 16.7 | E41: =D41*$E$11 -> 5.678 | F41: =(E41/0.65)+0.3 -> 9.0353846 | G41: =(E41/0.7)+0.3 -> 8.4114286 | H41: =(E41/0.75)+0.3 -> 7.8706667 | I41: 12 | J41: 10 LB.
B42: M1120301 | C42: 20x30x1 | D42: 22.38 | E42: =D42*$E$11 -> 7.6092 | F42: =(E42/0.65)+0.3 -> 12.006462 | G42: =(E42/0.7)+0.3 -> 11.170286 | H42: =(E42/0.75)+0.3 -> 10.4456 | I42: 12 | J42: 11 LB.
B43: M1122221 | C43: 22x22x1 | D43: 24.17 | E43: =D43*$E$11 -> 8.2178 | F43: =(E43/0.65)+0.3 -> 12.942769 | G43: =(E43/0.7)+0.3 -> 12.039714 | H43: =(E43/0.75)+0.3 -> 11.257067 | I43: 12 | J43: 9 LB.
B44: M1124241 | C44: 24x24x1 | D44: 19.41 | E44: =D44*$E$11 -> 6.5994 | F44: =(E44/0.65)+0.3 -> 10.452923 | G44: =(E44/0.7)+0.3 -> 9.7277143 | H44: =(E44/0.75)+0.3 -> 9.0992 | I44: 12 | J44: 11 LB.
B45: M1124301 | C45: 24x30x1 | D45: 28.67 | E45: =D45*$E$11 -> 9.7478 | F45: =(E45/0.65)+0.3 -> 15.296615 | G45: =(E45/0.7)+0.3 -> 14.225429 | H45: =(E45/0.75)+0.3 -> 13.297067 | I45: 12 | J45: 14 LB.
B46: M1125251 | C46: 25x25x1 | D46: 23.24 | E46: =D46*$E$11 -> 7.9016 | F46: =(E46/0.65)+0.3 -> 12.456308 | G46: =(E46/0.7)+0.3 -> 11.588 | H46: =(E46/0.75)+0.3 -> 10.835467 | I46: 12 | J46: 13 LB.
C49: 4 | M49: 6
B50: PART | C50: STANDARD | D50: LIST | E50: Multiplier | I50: CARTON | J50: CARTON | L50: PART | M50: STANDARD | N50: LIST | O50: Multiplier | S50: CARTON | T50: CARTON
B51: NUMBER | C51: SIZES | D51: PRICE | E51: 0.34 | F51: 35% Margin | G51: 30% Margin | H51: 25% Margin | I51: QUANTITY | J51: WEIGHT | L51: NUMBER | M51: SIZES | N51: PRICE | O51: 0.34 | P51: 35% Margin | Q51: 30% Margin | R51: 25% Margin | S51: QUANTITY | T51: WEIGHT
B52: M1112244 | C52: 12x24x4 | D52: 27.3 | E52: =D52*$E$51 -> 9.282 | F52: =(E52/0.65)+0.3 -> 14.58 | G52: =(E52/0.7)+0.3 -> 13.56 | H52: =(E52/0.75)+0.3 -> 12.676 | I52: 6 | J52: 9 LB. | L52: M1112246 | M52: 12x24x6 | N52: 38.3 | O52: =N52*$O$51 -> 13.022 | P52: =(O52/0.65)+0.3 -> 20.333846 | Q52: =(O52/0.7)+0.3 -> 18.902857 | R52: =(O52/0.75)+0.3 -> 17.662667 | S52: 4 | T52: 9 LB.
B53: M1116204 | C53: 16x20x4 | D53: 26.78 | E53: =D53*$E$51 -> 9.1052 | F53: =(E53/0.65)+0.3 -> 14.308 | G53: =(E53/0.7)+0.3 -> 13.307429 | H53: =(E53/0.75)+0.3 -> 12.440267 | I53: 6 | J53: 10 LB. | L53: M1116206 | M53: 16x20x6 | N53: 37.96 | O53: =N53*$O$51 -> 12.9064 | P53: =(O53/0.65)+0.3 -> 20.156 | Q53: =(O53/0.7)+0.3 -> 18.737714 | R53: =(O53/0.75)+0.3 -> 17.508533 | S53: 4 | T53: 11 LB.
B54: M1116254 | C54: 16x25x4 | D54: 31.17 | E54: =D54*$E$51 -> 10.5978 | F54: =(E54/0.65)+0.3 -> 16.604308 | G54: =(E54/0.7)+0.3 -> 15.439714 | H54: =(E54/0.75)+0.3 -> 14.4304 | I54: 6 | J54: 12 LB. | L54: M1116256 | M54: 16x25x6 | N54: 45.7 | O54: =N54*$O$51 -> 15.538 | P54: =(O54/0.65)+0.3 -> 24.204615 | Q54: =(O54/0.7)+0.3 -> 22.497143 | R54: =(O54/0.75)+0.3 -> 21.017333 | S54: 4 | T54: 12 LB.
B55: M1118244 | C55: 18x24x4 | D55: 34.2 | E55: =D55*$E$51 -> 11.628 | F55: =(E55/0.65)+0.3 -> 18.189231 | G55: =(E55/0.7)+0.3 -> 16.911429 | H55: =(E55/0.75)+0.3 -> 15.804 | I55: 6 | J55: 13 LB. | L55: M1118246 | M55: 18x24x6 | N55: 51.21 | O55: =N55*$O$51 -> 17.4114 | P55: =(O55/0.65)+0.3 -> 27.086769 | Q55: =(O55/0.7)+0.3 -> 25.173429 | R55: =(O55/0.75)+0.3 -> 23.5152 | S55: 4 | T55: 13 LB.
B56: M1120204 | C56: 20x20x4 | D56: 31.95 | E56: =D56*$E$51 -> 10.863 | F56: =(E56/0.65)+0.3 -> 17.012308 | G56: =(E56/0.7)+0.3 -> 15.818571 | H56: =(E56/0.75)+0.3 -> 14.784 | I56: 6 | J56: 11 LB. | L56: M1120206 | M56: 20x20x6 | N56: 45.7 | O56: =N56*$O$51 -> 15.538 | P56: =(O56/0.65)+0.3 -> 24.204615 | Q56: =(O56/0.7)+0.3 -> 22.497143 | R56: =(O56/0.75)+0.3 -> 21.017333 | S56: 4 | T56: 12 LB.
B57: M1120244 | C57: 20x24x4 | D57: 37.25 | E57: =D57*$E$51 -> 12.665 | F57: =(E57/0.65)+0.3 -> 19.784615 | G57: =(E57/0.7)+0.3 -> 18.392857 | H57: =(E57/0.75)+0.3 -> 17.186667 | I57: 6 | J57: 13 LB. | L57: M1120246 | M57: 20x24x6 | N57: 50.82 | O57: =N57*$O$51 -> 17.2788 | P57: =(O57/0.65)+0.3 -> 26.882769 | Q57: =(O57/0.7)+0.3 -> 24.984 | R57: =(O57/0.75)+0.3 -> 23.3384 | S57: 4 | T57: 14 LB.
B58: M1120254 | C58: 20x25x4 | D58: 36.65 | E58: =D58*$E$51 -> 12.461 | F58: =(E58/0.65)+0.3 -> 19.470769 | G58: =(E58/0.7)+0.3 -> 18.101429 | H58: =(E58/0.75)+0.3 -> 16.914667 | I58: 6 | J58: 14 LB. | L58: M1120256 | M58: 20x25x6 | N58: 50.02 | O58: =N58*$O$51 -> 17.0068 | P58: =(O58/0.65)+0.3 -> 26.464308 | Q58: =(O58/0.7)+0.3 -> 24.595429 | R58: =(O58/0.75)+0.3 -> 22.975733 | S58: 4 | T58: 15 LB.
B59: M1124244 | C59: 24x24x4 | D59: 41.69 | E59: =D59*$E$51 -> 14.1746 | F59: =(E59/0.65)+0.3 -> 22.107077 | G59: =(E59/0.7)+0.3 -> 20.549429 | H59: =(E59/0.75)+0.3 -> 19.199467 | I59: 6 | J59: 15 LB. | L59: M1124246 | M59: 24x24x6 | N59: 56.81 | O59: =N59*$O$51 -> 19.3154 | P59: =(O59/0.65)+0.3 -> 30.016 | Q59: =(O59/0.7)+0.3 -> 27.893429 | R59: =(O59/0.75)+0.3 -> 26.053867 | S59: 4 | T59: 16 LB.
B60: Semi-Std. Size | E60: =D60*$E$51 -> 0 | F60: =(E60/0.65)+0.3 -> 0.3 | G60: =(E60/0.7)+0.3 -> 0.3 | H60: =(E60/0.75)+0.3 -> 0.3
B61: M1125294 | C61: 25x29x4 (24 1/2x28 1/2) | D61: 48.52 | E61: =D61*$E$51 -> 16.4968 | F61: =(E61/0.65)+0.3 -> 25.679692 | G61: =(E61/0.7)+0.3 -> 23.866857 | H61: =(E61/0.75)+0.3 -> 22.295733 | I61: 6 | J61: 17 LB.

Sheet MR11 2
L2: SIZES | M2: H | N2: L | O2: W | P2: TOTAL | Q2: PRICE 1" | R2: PRICE 2" | S2: PRICE 4" | V2: PRICE 1" | W2: PRICE 2" | X2: PRICE 4"
C3: AFC COST | D3: 35% Margin | E3: 30% Margin | F3: 25% Margin | M3: 16 | N3: 24 | O3: 1 | P3: =M3*N3 -> 384 | Q3: =_xlfn.XLOOKUP($M$3*$N$3, $D$11:$D$20, $I$11:$I$20, $I$11, -1) -> 22.760415 | R3: =_xlfn.XLOOKUP($M$3*$N$3, $D$11:$D$20, $Q$11:$Q$20, $Q$11, -1) -> 26.573262 | S3: =_xlfn.XLOOKUP($M$3*$N$3, $D$11:$D$20, $Y$11:$Y$20, $Y$11, -1) -> 50.417308 | T3: 0.35 | V3: =IF(OR(AND($M$3>28, $N$3>28), $M$3>35, $N$3>35),_xlfn.XLOOKUP(($M$3*$N$3)/2, $D$11:$D$20, $I$11:$I$20, $I$11, -1) * 2,"N/A") -> N/A | W3: {=IF(OR(AND($M$3>28, $N$3>28), $M$3>35, $N$3>35),_xlfn.XLOOKUP(($M$3*$N$3)/2, $D$11:$D$20, Q$11:$Q$20, $Q$11, -1) * 2,"N/A")} -> N/A | X3: =IF(OR(AND($M$3>28, $N$3>28), $M$3>35, $N$3>35),_xlfn.XLOOKUP(($M$3*$N$3)/2, $D$11:$D$20, $Y$11:$Y$20, $Y$11, -1) * 2,"N/A") -> N/A | Y3: 0.35
Q4: =_xlfn.XLOOKUP($M$3*$N$3, $D$11:$D$20, $J$11:$J$20, $J$11, -1) -> 21.1561 | R4: =_xlfn.XLOOKUP($M$3*$N$3, $D$11:$D$20, $R$11:$R$20, $R$11, -1) -> 24.6966 | S4: =_xlfn.XLOOKUP($M$3*$N$3, $D$11:$D$20, $Z$11:$Z$20, $Z$11, -1) -> 46.8375 | T4: 0.3 | V4: =IF(OR(AND($M$3>28, $N$3>28), $M$3>35, $N$3>35),_xlfn.XLOOKUP(($M$3*$N$3)/2, $D$11:$D$20, $J$11:$J$20, $J$11, -1) * 2,"N/A") -> N/A | W4: =IF(OR(AND($M$3>28, $N$3>28), $M$3>35, $N$3>35),_xlfn.XLOOKUP(($M$3*$N$3)/2, $D$11:$D$20, $R$11:$R$20, $R$10, -1) * 2,"N/A") -> N/A | X4: =IF(OR(AND($M$3>28, $N$3>28), $M$3>35, $N$3>35),_xlfn.XLOOKUP(($M$3*$N$3)/2, $D$11:$D$20, $Z$11:$Z$20, $Z$11, -1) * 2,"N/A") -> N/A | Y4: 0.3
Q5: =_xlfn.XLOOKUP($M$3*$N$3, $D$11:$D$20, $K$11:$K$20, $K$11, -1) -> 19.765693 | R5: =_xlfn.XLOOKUP($M$3*$N$3, $D$11:$D$20, $S$11:$S$20, $S$11, -1) -> 23.07016 | S5: =_xlfn.XLOOKUP($M$3*$N$3, $D$11:$D$20, $AA$11:$AA$20, $AA$11, -1) -> 43.735 | T5: 0.25 | V5: =IF(OR(AND($M$3>28, $N$3>28), $M$3>35, $N$3>35),_xlfn.XLOOKUP(($M$3*$N$3)/2, $D$11:$D$20, $K$11:$K$20, $K$11, -1) * 2,"N/A") -> N/A | W5: =IF(OR(AND($M$3>28, $N$3>28), $M$3>35, $N$3>35),_xlfn.XLOOKUP(($M$3*$N$3)/2, $D$11:$D$20, $S$11:$S$20, $S$10, -1) * 2,"N/A") -> N/A | X5: =IF(OR(AND($M$3>28, $N$3>28), $M$3>35, $N$3>35),_xlfn.XLOOKUP(($M$3*$N$3)/2, $D$11:$D$20, $AA$11:$AA$20, $AA$11, -1) * 2,"N/A") -> N/A | Y5: 0.25
V6: DOUBLE SIZE PRICING
C7: The Z-Line Series
C8: MADE-TO-ORDER SIZES | F8: MR-11 1" | H8: Multiplier
C9: Gross Area | F9: Part | G9: List | H9: 0.511 | M9: MR-11 2" | U9: MR-11 4"
C10: Square Inches | F10: Number | G10: Price | H10: AFC COST | I10: 35% Margin | J10: 30% Margin | K10: 25% Margin | P10: AFC COST | Q10: 35% Margin | R10: 30% Margin | S10: 25% Margin | X10: AFC COST | Y10: 35% Margin | Z10: 30% Margin | AA10: 25% Margin
C11: Less than 150" | D11: 0 | E11: 150 | F11: M11SP1A | G11: 17.3 | H11: =G11*$H$9 -> 8.8403 | I11: =(H11/0.65)+0.3 -> 13.900462 | J11: =(H11/0.7)+0.3 -> 12.929 | K11: =(H11/0.75)+0.3 -> 12.087067 | M11: Less than 150" | N11: M11SP2A | O11: 20.85 | P11: =O11*$H$9 -> 10.65435 | Q11: =(P11/0.65)+0.3 -> 16.691308 | R11: =(P11/0.7)+0.3 -> 15.5205 | S11: =(P11/0.75)+0.3 -> 14.5058 | U11: Less than 150" | V11: M11SP4A | W11: 40.74 | X11: =W11*$H$9 -> 20.81814 | Y11: =(X11/0.65)+0.3 -> 32.327908 | Z11: =(X11/0.7)+0.3 -> 30.0402 | AA11: =(X11/0.75)+0.3 -> 28.05752
C12: 150-199" | D12: 150 | E12: 199 | F12: M11SP1B | G12: 20.49 | H12: =G12*$H$9 -> 10.47039 | I12: =(H12/0.65)+0.3 -> 16.408292 | J12: =(H12/0.7)+0.3 -> 15.2577 | K12: =(H12/0.75)+0.3 -> 14.26052 | M12: 150-199" | N12: M11SP2B | O12: 23.99 | P12: =O12*$H$9 -> 12.25889 | Q12: =(P12/0.65)+0.3 -> 19.159831 | R12: =(P12/0.7)+0.3 -> 17.8127 | S12: =(P12/0.75)+0.3 -> 16.645187 | U12: 150-199" | V12: M11SP4B | W12: 45.98 | X12: =W12*$H$9 -> 23.49578 | Y12: =(X12/0.65)+0.3 -> 36.447354 | Z12: =(X12/0.7)+0.3 -> 33.8654 | AA12: =(X12/0.75)+0.3 -> 31.627707
C13: 200-249" | D13: 200 | E13: 249 | F13: M11SP1C | G13: 23.07 | H13: =G13*$H$9 -> 11.78877 | I13: =(H13/0.65)+0.3 -> 18.436569 | J13: =(H13/0.7)+0.3 -> 17.1411 | K13: =(H13/0.75)+0.3 -> 16.01836 | M13: 200-249" | N13: M11SP2C | O13: 26.98 | P13: =O13*$H$9 -> 13.78678 | Q13: =(P13/0.65)+0.3 -> 21.510431 | R13: =(P13/0.7)+0.3 -> 19.9954 | S13: =(P13/0.75)+0.3 -> 18.682373 | U13: 200-249" | V13: M11SP4C | W13: 51.22 | X13: =W13*$H$9 -> 26.17342 | Y13: =(X13/0.65)+0.3 -> 40.5668 | Z13: =(X13/0.7)+0.3 -> 37.6906 | AA13: =(X13/0.75)+0.3 -> 35.197893
C14: 250-299" | D14: 250 | E14: 299 | F14: M11SP1D | G14: 25.42 | H14: =G14*$H$9 -> 12.98962 | I14: =(H14/0.65)+0.3 -> 20.284031 | J14: =(H14/0.7)+0.3 -> 18.8566 | K14: =(H14/0.75)+0.3 -> 17.619493 | M14: 250-299" | N14: M11SP2D | O14: 29.71 | P14: =O14*$H$9 -> 15.18181 | Q14: =(P14/0.65)+0.3 -> 23.656631 | R14: =(P14/0.7)+0.3 -> 21.9883 | S14: =(P14/0.75)+0.3 -> 20.542413 | U14: 250-299" | V14: M11SP4D | W14: 56.49 | X14: =W14*$H$9 -> 28.86639 | Y14: =(X14/0.65)+0.3 -> 44.709831 | Z14: =(X14/0.7)+0.3 -> 41.5377 | AA14: =(X14/0.75)+0.3 -> 38.78852
C15: 300-399" | D15: 300 | E15: 399 | F15: M11SP1E | G15: 28.57 | H15: =G15*$H$9 -> 14.59927 | I15: =(H15/0.65)+0.3 -> 22.760415 | J15: =(H15/0.7)+0.3 -> 21.1561 | K15: =(H15/0.75)+0.3 -> 19.765693 | M15: 300-399" | N15: M11SP2E | O15: 33.42 | P15: =O15*$H$9 -> 17.07762 | Q15: =(P15/0.65)+0.3 -> 26.573262 | R15: =(P15/0.7)+0.3 -> 24.6966 | S15: =(P15/0.75)+0.3 -> 23.07016 | U15: 300-399" | V15: M11SP4E | W15: 63.75 | X15: =W15*$H$9 -> 32.57625 | Y15: =(X15/0.65)+0.3 -> 50.417308 | Z15: =(X15/0.7)+0.3 -> 46.8375 | AA15: =(X15/0.75)+0.3 -> 43.735
C16: 400-499" | D16: 400 | E16: 499 | F16: M11SP1F | G16: 31.85 | H16: =G16*$H$9 -> 16.27535 | I16: =(H16/0.65)+0.3 -> 25.339 | J16: =(H16/0.7)+0.3 -> 23.5505 | K16: =(H16/0.75)+0.3 -> 22.000467 | M16: 400-499" | N16: M11SP2F | O16: 37.21 | P16: =O16*$H$9 -> 19.01431 | Q16: =(P16/0.65)+0.3 -> 29.552785 | R16: =(P16/0.7)+0.3 -> 27.4633 | S16: =(P16/0.75)+0.3 -> 25.652413 | U16: 400-499" | V16: M11SP4F | W16: 70.74 | X16: =W16*$H$9 -> 36.14814 | Y16: =(X16/0.65)+0.3 -> 55.912523 | Z16: =(X16/0.7)+0.3 -> 51.9402 | AA16: =(X16/0.75)+0.3 -> 48.49752
C17: 500-599" | D17: 500 | E17: 599 | F17: M11SP1G | G17: 34.16 | H17: =G17*$H$9 -> 17.45576 | I17: =(H17/0.65)+0.3 -> 27.155015 | J17: =(H17/0.7)+0.3 -> 25.2368 | K17: =(H17/0.75)+0.3 -> 23.574347 | M17: 500-599" | N17: M11SP2G | O17: 39.94 | P17: =O17*$H$9 -> 20.40934 | Q17: =(P17/0.65)+0.3 -> 31.698985 | R17: =(P17/0.7)+0.3 -> 29.4562 | S17: =(P17/0.75)+0.3 -> 27.512453 | U17: 500-599" | V17: M11SP4G | W17: 75.96 | X17: =W17*$H$9 -> 38.81556 | Y17: =(X17/0.65)+0.3 -> 60.016246 | Z17: =(X17/0.7)+0.3 -> 55.7508 | AA17: =(X17/0.75)+0.3 -> 52.05408
C18: 600-699" | D18: 600 | E18: 699 | F18: M11SP1H | G18: 36.69 | H18: =G18*$H$9 -> 18.74859 | I18: =(H18/0.65)+0.3 -> 29.143985 | J18: =(H18/0.7)+0.3 -> 27.0837 | K18: =(H18/0.75)+0.3 -> 25.29812 | M18: 600-699" | N18: M11SP2H | O18: 42.9 | P18: =O18*$H$9 -> 21.9219 | Q18: =(P18/0.65)+0.3 -> 34.026 | R18: =(P18/0.7)+0.3 -> 31.617 | S18: =(P18/0.75)+0.3 -> 29.5292 | U18: 600-699" | V18: M11SP4H | W18: 81.27 | X18: =W18*$H$9 -> 41.52897 | Y18: =(X18/0.65)+0.3 -> 64.190723 | Z18: =(X18/0.7)+0.3 -> 59.6271 | AA18: =(X18/0.75)+0.3 -> 55.67196
C19: 700-799" | D19: 700 | E19: 799 | F19: M11SP1I | G19: 38.86 | H19: =G19*$H$9 -> 19.85746 | I19: =(H19/0.65)+0.3 -> 30.849938 | J19: =(H19/0.7)+0.3 -> 28.6678 | K19: =(H19/0.75)+0.3 -> 26.776613 | M19: 700-799" | N19: M11SP2I | O19: 45.46 | P19: =O19*$H$9 -> 23.23006 | Q19: =(P19/0.65)+0.3 -> 36.038554 | R19: =(P19/0.7)+0.3 -> 33.4858 | S19: =(P19/0.75)+0.3 -> 31.273413 | U19: 700-799" | V19: M11SP4I | W19: 86.93 | X19: =W19*$H$9 -> 44.42123 | Y19: =(X19/0.65)+0.3 -> 68.640354 | Z19: =(X19/0.7)+0.3 -> 63.7589 | AA19: =(X19/0.75)+0.3 -> 59.528307
C20: 800-899" | D20: 800 | E20: 899 | F20: M11SP1J | G20: 42.7 | H20: =G20*$H$9 -> 21.8197 | I20: =(H20/0.65)+0.3 -> 33.868769 | J20: =(H20/0.7)+0.3 -> 31.471 | K20: =(H20/0.75)+0.3 -> 29.392933 | M20: 800-899" | N20: M11SP2J | O20: 49.99 | P20: =O20*$H$9 -> 25.54489 | Q20: =(P20/0.65)+0.3 -> 39.599831 | R20: =(P20/0.7)+0.3 -> 36.7927 | S20: =(P20/0.75)+0.3 -> 34.359853 | U20: 800-899" | V20: M11SP4J | W20: 95.65 | X20: =W20*$H$9 -> 48.87715 | Y20: =(X20/0.65)+0.3 -> 75.495615 | Z20: =(X20/0.7)+0.3 -> 70.1245 | AA20: =(X20/0.75)+0.3 -> 65.469533
C23: *MINIMUM: | F23: 12 Per size; Less than 12 per size add 40% to each filter.
F24: Made-To-Order filters are bulk packed.
F25: * The minimum size of a special size is 4" x 4".
C27: *DOUBLE SIZE: | F27: If both dimensions are larger than 24 3/4”, or if either dimension is
F28: larger than 35” it is considered a double size filter .
F29: To figure the price on a double size MR-11 calculate 1/2 of the square
F30: inches for the desired size and then double the list price.
F31: The maximum length dimension is 96".
F32: 6" Special-Size Pleats: add 55% to the 4" list price.

Sheet MR13 1
L1: List Price Sheet 6MR13-S
K2: 46143
C3: AFC COST | D3: 35% Margin | E3: 30% Margin | F3: 25% Margin | L3: Section 6
L4: Product Bulletin 6 MR13
B6: The Z-Line Series MR-13 | E6: Multiplier
B7: PART | C7: 1 | D7: LIST | E7: 0.18 | K7: CARTON | L7: CARTON
B8: NUMBER | C8: STANDARD SIZES | D8: PRICE | F8: 35% Margin | G8: 30% Margin | H8: 25% Margin | I8: 20% Margin | J8: 15% Margin | K8: QUANTITY | L8: WEIGHT
B9: M1310101 | C9: 10x10x1 | D9: 26.52 | E9: =D9*$E$7 -> 4.7736 | F9: =(E9/0.65)+0.3 -> 7.644 | G9: =(E9/0.7)+0.3 -> 7.1194286 | H9: =(E9/0.75)+0.3 -> 6.6648 | I9: =(E9/0.8)+0.3 -> 6.267 | J9: =(E9/0.85)+0.3 -> 5.916 | K9: 12 | L9: 3 LB.
B10: M1310201 | C10: 10x20x1 | D10: 27.97 | E10: =D10*$E$7 -> 5.0346 | F10: =(E10/0.65)+0.3 -> 8.0455385 | G10: =(E10/0.7)+0.3 -> 7.4922857 | H10: =(E10/0.75)+0.3 -> 7.0128 | I10: =(E10/0.8)+0.3 -> 6.59325 | J10: =(E10/0.85)+0.3 -> 6.2230588 | K10: 12 | L10: 7 LB.
B11: M1310241 | C11: 10x24x1 | D11: 40.87 | E11: =D11*$E$7 -> 7.3566 | F11: =(E11/0.65)+0.3 -> 11.617846 | G11: =(E11/0.7)+0.3 -> 10.809429 | H11: =(E11/0.75)+0.3 -> 10.1088 | I11: =(E11/0.8)+0.3 -> 9.49575 | J11: =(E11/0.85)+0.3 -> 8.9548235 | K11: 12 | L11: 8 LB.
B12: M1310301 | C12: 10x30x1 | D12: 41.3 | E12: =D12*$E$7 -> 7.434 | F12: =(E12/0.65)+0.3 -> 11.736923 | G12: =(E12/0.7)+0.3 -> 10.92 | H12: =(E12/0.75)+0.3 -> 10.212 | I12: =(E12/0.8)+0.3 -> 9.5925 | J12: =(E12/0.85)+0.3 -> 9.0458824 | K12: 12 | L12: 7 LB.
B13: M1312121 | C13: 12x12x1 | D13: 26.66 | E13: =D13*$E$7 -> 4.7988 | F13: =(E13/0.65)+0.3 -> 7.6827692 | G13: =(E13/0.7)+0.3 -> 7.1554286 | H13: =(E13/0.75)+0.3 -> 6.6984 | I13: =(E13/0.8)+0.3 -> 6.2985 | J13: =(E13/0.85)+0.3 -> 5.9456471 | K13: 12 | L13: 4 LB.
B14: M1312201 | C14: 12x20x1 | D14: 28.8 | E14: =D14*$E$7 -> 5.184 | F14: =(E14/0.65)+0.3 -> 8.2753846 | G14: =(E14/0.7)+0.3 -> 7.7057143 | H14: =(E14/0.75)+0.3 -> 7.212 | I14: =(E14/0.8)+0.3 -> 6.78 | J14: =(E14/0.85)+0.3 -> 6.3988235 | K14: 12 | L14: 8 LB.
B15: M1312241 | C15: 12x24x1 | D15: 26.34 | E15: =D15*$E$7 -> 4.7412 | F15: =(E15/0.65)+0.3 -> 7.5941538 | G15: =(E15/0.7)+0.3 -> 7.0731429 | H15: =(E15/0.75)+0.3 -> 6.6216 | I15: =(E15/0.8)+0.3 -> 6.2265 | J15: =(E15/0.85)+0.3 -> 5.8778824 | K15: 12 | L15: 12 LB.
B16: M1312251 | C16: 12x25x1 | D16: 28.13 | E16: =D16*$E$7 -> 5.0634 | F16: =(E16/0.65)+0.3 -> 8.0898462 | G16: =(E16/0.7)+0.3 -> 7.5334286 | H16: =(E16/0.75)+0.3 -> 7.0512 | I16: =(E16/0.8)+0.3 -> 6.62925 | J16: =(E16/0.85)+0.3 -> 6.2569412 | K16: 12 | L16: 12 LB.
B17: M1312301 | C17: 12x30x1 | D17: 41.3 | E17: =D17*$E$7 -> 7.434 | F17: =(E17/0.65)+0.3 -> 11.736923 | G17: =(E17/0.7)+0.3 -> 10.92 | H17: =(E17/0.75)+0.3 -> 10.212 | I17: =(E17/0.8)+0.3 -> 9.5925 | J17: =(E17/0.85)+0.3 -> 9.0458824 | K17: 12 | L17: 8 LB.
B18: M1314141 | C18: 14x14x1 | D18: 25.31 | E18: =D18*$E$7 -> 4.5558 | F18: =(E18/0.65)+0.3 -> 7.3089231 | G18: =(E18/0.7)+0.3 -> 6.8082857 | H18: =(E18/0.75)+0.3 -> 6.3744 | I18: =(E18/0.8)+0.3 -> 5.99475 | J18: =(E18/0.85)+0.3 -> 5.6597647 | K18: 12 | L18: 5 LB.
B19: M1314201 | C19: 14x20x1 | D19: 26.87 | E19: =D19*$E$7 -> 4.8366 | F19: =(E19/0.65)+0.3 -> 7.7409231 | G19: =(E19/0.7)+0.3 -> 7.2094286 | H19: =(E19/0.75)+0.3 -> 6.7488 | I19: =(E19/0.8)+0.3 -> 6.34575 | J19: =(E19/0.85)+0.3 -> 5.9901176 | K19: 12 | L19: 8 LB.
B20: M1314241 | C20: 14x24x1 | D20: 43.25 | E20: =D20*$E$7 -> 7.785 | F20: =(E20/0.65)+0.3 -> 12.276923 | G20: =(E20/0.7)+0.3 -> 11.421429 | H20: =(E20/0.75)+0.3 -> 10.68 | I20: =(E20/0.8)+0.3 -> 10.03125 | J20: =(E20/0.85)+0.3 -> 9.4588235 | K20: 12 | L20: 8 LB.
... B43: M1325251 | C43: 25x25x1 | D43: 44.72 | E43: =D43*$E$7 -> 8.0496 | F43: =(E43/0.65)+0.3 -> 12.684 | G43: =(E43/0.7)+0.3 -> 11.799429 | H43: =(E43/0.75)+0.3 -> 11.0328 | I43: =(E43/0.8)+0.3 -> 10.362 | J43: =(E43/0.85)+0.3 -> 9.7701176 | K43: 12 | L43: 15 LB.
E44: Multiplier
B45: PART | C45: 2 | D45: LIST | E45: 0.18 | K45: CARTON | L45: CARTON
B46: NUMBER | C46: STANDARD SIZES | D46: PRICE | K46: QUANTITY | L46: WEIGHT
B47: M1310202 | C47: 10x20x2 | D47: 34.54 | E47: =D47*$E$45 -> 6.2172 | F47: =(E47/0.65)+0.3 -> 9.8649231 | G47: =(E47/0.7)+0.3 -> 9.1817143 | H47: =(E47/0.75)+0.3 -> 8.5896 | I47: =(E47/0.8)+0.3 -> 8.0715 | J47: =(E47/0.85)+0.3 -> 7.6143529 | K47: 12 | L47: 10 LB.
B48: M1312122 | C48: 12x12x2 | D48: 32.56 | E48: =D48*$E$45 -> 5.8608 | F48: =(E48/0.65)+0.3 -> 9.3166154 | G48: =(E48/0.7)+0.3 -> 8.6725714 | H48: =(E48/0.75)+0.3 -> 8.1144 | I48: =(E48/0.8)+0.3 -> 7.626 | J48: =(E48/0.85)+0.3 -> 7.1950588 | K48: 12 | L48: 9 LB.
B49: M1312202 | C49: 12x20x2 | D49: 36.65 | E49: =D49*$E$45 -> 6.597 | F49: =(E49/0.65)+0.3 -> 10.449231 | G49: =(E49/0.7)+0.3 -> 9.7242857 | H49: =(E49/0.75)+0.3 -> 9.096 | I49: =(E49/0.8)+0.3 -> 8.54625 | J49: =(E49/0.85)+0.3 -> 8.0611765 | K49: 12 | L49: 9 LB.
B50: M1312242 | C50: 12x24x2 | D50: 34.85 | E50: =D50*$E$45 -> 6.273 | F50: =(E50/0.65)+0.3 -> 9.9507692 | G50: =(E50/0.7)+0.3 -> 9.2614286 | H50: =(E50/0.75)+0.3 -> 8.664 | I50: =(E50/0.8)+0.3 -> 8.14125 | J50: =(E50/0.85)+0.3 -> 7.68 | K50: 12 | L50: 11 LB.
B51: M1314202 | C51: 14x20x2 | D51: 35.67 | E51: =D51*$E$45 -> 6.4206 | F51: =(E51/0.65)+0.3 -> 10.177846 | G51: =(E51/0.7)+0.3 -> 9.4722857 | H51: =(E51/0.75)+0.3 -> 8.8608 | I51: =(E51/0.8)+0.3 -> 8.32575 | J51: =(E51/0.85)+0.3 -> 7.8536471 | K51: 12 | L51: 12 LB.
B52: M1314252 | C52: 14x25x2 | D52: 38.84 | E52: =D52*$E$45 -> 6.9912 | F52: =(E52/0.65)+0.3 -> 11.055692 | G52: =(E52/0.7)+0.3 -> 10.287429 | H52: =(E52/0.75)+0.3 -> 9.6216 | I52: =(E52/0.8)+0.3 -> 9.039 | J52: =(E52/0.85)+0.3 -> 8.5249412 | K52: 12 | L52: 12 LB.
B53: M1315202 | C53: 15x20x2 | D53: 36.84 | E53: =D53*$E$45 -> 6.6312 | F53: =(E53/0.65)+0.3 -> 10.501846 | G53: =(E53/0.7)+0.3 -> 9.7731429 | H53: =(E53/0.75)+0.3 -> 9.1416 | I53: =(E53/0.8)+0.3 -> 8.589 | J53: =(E53/0.85)+0.3 -> 8.1014118 | K53: 12 | L53: 15 LB.
B54: M1316162 | C54: 16x16x2 | D54: 36.75 | E54: =D54*$E$45 -> 6.615 | F54: =(E54/0.65)+0.3 -> 10.476923 | G54: =(E54/0.7)+0.3 -> 9.75 | H54: =(E54/0.75)+0.3 -> 9.12 | I54: =(E54/0.8)+0.3 -> 8.56875 | J54: =(E54/0.85)+0.3 -> 8.0823529 | K54: 12 | L54: 11 LB. | P54: 1 | S54: 12
B55: M1316202 | C55: 16x20x2 | D55: 35.36 | E55: =D55*$E$45 -> 6.3648 | F55: =(E55/0.65)+0.3 -> 10.092 | G55: =(E55/0.7)+0.3 -> 9.3925714 | H55: =(E55/0.75)+0.3 -> 8.7864 | I55: =(E55/0.8)+0.3 -> 8.256 | J55: =(E55/0.85)+0.3 -> 7.788 | K55: 12 | L55: 12 LB. | P55: 2 | S55: 6
B56: M1316242 | C56: 16x24x2 | D56: 45.42 | E56: =D56*$E$45 -> 8.1756 | F56: =(E56/0.65)+0.3 -> 12.877846 | G56: =(E56/0.7)+0.3 -> 11.979429 | H56: =(E56/0.75)+0.3 -> 11.2008 | I56: =(E56/0.8)+0.3 -> 10.5195 | J56: =(E56/0.85)+0.3 -> 9.9183529 | K56: 12 | L56: 12 LB. | P56: 2 | S56: 1
B57: M1316252 | C57: 16x25x2 | D57: 40.87 | E57: =D57*$E$45 -> 7.3566 | F57: =(E57/0.65)+0.3 -> 11.617846 | G57: =(E57/0.7)+0.3 -> 10.809429 | H57: =(E57/0.75)+0.3 -> 10.1088 | I57: =(E57/0.8)+0.3 -> 9.49575 | J57: =(E57/0.85)+0.3 -> 8.9548235 | K57: 12 | L57: 15 LB. | P57: 2 | S57: 2
B58: M1318182 | C58: 18x18x2 | D58: 48.5 | E58: =D58*$E$45 -> 8.73 | F58: =(E58/0.65)+0.3 -> 13.730769 | G58: =(E58/0.7)+0.3 -> 12.771429 | H58: =(E58/0.75)+0.3 -> 11.94 | I58: =(E58/0.8)+0.3 -> 11.2125 | J58: =(E58/0.85)+0.3 -> 10.570588 | K58: 12 | L58: 12LB. | P58: 1 | S58: 6
B59: M1318202 | C59: 18x20x2 | D59: 48.5 | E59: =D59*$E$45 -> 8.73 | F59: =(E59/0.65)+0.3 -> 13.730769 | G59: =(E59/0.7)+0.3 -> 12.771429 | H59: =(E59/0.75)+0.3 -> 11.94 | I59: =(E59/0.8)+0.3 -> 11.2125 | J59: =(E59/0.85)+0.3 -> 10.570588 | K59: 12 | L59: 15 LB. | P59: 2 | S59: 2
B60: M1318242 | C60: 18x24x2 | D60: 47.08 | E60: =D60*$E$45 -> 8.4744 | F60: =(E60/0.65)+0.3 -> 13.337538 | G60: =(E60/0.7)+0.3 -> 12.406286 | H60: =(E60/0.75)+0.3 -> 11.5992 | I60: =(E60/0.8)+0.3 -> 10.893 | J60: =(E60/0.85)+0.3 -> 10.269882 | K60: 12 | L60: 15 LB. | P60: 2 | S60: 1
B61: M1318252 | C61: 18x25x2 | D61: 49.86 | E61: =D61*$E$45 -> 8.9748 | F61: =(E61/0.65)+0.3 -> 14.107385 | G61: =(E61/0.7)+0.3 -> 13.121143 | H61: =(E61/0.75)+0.3 -> 12.2664 | I61: =(E61/0.8)+0.3 -> 11.5185 | J61: =(E61/0.85)+0.3 -> 10.858588 | K61: 12 | L61: 15 LB. | P61: 2 | S61: 2
B62: M1320202 | C62: 20x20x2 | D62: 41.59 | E62: =D62*$E$45 -> 7.4862 | F62: =(E62/0.65)+0.3 -> 11.817231 | G62: =(E62/0.7)+0.3 -> 10.994571 | H62: =(E62/0.75)+0.3 -> 10.2816 | I62: =(E62/0.8)+0.3 -> 9.65775 | J62: =(E62/0.85)+0.3 -> 9.1072941 | K62: 12 | L62: 16 LB. | P62: 2 | S62: 2
B63: M1320242 | C63: 20x24x2 | D63: 49.03 | E63: =D63*$E$45 -> 8.8254 | F63: =(E63/0.65)+0.3 -> 13.877538 | G63: =(E63/0.7)+0.3 -> 12.907714 | H63: =(E63/0.75)+0.3 -> 12.0672 | I63: =(E63/0.8)+0.3 -> 11.33175 | J63: =(E63/0.85)+0.3 -> 10.682824 | K63: 12 | L63: 15 LB. | P63: 2 | S63: 2
B64: M1320252 | C64: 20x25x2 | D64: 48.03 | E64: =D64*$E$45 -> 8.6454 | F64: =(E64/0.65)+0.3 -> 13.600615 | G64: =(E64/0.7)+0.3 -> 12.650571 | H64: =(E64/0.75)+0.3 -> 11.8272 | I64: =(E64/0.8)+0.3 -> 11.10675 | J64: =(E64/0.85)+0.3 -> 10.471059 | K64: 12 | L64: 18 LB. | P64: 1 | S64: 1
B65: M1320302 | C65: 20x30x2 | D65: 58.16 | E65: =D65*$E$45 -> 10.4688 | F65: =(E65/0.65)+0.3 -> 16.405846 | G65: =(E65/0.7)+0.3 -> 15.255429 | H65: =(E65/0.75)+0.3 -> 14.2584 | I65: =(E65/0.8)+0.3 -> 13.386 | J65: =(E65/0.85)+0.3 -> 12.616235 | K65: 12 | L65: 18 LB. | P65: 1 | S65: 1
... B67: M1325252 | C67: 25x25x2 | D67: 63.11 | E67: =D67*$E$45 -> 11.3598 | F67: =(E67/0.65)+0.3 -> 17.776615 | G67: =(E67/0.7)+0.3 -> 16.528286 | H67: =(E67/0.75)+0.3 -> 15.4464 | I67: =(E67/0.8)+0.3 -> 14.49975 | J67: =(E67/0.85)+0.3 -> 13.664471 | K67: 12 | L67: 20 LB. | P67: 2 | S67: 4
E68: Multiplier | P68: 1 | S68: 4
B69: PART | C69: 4 | D69: LIST | E69: 0.18 | P69: 1 | S69: 2
B70: NUMBER | C70: STANDARD SIZES | D70: PRICE | P70: 2 | S70: 6
B71: M1312244 | C71: 12x24x4 | D71: 63 | E71: =D71*$E$69 -> 11.34 | F71: =(E71/0.65)+0.3 -> 17.746154 | G71: =(E71/0.7)+0.3 -> 16.5 | H71: =(E71/0.75)+0.3 -> 15.42 | I71: =(E71/0.8)+0.3 -> 14.475 | J71: =(E71/0.85)+0.3 -> 13.641176 | K71: 6 | L71: 10 LB. | P71: 1 | S71: 1
B72: M1316204 | C72: 16x20x4 | D72: 61.73 | E72: =D72*$E$69 -> 11.1114 | F72: =(E72/0.65)+0.3 -> 17.394462 | G72: =(E72/0.7)+0.3 -> 16.173429 | H72: =(E72/0.75)+0.3 -> 15.1152 | I72: =(E72/0.8)+0.3 -> 14.18925 | J72: =(E72/0.85)+0.3 -> 13.372235 | K72: 6 | L72: 11 LB. | P72: 1 | S72: 1
B73: M1316254 | C73: 16x25x4 | D73: 71.9 | E73: =D73*$E$69 -> 12.942 | F73: =(E73/0.65)+0.3 -> 20.210769 | G73: =(E73/0.7)+0.3 -> 18.788571 | H73: =(E73/0.75)+0.3 -> 17.556 | I73: =(E73/0.8)+0.3 -> 16.4775 | J73: =(E73/0.85)+0.3 -> 15.525882 | K73: 6 | L73: 12 LB. | P73: 1 | S73: 4
B74: M1318244 | C74: 18x24x4 | D74: 78.88 | E74: =D74*$E$69 -> 14.1984 | F74: =(E74/0.65)+0.3 -> 22.143692 | G74: =(E74/0.7)+0.3 -> 20.583429 | H74: =(E74/0.75)+0.3 -> 19.2312 | I74: =(E74/0.8)+0.3 -> 18.048 | J74: =(E74/0.85)+0.3 -> 17.004 | K74: 6 | L74: 12 LB. | P74: 1 | S74: =SUM(S54:S73) -> 61
B75: M1320204 | C75: 20x20x4 | D75: 73.76 | E75: =D75*$E$69 -> 13.2768 | F75: =(E75/0.65)+0.3 -> 20.725846 | G75: =(E75/0.7)+0.3 -> 19.266857 | H75: =(E75/0.75)+0.3 -> 18.0024 | I75: =(E75/0.8)+0.3 -> 16.896 | J75: =(E75/0.85)+0.3 -> 15.919765 | K75: 6 | L75: 11 LB. | P75: 1
B76: M1320244 | C76: 20x24x4 | D76: 85.86 | E76: =D76*$E$69 -> 15.4548 | F76: =(E76/0.65)+0.3 -> 24.076615 | G76: =(E76/0.7)+0.3 -> 22.378286 | H76: =(E76/0.75)+0.3 -> 20.9064 | I76: =(E76/0.8)+0.3 -> 19.6185 | J76: =(E76/0.85)+0.3 -> 18.482118 | K76: 6 | L76: 14 LB. | P76: 1
B77: M1320254 | C77: 20x25x4 | D77: 84.49 | E77: =D77*$E$69 -> 15.2082 | F77: =(E77/0.65)+0.3 -> 23.697231 | G77: =(E77/0.7)+0.3 -> 22.026 | H77: =(E77/0.75)+0.3 -> 20.5776 | I77: =(E77/0.8)+0.3 -> 19.31025 | J77: =(E77/0.85)+0.3 -> 18.192 | K77: 6 | L77: 15 LB. | P77: 2
B78: M1324244 | C78: 24x24x4 | D78: 96.16 | E78: =D78*$E$69 -> 17.3088 | F78: =(E78/0.65)+0.3 -> 26.928923 | G78: =(E78/0.7)+0.3 -> 25.026857 | H78: =(E78/0.75)+0.3 -> 23.3784 | I78: =(E78/0.8)+0.3 -> 21.936 | J78: =(E78/0.85)+0.3 -> 20.663294 | K78: 6 | L78: 16 LB. | P78: =SUM(P54:P77) -> 36
N82: 36402.43 | Q82: 35827.36 | R82: =N82-Q82 -> 575.07
N83: 47307.33 | Q83: 46982.99 | R83: =N83-Q83 -> 324.34
E84: GG | N84: 78676.14 | Q84: 77740.83 | R84: =N84-Q84 -> 935.31
F85: NEW | G85: OLD | N85: 48698.21 | Q85: 47621.56 | R85: =N85-Q85 -> 1076.65
E86: FINALS | F86: 12788.36 | G86: 13006.16 | H86: =F86-G86 -> -217.8 | N86: 17865.83 | Q86: 18122.1 | R86: =N86-Q86 -> -256.27
E87: PRES | F87: 11033.36 | G87: 10820.76 | H87: =F87-G87 -> 212.6 | N87: 32381.29 | Q87: 32184.42 | R87: =N87-Q87 -> 196.87
E88: MEDIA | F88: 13163.92 | G88: 12000.44 | H88: =F88-G88 -> 1163.48 | N88: 46671.59 | Q88: 42071.65 | R88: =N88-Q88 -> 4599.94
F89: =SUM(F86:F88) -> 36985.64 | G89: =SUM(G86:G88) -> 35827.36 | H89: =F89-G89 -> 1158.28 | N89: 36394.93 | Q89: 34193.1 | R89: =N89-Q89 -> 2201.83
N90: 13376.51 | Q90: 13374.81 | R90: =N90-Q90 -> 1.7
N91: 11887.98 | Q91: 11239.91 | R91: =N91-Q91 -> 648.07
N92: 17645.5 | Q92: 17516.95 | R92: =N92-Q92 -> 128.55
N93: 14363.47 | Q93: 14042.11 | R93: =N93-Q93 -> 321.36
C94: 48698.21 | D94: 47621.56 | E94: =C94-D94 -> 1076.65 | M94: total | N94: =SUM(N82:N93) -> 401671.21 | Q94: =SUM(Q82:Q93) -> 390917.79 | R94: =N94-Q94 -> 10753.42
I97: =(N94/Q94)*100% -> 1.0275081 | R97: =SUM(R82:R93) -> 10753.42
N105: 36402.43
N106: 47307.33
N107: 78676.14
N108: 48698.21
N109: 17865.83
N110: 32381.29
N111: 46671.59
N112: 36394.93
N113: 13376.51
N114: 11887.98
N115: 17645.5
N116: 14363.47

Sheet MR13 2
F2: SIZES | G2: H | H2: L | I2: W | J2: TOTAL | K2: PRICE 1" | L2: PRICE 2" | M2: PRICE 4" | P2: PRICE 1" | Q2: PRICE 2" | R2: PRICE 4"
A3: AFC COST | B3: 35% Margin | C3: 30% Margin | D3: 25% Margin | G3: 10 | H3: 25 | I3: 2 | J3: =G3*H3 -> 250 | K3: =_xlfn.XLOOKUP($G$3*$H$3, $B$12:$B$21, $G$12:$G$21, $G$12, -1) -> 22.915385 | L3: =_xlfn.XLOOKUP($G$3*$H$3, $B$12:$B$21, $O$12:$O$21, $O$12, -1) -> 27.982308 | M3: =_xlfn.XLOOKUP($G$3*$H$3, $B$12:$B$21, $W$12:$W$21, $W$12, -1) -> 41.217692 | N3: 0.35 | P3: =IF(OR(AND($G$3>28, $H$3>28), $G$3>35, $H$3>35),_xlfn.XLOOKUP(($G$3*$H$3)/2, $B$12:$B$21, $G$12:$G$21, $G$12, -1) * 2,"N/A") -> N/A | Q3: =IF(OR(AND($G$3>28, $H$3>28), $G$3>35, $H$3>35),_xlfn.XLOOKUP(($G$3*$H$3)/2, $B$12:$B$21, $O$12:$O$21, $O$12, -1) * 2,"N/A") -> N/A | R3: =IF(OR(AND($G$3>28, $H$3>28), $G$3>35, $H$3>35),_xlfn.XLOOKUP(($G$3*$H$3)/2, $B$12:$B$21, $W$12:$W$21, $W$12, -1) * 2,"N/A") -> N/A | S3: 0.35
K4: =_xlfn.XLOOKUP($G$3*$H$3, $B$12:$B$21, $H$12:$H$21, $H$12, -1) -> 21.3 | L4: =_xlfn.XLOOKUP($G$3*$H$3, $B$12:$B$21, $P$12:$P$21, $P$12, -1) -> 26.005 | M4: =_xlfn.XLOOKUP($G$3*$H$3, $B$12:$B$21, $X$12:$X$21, $X$12, -1) -> 38.295 | N4: 0.3 | P4: =IF(OR(AND($G$3>28, $H$3>28), $G$3>35, $H$3>35),_xlfn.XLOOKUP(($G$3*$H$3)/2, $B$12:$B$21, $H$12:$H$21, $H$12, -1) * 2,"N/A") -> N/A | Q4: =IF(OR(AND($G$3>28, $H$3>28), $G$3>35, $H$3>35),_xlfn.XLOOKUP(($G$3*$H$3)/2, $B$12:$B$21, $P$12:$P$21, $P$12, -1) * 2,"N/A") -> N/A | R4: =IF(OR(AND($G$3>28, $H$3>28), $G$3>35, $H$3>35),_xlfn.XLOOKUP(($G$3*$H$3)/2, $B$12:$B$21, $X$12:$X$21, $X$12, -1) * 2,"N/A") -> N/A | S4: 0.3
K5: =_xlfn.XLOOKUP($G$3*$H$3, $B$12:$B$21, $I$12:$I$21, $I$12, -1) -> 19.9 | L5: =_xlfn.XLOOKUP($G$3*$H$3, $B$12:$B$21, $Q$12:$Q$21, $Q$12, -1) -> 24.291333 | M5: =_xlfn.XLOOKUP($G$3*$H$3, $B$12:$B$21, $Y$12:$Y$21, $Y$12, -1) -> 35.762 | N5: 0.25 | P5: =IF(OR(AND($G$3>28, $H$3>28), $G$3>35, $H$3>35),_xlfn.XLOOKUP(($G$3*$H$3)/2, $B$12:$B$21, $I$12:$I$21, $I$12, -1) * 2,"N/A") -> N/A | Q5: =IF(OR(AND($G$3>28, $H$3>28), $G$3>35, $H$3>35),_xlfn.XLOOKUP(($G$3*$H$3)/2, $B$12:$B$21, $Q$12:$Q$21, $Q$12, -1) * 2,"N/A") -> N/A | R5: =IF(OR(AND($G$3>28, $H$3>28), $G$3>35, $H$3>35),_xlfn.XLOOKUP(($G$3*$H$3)/2, $B$12:$B$21, $Y$12:$Y$21, $Y$12, -1) * 2,"N/A") -> N/A | S5: 0.25
A6: The Z-Line Series | P6: DOUBLE SIZE PRICING
A7: MADE-TO-ORDER SIZES
D9: MR-13 1" | L9: MR-13 2" | T9: MR-13 4"
A10: Gross Area | D10: Part | E10: List | F10: Multiplier | K10: Gross Area | L10: Part | M10: List | S10: Gross Area | T10: Part | U10: List
A11: Square Inches | D11: Number | E11: Price | F11: 0.35 | G11: 35% Margin | H11: 30% Margin | I11: 25% Margin | K11: Square Inches | L11: Number | M11: Price | S11: Square Inches | T11: Number | U11: Price
A12: Less than 150" | B12: 0 | C12: 150 | D12: M13SP1A | E12: 28.59 | F12: =E12*$F$11 -> 10.0065 | G12: =(F12/0.65)+0.3 -> 15.694615 | H12: =(F12/0.7)+0.3 -> 14.595 | I12: =(F12/0.75)+0.3 -> 13.642 | K12: Less than 150" | L12: M13SP2A | M12: 36.09 | N12: =M12*$F$11 -> 12.6315 | O12: =(N12/0.65)+0.3 -> 19.733077 | P12: =(N12/0.7)+0.3 -> 18.345 | Q12: =(N12/0.75)+0.3 -> 17.142 | S12: Less than 150" | T12: M13SP4A | U12: 54.8 | V12: =U12*$F$11 -> 19.18 | W12: =(V12/0.65)+0.3 -> 29.807692 | X12: =(V12/0.7)+0.3 -> 27.7 | Y12: =(V12/0.75)+0.3 -> 25.873333
A13: 150-199" | B13: 150 | C13: 199 | D13: M13SP1B | E13: 33.89 | F13: =E13*$F$11 -> 11.8615 | G13: =(F13/0.65)+0.3 -> 18.548462 | H13: =(F13/0.7)+0.3 -> 17.245 | I13: =(F13/0.75)+0.3 -> 16.115333 | K13: 150-199" | L13: M13SP2B | M13: 41.48 | N13: =M13*$F$11 -> 14.518 | O13: =(N13/0.65)+0.3 -> 22.635385 | P13: =(N13/0.7)+0.3 -> 21.04 | Q13: =(N13/0.75)+0.3 -> 19.657333 | S13: 150-199" | T13: M13SP4B | U13: 61.92 | V13: =U13*$F$11 -> 21.672 | W13: =(V13/0.65)+0.3 -> 33.641538 | X13: =(V13/0.7)+0.3 -> 31.26 | Y13: =(V13/0.75)+0.3 -> 29.196
A14: 200-249" | B14: 200 | C14: 249 | D14: M13SP1C | E14: 38.13 | F14: =E14*$F$11 -> 13.3455 | G14: =(F14/0.65)+0.3 -> 20.831538 | H14: =(F14/0.7)+0.3 -> 19.365 | I14: =(F14/0.75)+0.3 -> 18.094 | K14: 200-249" | L14: M13SP2C | M14: 46.7 | N14: =M14*$F$11 -> 16.345 | O14: =(N14/0.65)+0.3 -> 25.446154 | P14: =(N14/0.7)+0.3 -> 23.65 | Q14: =(N14/0.75)+0.3 -> 22.093333 | S14: 200-249" | T14: M13SP4C | U14: 68.9 | V14: =U14*$F$11 -> 24.115 | W14: =(V14/0.65)+0.3 -> 37.4 | X14: =(V14/0.7)+0.3 -> 34.75 | Y14: =(V14/0.75)+0.3 -> 32.453333
A15: 250-299" | B15: 250 | C15: 299 | D15: M13SP1D | E15: 42 | F15: =E15*$F$11 -> 14.7 | G15: =(F15/0.65)+0.3 -> 22.915385 | H15: =(F15/0.7)+0.3 -> 21.3 | I15: =(F15/0.75)+0.3 -> 19.9 | K15: 250-299" | L15: M13SP2D | M15: 51.41 | N15: =M15*$F$11 -> 17.9935 | O15: =(N15/0.65)+0.3 -> 27.982308 | P15: =(N15/0.7)+0.3 -> 26.005 | Q15: =(N15/0.75)+0.3 -> 24.291333 | S15: 250-299" | T15: M13SP4D | U15: 75.99 | V15: =U15*$F$11 -> 26.5965 | W15: =(V15/0.65)+0.3 -> 41.217692 | X15: =(V15/0.7)+0.3 -> 38.295 | Y15: =(V15/0.75)+0.3 -> 35.762
A16: 300-399" | B16: 300 | C16: 399 | D16: M13SP1E | E16: 47.22 | F16: =E16*$F$11 -> 16.527 | G16: =(F16/0.65)+0.3 -> 25.726154 | H16: =(F16/0.7)+0.3 -> 23.91 | I16: =(F16/0.75)+0.3 -> 22.336 | K16: 300-399" | L16: M13SP2E | M16: 57.8 | N16: =M16*$F$11 -> 20.23 | O16: =(N16/0.65)+0.3 -> 31.423077 | P16: =(N16/0.7)+0.3 -> 29.2 | Q16: =(N16/0.75)+0.3 -> 27.273333 | S16: RPSGFLOSS | T16: M13SP4E | U16: 85.78 | V16: =U16*$F$11 -> 30.023 | W16: =(V16/0.65)+0.3 -> 46.489231 | X16: =(V16/0.7)+0.3 -> 43.19 | Y16: =(V16/0.75)+0.3 -> 40.330667
A17: 400-499" | B17: 400 | C17: 499 | D17: M13SP1F | E17: 52.64 | F17: =E17*$F$11 -> 18.424 | G17: =(F17/0.65)+0.3 -> 28.644615 | H17: =(F17/0.7)+0.3 -> 26.62 | I17: =(F17/0.75)+0.3 -> 24.865333 | K17: 400-499" | L17: M13SP2F | M17: 64.4 | N17: =M17*$F$11 -> 22.54 | O17: =(N17/0.65)+0.3 -> 34.976923 | P17: =(N17/0.7)+0.3 -> 32.5 | Q17: =(N17/0.75)+0.3 -> 30.353333 | S17: GFLOSS | T17: M13SP4F | U17: 95.21 | V17: =U17*$F$11 -> 33.3235 | W17: =(V17/0.65)+0.3 -> 51.566923 | X17: =(V17/0.7)+0.3 -> 47.905 | Y17: =(V17/0.75)+0.3 -> 44.731333
A18: 500-599" | B18: 500 | C18: 599 | D18: M13SP1G | E18: 56.45 | F18: =E18*$F$11 -> 19.7575 | G18: =(F18/0.65)+0.3 -> 30.696154 | H18: =(F18/0.7)+0.3 -> 28.525 | I18: =(F18/0.75)+0.3 -> 26.643333 | K18: 500-599" | L18: M13SP2G | M18: 69.14 | N18: =M18*$F$11 -> 24.199 | O18: =(N18/0.65)+0.3 -> 37.529231 | P18: =(N18/0.7)+0.3 -> 34.87 | Q18: =(N18/0.75)+0.3 -> 32.565333 | S18: 500-599" | T18: M13SP4G | U18: 102.22 | V18: =U18*$F$11 -> 35.777 | W18: =(V18/0.65)+0.3 -> 55.341538 | X18: =(V18/0.7)+0.3 -> 51.41 | Y18: =(V18/0.75)+0.3 -> 48.002667
A19: 600-699" | B19: 600 | C19: 699 | D19: M13SP1H | E19: 60.67 | F19: =E19*$F$11 -> 21.2345 | G19: =(F19/0.65)+0.3 -> 32.968462 | H19: =(F19/0.7)+0.3 -> 30.635 | I19: =(F19/0.75)+0.3 -> 28.612667 | K19: 600-699" | L19: M13SP2H | M19: 74.22 | N19: =M19*$F$11 -> 25.977 | O19: =(N19/0.65)+0.3 -> 40.264615 | P19: =(N19/0.7)+0.3 -> 37.41 | Q19: =(N19/0.75)+0.3 -> 34.936 | S19: 600-699" | T19: M13SP4H | U19: 109.36 | V19: =U19*$F$11 -> 38.276 | W19: =(V19/0.65)+0.3 -> 59.186154 | X19: =(V19/0.7)+0.3 -> 54.98 | Y19: =(V19/0.75)+0.3 -> 51.334667
A20: 700-799" | B20: 700 | C20: 799 | D20: M13SP1I | E20: 64.26 | F20: =E20*$F$11 -> 22.491 | G20: =(F20/0.65)+0.3 -> 34.901538 | H20: =(F20/0.7)+0.3 -> 32.43 | I20: =(F20/0.75)+0.3 -> 30.288 | K20: 700-799" | L20: M13SP2I | M20: 78.64 | N20: =M20*$F$11 -> 27.524 | O20: =(N20/0.65)+0.3 -> 42.644615 | P20: =(N20/0.7)+0.3 -> 39.62 | Q20: =(N20/0.75)+0.3 -> 36.998667 | S20: 700-799" | T20: M13SP4I | U20: 116.97 | V20: =U20*$F$11 -> 40.9395 | W20: =(V20/0.65)+0.3 -> 63.283846 | X20: =(V20/0.7)+0.3 -> 58.785 | Y20: =(V20/0.75)+0.3 -> 54.886
A21: 800-899" | B21: 800 | C21: 899 | D21: M13SP1J | E21: 70.6 | F21: =E21*$F$11 -> 24.71 | G21: =(F21/0.65)+0.3 -> 38.315385 | H21: =(F21/0.7)+0.3 -> 35.6 | I21: =(F21/0.75)+0.3 -> 33.246667 | K21: 800-899" | L21: M13SP2J | M21: 86.49 | N21: =M21*$F$11 -> 30.2715 | O21: =(N21/0.65)+0.3 -> 46.871538 | P21: =(N21/0.7)+0.3 -> 43.545 | Q21: =(N21/0.75)+0.3 -> 40.662 | S21: 800-899" | T21: M13SP4J | U21: 128.68 | V21: =U21*$F$11 -> 45.038 | W21: =(V21/0.65)+0.3 -> 69.589231 | X21: =(V21/0.7)+0.3 -> 64.64 | Y21: =(V21/0.75)+0.3 -> 60.350667
A24: *MINIMUM: | D24: 12 Per size; less than 12 per size add +40% to each filter.
D25: Made-To-Order filters are bulk packed.
D26: * The minimum size of a special size is 4" x 4".
A28: *DOUBLE SIZE: | D28: If both dimensions are larger than 24 3/4”, or if either dimension is
D29: larger than 35” it is considered a double size filter .
D30: To figure the price on a double size MR-13 calculate 1/2 of the square
D31: inches for the desired size and then double the list price.
D32: The maximum length is 96".
A34: 6" Special Size MR-13 Pleats: add 55% to 4" list price

Sheet Carbotron 1
J1: List Price Sheet 6CR-W
J2: 46143
C3: AFC COST | D3: 35% Margin | E3: 30% Margin | F3: 25% Margin | J3: Section 6
J4: Product Bulletin 6 CARB
C6: The Z-Line Series CARBOTRON | R6: 80 | S6: 15 | T6: 80
R7: 80 | S7: 5 | T7: 15
C8: PART | D8: 1 STANDARD | E8: LIST | F8: Multiplier | J8: CARTON | R8: 112 | S8: 15 | T8: 5
C9: NUMBER | D9: SIZES | E9: PRICE | F9: 0.31 | J9: QUANTITY | R9: 28 | S9: 5 | T9: 80
C10: ZLN101014AC | D10: 10 X 10 X 1 | E10: 24.23 | F10: =E10*$F$9 -> 7.5113 | G10: =(F10/0.65)+0.3 -> 11.855846 | H10: =(F10/0.7)+0.3 -> 11.030429 | I10: =(F10/0.75)+0.3 -> 10.315067 | J10: 12 | R10: 80 | S10: 15 | T10: 15
C11: ZLN102014AC | D11: 10 X 20 X 1 | E11: 25.44 | F11: =E11*$F$9 -> 7.8864 | G11: =(F11/0.65)+0.3 -> 12.432923 | H11: =(F11/0.7)+0.3 -> 11.566286 | I11: =(F11/0.75)+0.3 -> 10.8152 | J11: 12 | R11: 80 | S11: 5 | T11: 5
C12: ZLN102414AC | D12: 10 X 24 X 1 | E12: 39.07 | F12: =E12*$F$9 -> 12.1117 | G12: =(F12/0.65)+0.3 -> 18.933385 | H12: =(F12/0.7)+0.3 -> 17.602429 | I12: =(F12/0.75)+0.3 -> 16.448933 | J12: 12 | R12: 112 | S12: 15 | T12: 112
C13: ZLN103014AC | D13: 10 X 30 X 1 | E13: 40.1 | F13: =E13*$F$9 -> 12.431 | G13: =(F13/0.65)+0.3 -> 19.424615 | H13: =(F13/0.7)+0.3 -> 18.058571 | I13: =(F13/0.75)+0.3 -> 16.874667 | J13: 12 | R13: 28 | S13: 15 | T13: 28
C14: ZLN121214AC | D14: 12 X 12 X 1 | E14: 27.52 | F14: =E14*$F$9 -> 8.5312 | G14: =(F14/0.65)+0.3 -> 13.424923 | H14: =(F14/0.7)+0.3 -> 12.487429 | I14: =(F14/0.75)+0.3 -> 11.674933 | J14: 12 | R14: 60 | S14: 16 | T14: 80
C15: ZLN122014AC | D15: 12 X 20 X 1 | E15: 26.73 | F15: =E15*$F$9 -> 8.2863 | G15: =(F15/0.65)+0.3 -> 13.048154 | H15: =(F15/0.7)+0.3 -> 12.137571 | I15: =(F15/0.75)+0.3 -> 11.3484 | J15: 12 | R15: 60 | S15: 16 | T15: 15
C16: ZLN122414AC | D16: 12 X 24 X 1 | E16: 22.73 | F16: =E16*$F$9 -> 7.0463 | G16: =(F16/0.65)+0.3 -> 11.140462 | H16: =(F16/0.7)+0.3 -> 10.366143 | I16: =(F16/0.75)+0.3 -> 9.6950667 | J16: 12 | R16: 128 | S16: 16 | T16: 5
C17: ZLN122514AC | D17: 12 X 25 X 1 | E17: 24.33 | F17: =E17*$F$9 -> 7.5423 | G17: =(F17/0.65)+0.3 -> 11.903538 | H17: =(F17/0.7)+0.3 -> 11.074714 | I17: =(F17/0.75)+0.3 -> 10.3564 | J17: 12 | R17: 48 | S17: 16 | T17: 80
C18: ZLN123014AC | D18: 12 X 30 X 1 | E18: 40.1 | F18: =E18*$F$9 -> 12.431 | G18: =(F18/0.65)+0.3 -> 19.424615 | H18: =(F18/0.7)+0.3 -> 18.058571 | I18: =(F18/0.75)+0.3 -> 16.874667 | J18: 12 | R18: 64 | S18: 1 | T18: 15
C19: ZLN141414AC | D19: 14 X 14 X 1 | E19: 28.66 | F19: =E19*$F$9 -> 8.8846 | G19: =(F19/0.65)+0.3 -> 13.968615 | H19: =(F19/0.7)+0.3 -> 12.992286 | I19: =(F19/0.75)+0.3 -> 12.146133 | J19: 12 | R19: 64 | S19: 1 | T19: 5
C20: ZLN142414AC | D20: 14 X 24 X 1 | E20: 33.02 | F20: =E20*$F$9 -> 10.2362 | G20: =(F20/0.65)+0.3 -> 16.048 | H20: =(F20/0.7)+0.3 -> 14.923143 | I20: =(F20/0.75)+0.3 -> 13.948267 | J20: 12 | R20: 96 | S20: 1 | T20: 112
C21: ZLN142014AC | D21: 14 X 20 X 1 | E21: 23.62 | F21: =E21*$F$9 -> 7.3222 | G21: =(F21/0.65)+0.3 -> 11.564923 | H21: =(F21/0.7)+0.3 -> 10.760286 | I21: =(F21/0.75)+0.3 -> 10.062933 | J21: 12 | R21: 32 | S21: 1 | T21: 28
C22: ZLN142514AC | D22: 14 X 25 X 1 | E22: 25.15 | F22: =E22*$F$9 -> 7.7965 | G22: =(F22/0.65)+0.3 -> 12.294615 | H22: =(F22/0.7)+0.3 -> 11.437857 | I22: =(F22/0.75)+0.3 -> 10.695333 | J22: 12 | R22: 64 | S22: =SUM(S6:S21)+20 -> 178 | T22: 60
C23: ZLN143014AC | D23: 14 x 30 x 1 | E23: 45.65 | F23: =E23*$F$9 -> 14.1515 | G23: =(F23/0.65)+0.3 -> 22.071538 | H23: =(F23/0.7)+0.3 -> 20.516429 | I23: =(F23/0.75)+0.3 -> 19.168667 | J23: 12 | R23: 64 | T23: 15
C24: ZLN152014AC | D24: 15 X 20 X 1 | E24: 23.87 | F24: =E24*$F$9 -> 7.3997 | G24: =(F24/0.65)+0.3 -> 11.684154 | H24: =(F24/0.7)+0.3 -> 10.871 | I24: =(F24/0.75)+0.3 -> 10.166267 | J24: 12 | R24: 96 | T24: 60
C25: ZLN1530K14AC | D25: 15 x 30 5/8 x 1 | E25: 45.65 | F25: =E25*$F$9 -> 14.1515 | G25: =(F25/0.65)+0.3 -> 22.071538 | H25: =(F25/0.7)+0.3 -> 20.516429 | I25: =(F25/0.75)+0.3 -> 19.168667 | J25: 12 | R25: 32 | T25: 15
C26: ZLN161614AC | D26: 16 X 16 X 1 | E26: 35.47 | F26: =E26*$F$9 -> 10.9957 | G26: =(F26/0.65)+0.3 -> 17.216462 | H26: =(F26/0.7)+0.3 -> 16.008143 | I26: =(F26/0.75)+0.3 -> 14.960933 | J26: 12 | R26: 4 | T26: 128
C27: ZLN162014AC | D27: 16 X 20 X 1 | E27: 23.62 | F27: =E27*$F$9 -> 7.3222 | G27: =(F27/0.65)+0.3 -> 11.564923 | H27: =(F27/0.7)+0.3 -> 10.760286 | I27: =(F27/0.75)+0.3 -> 10.062933 | J27: 12 | R27: 4 | T27: 48
C28: ZLN162414AC | D28: 16 X 24 X 1 | E28: 38.06 | F28: =E28*$F$9 -> 11.7986 | G28: =(F28/0.65)+0.3 -> 18.451692 | H28: =(F28/0.7)+0.3 -> 17.155143 | I28: =(F28/0.75)+0.3 -> 16.031467 | J28: 12 | R28: 4 | T28: 64
C29: ZLN162514AC | D29: 16 X 25 X 1 | E29: 27.62 | F29: =E29*$F$9 -> 8.5622 | G29: =(F29/0.65)+0.3 -> 13.472615 | H29: =(F29/0.7)+0.3 -> 12.531714 | I29: =(F29/0.75)+0.3 -> 11.716267 | J29: 12 | R29: 4 | T29: 16
C30: ZLN163014AC | D30: 16 x 30 x 1 | E30: 45.65 | F30: =E30*$F$9 -> 14.1515 | G30: =(F30/0.65)+0.3 -> 22.071538 | H30: =(F30/0.7)+0.3 -> 20.516429 | I30: =(F30/0.75)+0.3 -> 19.168667 | J30: 12 | R30: =SUM(R6:R29) -> 1424 | T30: 64
C31: ZLN181814AC | D31: 18 X 18 X 1 | E31: 40.1 | F31: =E31*$F$9 -> 12.431 | G31: =(F31/0.65)+0.3 -> 19.424615 | H31: =(F31/0.7)+0.3 -> 18.058571 | I31: =(F31/0.75)+0.3 -> 16.874667 | J31: 12 | T31: 16
C32: ZLN182014AC | D32: 18 X 20 X 1 | E32: 43.4 | F32: =E32*$F$9 -> 13.454 | G32: =(F32/0.65)+0.3 -> 20.998462 | H32: =(F32/0.7)+0.3 -> 19.52 | I32: =(F32/0.75)+0.3 -> 18.238667 | J32: 12 | R32: =SUM(R30,S22) -> 1602 | T32: 96
C33: ZLN182414AC | D33: 18 X 24 X 1 | E33: 30.35 | F33: =E33*$F$9 -> 9.4085 | G33: =(F33/0.65)+0.3 -> 14.774615 | H33: =(F33/0.7)+0.3 -> 13.740714 | I33: =(F33/0.75)+0.3 -> 12.844667 | J33: 12 | T33: 32
C34: ZLN182514AC | D34: 18 X 25 X 1 | E34: 33.37 | F34: =E34*$F$9 -> 10.3447 | G34: =(F34/0.65)+0.3 -> 16.214923 | H34: =(F34/0.7)+0.3 -> 15.078143 | I34: =(F34/0.75)+0.3 -> 14.092933 | J34: 12 | T34: 64
C35: ZLN183014AC | D35: 18 X 30 X 1 | E35: 47.82 | F35: =E35*$F$9 -> 14.8242 | G35: =(F35/0.65)+0.3 -> 23.106462 | H35: =(F35/0.7)+0.3 -> 21.477429 | I35: =(F35/0.75)+0.3 -> 20.0656 | J35: 12 | T35: 16
C36: ZLN202014AC | D36: 20 X 20 X 1 | E36: 27.62 | F36: =E36*$F$9 -> 8.5622 | G36: =(F36/0.65)+0.3 -> 13.472615 | H36: =(F36/0.7)+0.3 -> 12.531714 | I36: =(F36/0.75)+0.3 -> 11.716267 | J36: 12 | T36: 64
C37: ZLN202214AC | D37: 20 X 22 X 1 | E37: 38.36 | F37: =E37*$F$9 -> 11.8916 | G37: =(F37/0.65)+0.3 -> 18.594769 | H37: =(F37/0.7)+0.3 -> 17.288 | I37: =(F37/0.75)+0.3 -> 16.155467 | J37: 12 | T37: 16
C38: ZLN202414AC | D38: 20 X 24 X 1 | E38: 33.12 | F38: =E38*$F$9 -> 10.2672 | G38: =(F38/0.65)+0.3 -> 16.095692 | H38: =(F38/0.7)+0.3 -> 14.967429 | I38: =(F38/0.75)+0.3 -> 13.9896 | J38: 12 | T38: 96
C39: ZLN202514AC | D39: 20 X 25 X 1 | E39: 32.66 | F39: =E39*$F$9 -> 10.1246 | G39: =(F39/0.65)+0.3 -> 15.876308 | H39: =(F39/0.7)+0.3 -> 14.763714 | I39: =(F39/0.75)+0.3 -> 13.799467 | J39: 12 | T39: 32
C40: ZLN203014AC | D40: 20 X 30 X 1 | E40: 42.79 | F40: =E40*$F$9 -> 13.2649 | G40: =(F40/0.65)+0.3 -> 20.707538 | H40: =(F40/0.7)+0.3 -> 19.249857 | I40: =(F40/0.75)+0.3 -> 17.986533 | J40: 12 | T40: 4
C41: ZLN222214AC | D41: 22 X 22 X 1 | E41: 44.52 | F41: =E41*$F$9 -> 13.8012 | G41: =(F41/0.65)+0.3 -> 21.532615 | H41: =(F41/0.7)+0.3 -> 20.016 | I41: =(F41/0.75)+0.3 -> 18.7016 | J41: 12 | T41: 4
C42: ZLN242414AC | D42: 24 X 24 X 1 | E42: 37.13 | F42: =E42*$F$9 -> 11.5103 | G42: =(F42/0.65)+0.3 -> 18.008154 | H42: =(F42/0.7)+0.3 -> 16.743286 | I42: =(F42/0.75)+0.3 -> 15.647067 | J42: 12 | T42: 1
C43: ZLN243014AC | D43: 24 X 30 X 1 | E43: 55.73 | F43: =E43*$F$9 -> 17.2763 | G43: =(F43/0.65)+0.3 -> 26.878923 | H43: =(F43/0.7)+0.3 -> 24.980429 | I43: =(F43/0.75)+0.3 -> 23.335067 | J43: 12 | T43: 1
C44: ZLN252514AC | D44: 25 X 25 X 1 | E44: 39.74 | F44: =E44*$F$9 -> 12.3194 | G44: =(F44/0.65)+0.3 -> 19.252923 | H44: =(F44/0.7)+0.3 -> 17.899143 | I44: =(F44/0.75)+0.3 -> 16.725867 | J44: 12 | T44: 4
T45: 4
C46: PART | D46: 2 STANDARD | E46: LIST | T46: 1
C47: NUMBER | D47: SIZES | E47: PRICE | T47: 1
C48: ZLN102024AC | D48: 10 X 20 X 2 | E48: 26.25 | F48: =E48*$F$9 -> 8.1375 | G48: =(F48/0.65)+0.3 -> 12.819231 | H48: =(F48/0.7)+0.3 -> 11.925 | I48: =(F48/0.75)+0.3 -> 11.15 | J48: 12 | T48: =SUM(T6:T47) -> 1602
C49: ZLN121224AC | D49: 12 X 12 X 2 | E49: 26.14 | F49: =E49*$F$9 -> 8.1034 | G49: =(F49/0.65)+0.3 -> 12.766769 | H49: =(F49/0.7)+0.3 -> 11.876286 | I49: =(F49/0.75)+0.3 -> 11.104533 | J49: 12
C50: ZLN122024AC | D50: 12 X 20 X 2 | E50: 27.93 | F50: =E50*$F$9 -> 8.6583 | G50: =(F50/0.65)+0.3 -> 13.620462 | H50: =(F50/0.7)+0.3 -> 12.669 | I50: =(F50/0.75)+0.3 -> 11.8444 | J50: 12
C51: ZLN122424AC | D51: 12 X 24 X 2 | E51: 30.83 | F51: =E51*$F$9 -> 9.5573 | G51: =(F51/0.65)+0.3 -> 15.003538 | H51: =(F51/0.7)+0.3 -> 13.953286 | I51: =(F51/0.75)+0.3 -> 13.043067 | J51: 12
C52: ZLN142024AC | D52: 14 X 20 X 2 | E52: 32.85 | F52: =E52*$F$9 -> 10.1835 | G52: =(F52/0.65)+0.3 -> 15.966923 | H52: =(F52/0.7)+0.3 -> 14.847857 | I52: =(F52/0.75)+0.3 -> 13.878 | J52: 12
C53: ZLN142524AC | D53: 14 X 25 X 2 | E53: 35 | F53: =E53*$F$9 -> 10.85 | G53: =(F53/0.65)+0.3 -> 16.992308 | H53: =(F53/0.7)+0.3 -> 15.8 | I53: =(F53/0.75)+0.3 -> 14.766667 | J53: 12
C54: ZLN152024AC | D54: 15 X 20 X 2 | E54: 33.24 | F54: =E54*$F$9 -> 10.3044 | G54: =(F54/0.65)+0.3 -> 16.152923 | H54: =(F54/0.7)+0.3 -> 15.020571 | I54: =(F54/0.75)+0.3 -> 14.0392 | J54: 12
C55: ZLN161624AC | D55: 16 X 16 X 2 | E55: 34.38 | F55: =E55*$F$9 -> 10.6578 | G55: =(F55/0.65)+0.3 -> 16.696615 | H55: =(F55/0.7)+0.3 -> 15.525429 | I55: =(F55/0.75)+0.3 -> 14.5104 | J55: 12
C56: ZLN162024AC | D56: 16 X 20 X 2 | E56: 32.7 | F56: =E56*$F$9 -> 10.137 | G56: =(F56/0.65)+0.3 -> 15.895385 | H56: =(F56/0.7)+0.3 -> 14.781429 | I56: =(F56/0.75)+0.3 -> 13.816 | J56: 12
C57: ZLN162424AC | D57: 16 X 24 X 2 | E57: 43.03 | F57: =E57*$F$9 -> 13.3393 | G57: =(F57/0.65)+0.3 -> 20.822 | H57: =(F57/0.7)+0.3 -> 19.356143 | I57: =(F57/0.75)+0.3 -> 18.085733 | J57: 12
C58: ZLN162524AC | D58: 16 X 25 X 2 | E58: 39.45 | F58: =E58*$F$9 -> 12.2295 | G58: =(F58/0.65)+0.3 -> 19.114615 | H58: =(F58/0.7)+0.3 -> 17.770714 | I58: =(F58/0.75)+0.3 -> 16.606 | J58: 12
C59: ZLN181824AC | D59: 18 X 18 X 2 | E59: 41.27 | F59: =E59*$F$9 -> 12.7937 | G59: =(F59/0.65)+0.3 -> 19.982615 | H59: =(F59/0.7)+0.3 -> 18.576714 | I59: =(F59/0.75)+0.3 -> 17.358267 | J59: 12
C60: ZLN182024AC | D60: 18 X 20 X 2 | E60: 44.41 | F60: =E60*$F$9 -> 13.7671 | G60: =(F60/0.65)+0.3 -> 21.480154 | H60: =(F60/0.7)+0.3 -> 19.967286 | I60: =(F60/0.75)+0.3 -> 18.656133 | J60: 12
... C68: ZLN252524AC | D68: 25 X 25 X 2 | E68: 58.07 | F68: =E68*$F$9 -> 18.0017 | G68: =(F68/0.65)+0.3 -> 27.994923 | H68: =(F68/0.7)+0.3 -> 26.016714 | I68: =(F68/0.75)+0.3 -> 24.302267 | J68: 12
C70: PART | D70: 4 STANDARD | E70: LIST
C71: NUMBER | D71: SIZES | E71: PRICE
C72: ZLN122444AC | D72: 12 X 24 X 4 | E72: 47.02 | F72: =E72*$F$9 -> 14.5762 | G72: =(F72/0.65)+0.3 -> 22.724923 | H72: =(F72/0.7)+0.3 -> 21.123143 | I72: =(F72/0.75)+0.3 -> 19.734933 | J72: 6
C73: ZLN162044AC | D73: 16 X 20 X 4 | E73: 49.41 | F73: =E73*$F$9 -> 15.3171 | G73: =(F73/0.65)+0.3 -> 23.864769 | H73: =(F73/0.7)+0.3 -> 22.181571 | I73: =(F73/0.75)+0.3 -> 20.7228 | J73: 6
C74: ZLN162544AC | D74: 16 X 25 X 4 | E74: 59.64 | F74: =E74*$F$9 -> 18.4884 | G74: =(F74/0.65)+0.3 -> 28.743692 | H74: =(F74/0.7)+0.3 -> 26.712 | I74: =(F74/0.75)+0.3 -> 24.9512 | J74: 6
C75: ZLN182444AC | D75: 18 X 24 X 4 | E75: 64.61 | F75: =E75*$F$9 -> 20.0291 | G75: =(F75/0.65)+0.3 -> 31.114 | H75: =(F75/0.7)+0.3 -> 28.913 | I75: =(F75/0.75)+0.3 -> 27.005467 | J75: 6
C76: ZLN202044AC | D76: 20 X 20 X 4 | E76: 59.64 | F76: =E76*$F$9 -> 18.4884 | G76: =(F76/0.65)+0.3 -> 28.743692 | H76: =(F76/0.7)+0.3 -> 26.712 | I76: =(F76/0.75)+0.3 -> 24.9512 | J76: 6
C77: ZLN202444AC | D77: 20 X 24 X 4 | E77: 72.43 | F77: =E77*$F$9 -> 22.4533 | G77: =(F77/0.65)+0.3 -> 34.843538 | H77: =(F77/0.7)+0.3 -> 32.376143 | I77: =(F77/0.75)+0.3 -> 30.237733 | J77: 6
C78: ZLN202544AC | D78: 20 X 25 X 4 | E78: 71.83 | F78: =E78*$F$9 -> 22.2673 | G78: =(F78/0.65)+0.3 -> 34.557385 | H78: =(F78/0.7)+0.3 -> 32.110429 | I78: =(F78/0.75)+0.3 -> 29.989733 | J78: 6
C79: ZLN242444AC | D79: 24 X 24 X 4 | E79: 81.55 | F79: =E79*$F$9 -> 25.2805 | G79: =(F79/0.65)+0.3 -> 39.193077 | H79: =(F79/0.7)+0.3 -> 36.415 | I79: =(F79/0.75)+0.3 -> 34.007333 | J79: 6
A2276: CAR2 | B2276: 6 | E2276: 32.94
A2277: CAR2 | B2277: 6 | E2277: HWP202042PK
A2278: CAR2 | B2278: 6 | E2278: HWP202542PK
A2279: CAR2 | B2279: 6
A2280: CAR2 | B2280: 6 | E2280: HWP13204M112PK
A2281: CAR2 | B2281: 6 | E2281: HWP16204M112PK
A2282: CAR2 | B2282: 6 | E2282: HWP16254M112PK
A2283: CAR2 | B2283: 6 | E2283: HWP20204M112PK
A2284: CAR2 | B2284: 6 | E2284: HWP20254M112PK
A2285: CAR2 | B2285: 6 | E2285: HWP20204M132PK
A2286: CAR2 | B2286: 6 | E2286: HWP20254M132PK
A2287: CAR2 | B2287: 6
A2288: CAR2 | B2288: 6
A2289: CAR2 | B2289: 6
A2290: CAR2 | B2290: 6
A2291: CAR2 | B2291: 6 | E2291: 2-Pack
A2292: CAR2 | B2292: 6 | E2292: HWR121242PK
A2293: CAR2 | B2293: 6 | E2293: HWR122442PK
A2294: CAR2 | B2294: 6 | E2294: HWR143042PK
A2295: CAR2 | B2295: 6 | E2295: HWR162042PK
A2296: CAR2 | B2296: 6 | E2296: HWR162542PK
A2297: CAR2 | B2297: 6 | E2297: HWR181842PK
A2298: CAR2 | B2298: 6 | E2298: HWR182442PK
A2299: CAR2 | B2299: 6 | E2299: HWR183042PK
A2300: CAR2 | B2300: 6 | E2300: HWR202042PK
A2301: CAR2 | B2301: 6 | E2301: HWR202442PK
A2302: CAR2 | B2302: 6 | E2302: HWR202542PK

Sheet Carbotron 2
G2: SIZES | H2: H | I2: L | J2: W | K2: TOTAL | L2: PRICE 1" | M2: PRICE 2" | N2: PRICE 4" | Q2: PRICE 1" | R2: PRICE 2" | S2: PRICE 4"
A3: AFC COST | B3: 35% Margin | C3: 30% Margin | D3: 25% Margin | H3: 17 | I3: 22 | J3: 1 | K3: =H3*I3 -> 374 | L3: =_xlfn.XLOOKUP($H$3*$I$3, $B$12:$B$20, $G$12:$G$20, $G$12, -1) -> 39.489508 | M3: =_xlfn.XLOOKUP($H$3*$I$3, $B$12:$B$20, $O$12:$O$20, $O$12, -1) -> 41.669046 | N3: =_xlfn.XLOOKUP($H$3*$I$3, $B$12:$B$20, $W$12:$W$20, $W$12, -1) -> 82.855292 | O3: 0.35 | Q3: =IF(OR(AND($H$3>28, $I$3>28), $H$3>35, $I$3>35),_xlfn.XLOOKUP(($H$3*$I$3)/2, $B$12:$B$20, $G$12:$G$20, $G$12, -1) * 2,"N/A") -> N/A | R3: =IF(OR(AND($H$3>28, $I$3>28), $H$3>35, $I$3>35),_xlfn.XLOOKUP(($H$3*$I$3)/2, $B$12:$B$20, $O$12:$O$20, $O$12, -1) * 2,"N/A") -> N/A | S3: =IF(OR(AND($H$3>28, $I$3>28), $H$3>35, $I$3>35),_xlfn.XLOOKUP(($H$3*$I$3)/2, $B$12:$B$20, $W$12:$W$20, $W$12, -1) * 2,"N/A") -> N/A | T3: 0.35
L4: =_xlfn.XLOOKUP($H$3*$I$3, $B$12:$B$20, $H$12:$H$20, $H$12, -1) -> 36.690257 | M4: =_xlfn.XLOOKUP($H$3*$I$3, $B$12:$B$20, $P$12:$P$20, $P$12, -1) -> 38.714114 | N4: =_xlfn.XLOOKUP($H$3*$I$3, $B$12:$B$20, $X$12:$X$20, $XX12, -1) -> 76.958486 | O4: 0.3 | Q4: =IF(OR(AND($H$3>28, $I$3>28), $H$3>35, $I$3>35),_xlfn.XLOOKUP(($H$3*$I$3)/2, $B$12:$B$20, $H$12:$H$20, $H$12, -1) * 2,"N/A") -> N/A | R4: =IF(OR(AND($H$3>28, $I$3>28), $H$3>35, $I$3>35),_xlfn.XLOOKUP(($H$3*$I$3)/2, $B$12:$B$20, $P$12:$P$20, $P$12, -1) * 2,"N/A") -> N/A | S4: =IF(OR(AND($H$3>28, $I$3>28), $H$3>35, $I$3>35),_xlfn.XLOOKUP(($H$3*$I$3)/2, $B$12:$B$20, $X$12:$X$20, $X$12, -1) * 2,"N/A") -> N/A | T4: 0.3
L5: =_xlfn.XLOOKUP($H$3*$I$3, $B$12:$B$20, $I$12:$I$20, $I$12, -1) -> 34.26424 | M5: =_xlfn.XLOOKUP($H$3*$I$3, $B$12:$B$20, $Q$12:$Q$20, $Q$12, -1) -> 36.153173 | N5: =_xlfn.XLOOKUP($H$3*$I$3, $B$12:$B$20, $Y$12:$Y$20, $Y$12, -1) -> 71.84792 | O5: 0.25 | Q5: =IF(OR(AND($H$3>28, $I$3>28), $H$3>35, $I$3>35),_xlfn.XLOOKUP(($H$3*$I$3)/2, $B$12:$B$20, $I$12:$I$20, $I$12, -1) * 2,"N/A") -> N/A | R5: =IF(OR(AND($H$3>28, $I$3>28), $H$3>35, $I$3>35),_xlfn.XLOOKUP(($H$3*$I$3)/2, $B$12:$B$20, $Q$12:$Q$20, $Q$12, -1) * 2,"N/A") -> N/A | S5: =IF(OR(AND($H$3>28, $I$3>28), $H$3>35, $I$3>35),_xlfn.XLOOKUP(($H$3*$I$3)/2, $B$12:$B$20, $Y$12:$Y$20, $Y$12, -1) * 2,"N/A") -> N/A | T5: 0.25
A6: The Z-Line Series | Q6: DOUBLE SIZE PRICING
A7: MADE-TO-ORDER SIZES
A9: CARBOTRON 1" | K9: CARBOTRON 2" | S9: CARBOTRON 4"
A10: GROSS AREA | D10: Part | E10: List | F10: Multiplier | K10: GROSS AREA | L10: Part | M10: List | S10: GROSS AREA | T10: Part | U10: List
A11: SQ. INCHES | D11: Number | E11: Price | F11: 0.457 | K11: SQ. INCHES | L11: Number | M11: Price | S11: SQ. INCHES | T11: Number | U11: Price
A12: LESS THAN 150 | B12: 0 | C12: 150 | D12: ZLNSP14ACA | E12: 35.3 | F12: =E12*$F$11 -> 16.1321 | G12: =(F12/0.65)+0.3 -> 25.118615 | H12: =(F12/0.7)+0.3 -> 23.345857 | I12: =(F12/0.75)+0.3 -> 21.809467 | K12: LESS THAN 150 | L12: ZLNSP24ACA | M12: 37.24 | N12: =M12*$F$11 -> 17.01868 | O12: =(N12/0.65)+0.3 -> 26.482585 | P12: =(N12/0.7)+0.3 -> 24.6124 | Q12: =(N12/0.75)+0.3 -> 22.991573 | S12: LESS THAN 150 | T12: ZLNSP44ACA | U12: 74.85 | V12: =U12*$F$11 -> 34.20645 | W12: =(V12/0.65)+0.3 -> 52.925308 | X12: =(V12/0.7)+0.3 -> 49.166357 | Y12: =(V12/0.75)+0.3 -> 45.9086
A13: 150-199 | B13: 150 | C13: 199 | D13: ZLNSP14ACB | E13: 39.82 | F13: =E13*$F$11 -> 18.19774 | G13: =(F13/0.65)+0.3 -> 28.296523 | H13: =(F13/0.7)+0.3 -> 26.296771 | I13: =(F13/0.75)+0.3 -> 24.563653 | K13: 150-199 | L13: ZLNSP24ACB | M13: 42.06 | N13: =M13*$F$11 -> 19.22142 | O13: =(N13/0.65)+0.3 -> 29.871415 | P13: =(N13/0.7)+0.3 -> 27.759171 | Q13: =(N13/0.75)+0.3 -> 25.92856 | S13: 150-199 | T13: ZLNSP44ACB | U13: 84.72 | V13: =U13*$F$11 -> 38.71704 | W13: =(V13/0.65)+0.3 -> 59.864677 | X13: =(V13/0.7)+0.3 -> 55.610057 | Y13: =(V13/0.75)+0.3 -> 51.92272
A14: 200-249 | B14: 200 | C14: 249 | D14: ZLNSP14ACC | E14: 44.85 | F14: =E14*$F$11 -> 20.49645 | G14: =(F14/0.65)+0.3 -> 31.833 | H14: =(F14/0.7)+0.3 -> 29.580643 | I14: =(F14/0.75)+0.3 -> 27.6286 | K14: 200-249 | L14: ZLNSP24ACC | M14: 47.35 | N14: =M14*$F$11 -> 21.63895 | O14: =(N14/0.65)+0.3 -> 33.590692 | P14: =(N14/0.7)+0.3 -> 31.212786 | Q14: =(N14/0.75)+0.3 -> 29.151933 | S14: 200-249 | T14: ZLNSP44ACC | U14: 94.39 | V14: =U14*$F$11 -> 43.13623 | W14: =(V14/0.65)+0.3 -> 66.663431 | X14: =(V14/0.7)+0.3 -> 61.923186 | Y14: =(V14/0.75)+0.3 -> 57.814973
A15: 250-299 | B15: 250 | C15: 299 | D15: ZLNSP14ACD | E15: 49.34 | F15: =E15*$F$11 -> 22.54838 | G15: =(F15/0.65)+0.3 -> 34.989815 | H15: =(F15/0.7)+0.3 -> 32.511971 | I15: =(F15/0.75)+0.3 -> 30.364507 | K15: 250-299 | L15: ZLNSP24ACD | M15: 52.11 | N15: =M15*$F$11 -> 23.81427 | O15: =(N15/0.65)+0.3 -> 36.937338 | P15: =(N15/0.7)+0.3 -> 34.320386 | Q15: =(N15/0.75)+0.3 -> 32.05236 | S15: 250-299 | T15: ZLNSP44ACD | U15: 104.15 | V15: =U15*$F$11 -> 47.59655 | W15: =(V15/0.65)+0.3 -> 73.525462 | X15: =(V15/0.7)+0.3 -> 68.295071 | Y15: =(V15/0.75)+0.3 -> 63.762067
A16: 300-399 | B16: 300 | C16: 399 | D16: ZLNSP14ACE | E16: 55.74 | F16: =E16*$F$11 -> 25.47318 | G16: =(F16/0.65)+0.3 -> 39.489508 | H16: =(F16/0.7)+0.3 -> 36.690257 | I16: =(F16/0.75)+0.3 -> 34.26424 | K16: 300-399 | L16: ZLNSP24ACE | M16: 58.84 | N16: =M16*$F$11 -> 26.88988 | O16: =(N16/0.65)+0.3 -> 41.669046 | P16: =(N16/0.7)+0.3 -> 38.714114 | Q16: =(N16/0.75)+0.3 -> 36.153173 | S16: 300-399 | T16: ZLNSP44ACE | U16: 117.42 | V16: =U16*$F$11 -> 53.66094 | W16: =(V16/0.65)+0.3 -> 82.855292 | X16: =(V16/0.7)+0.3 -> 76.958486 | Y16: =(V16/0.75)+0.3 -> 71.84792
A17: 400-499 | B17: 400 | C17: 499 | D17: ZLNSP14ACF | E17: 61.93 | F17: =E17*$F$11 -> 28.30201 | G17: =(F17/0.65)+0.3 -> 43.841554 | H17: =(F17/0.7)+0.3 -> 40.731443 | I17: =(F17/0.75)+0.3 -> 38.036013 | K17: 400-499 | L17: ZLNSP24ACF | M17: 65.38 | N17: =M17*$F$11 -> 29.87866 | O17: =(N17/0.65)+0.3 -> 46.267169 | P17: =(N17/0.7)+0.3 -> 42.9838 | Q17: =(N17/0.75)+0.3 -> 40.138213 | S17: 400-499 | T17: ZLNSP44ACF | U17: 130.32 | V17: =U17*$F$11 -> 59.55624 | W17: =(V17/0.65)+0.3 -> 91.924985 | X17: =(V17/0.7)+0.3 -> 85.380343 | Y17: =(V17/0.75)+0.3 -> 79.70832
A18: 500-599 | B18: 500 | C18: 599 | D18: ZLNSP14ACG | E18: 66.52 | F18: =E18*$F$11 -> 30.39964 | G18: =(F18/0.65)+0.3 -> 47.068677 | H18: =(F18/0.7)+0.3 -> 43.728057 | I18: =(F18/0.75)+0.3 -> 40.832853 | K18: 500-599 | L18: ZLNSP24ACG | M18: 70.22 | N18: =M18*$F$11 -> 32.09054 | O18: =(N18/0.65)+0.3 -> 49.670062 | P18: =(N18/0.7)+0.3 -> 46.143629 | Q18: =(N18/0.75)+0.3 -> 43.087387 | S18: 500-599 | T18: ZLNSP44ACG | U18: 140.07 | V18: =U18*$F$11 -> 64.01199 | W18: =(V18/0.65)+0.3 -> 98.779985 | X18: =(V18/0.7)+0.3 -> 91.7457 | Y18: =(V18/0.75)+0.3 -> 85.64932
A19: 600-699 | B19: 600 | C19: 699 | D19: ZLNSP14ACH | E19: 71.41 | F19: =E19*$F$11 -> 32.63437 | G19: =(F19/0.65)+0.3 -> 50.506723 | H19: =(F19/0.7)+0.3 -> 46.920529 | I19: =(F19/0.75)+0.3 -> 43.812493 | K19: 600-699 | L19: ZLNSP24ACH | M19: 75.41 | N19: =M19*$F$11 -> 34.46237 | O19: =(N19/0.65)+0.3 -> 53.319031 | P19: =(N19/0.7)+0.3 -> 49.531957 | Q19: =(N19/0.75)+0.3 -> 46.249827 | S19: 600-699 | T19: ZLNSP44ACH | U19: 149.78 | V19: =U19*$F$11 -> 68.44946 | W19: =(V19/0.65)+0.3 -> 105.60686 | X19: =(V19/0.7)+0.3 -> 98.084943 | Y19: =(V19/0.75)+0.3 -> 91.565947
A20: 700-882 | B20: 700 | C20: 88 | D20: ZLNSP14ACI | E20: 75.56 | F20: =E20*$F$11 -> 34.53092 | G20: =(F20/0.65)+0.3 -> 53.424492 | H20: =(F20/0.7)+0.3 -> 49.629886 | I20: =(F20/0.75)+0.3 -> 46.341227 | K20: 700-882 | L20: ZLNSP24ACI | M20: 79.72 | N20: =M20*$F$11 -> 36.43204 | O20: =(N20/0.65)+0.3 -> 56.349292 | P20: =(N20/0.7)+0.3 -> 52.345771 | Q20: =(N20/0.75)+0.3 -> 48.876053 | S20: 700-882 | T20: ZLNSP44ACI | U20: 160.09 | V20: =U20*$F$11 -> 73.16113 | W20: =(V20/0.65)+0.3 -> 112.85558 | X20: =(V20/0.7)+0.3 -> 104.8159 | Y20: =(V20/0.75)+0.3 -> 97.848173
A23: Minimum of 12 pieces per size; less than 12 add +40% to each filter.
A25: * DOUBLE SIZE: Z-Line Series "Carbotron" Pleated Filters
A26: If both dimensions are larger than 25”, or if either dimension
A27: is larger than 35” it is considered a double size filter.
A28: To figure the price on a double size Carbotron, calculate 1/2 of the square
A29: inches for the desired size and then double the list price.
A30: The maximum length dimension is 96".

Sheet XM
T1: List Price Sheet 6HVXM-o
S2: 46143
C3: AFC COST | D3: 35% Margin | E3: 30% Margin | F3: 25% Margin | T3: Section 6
T4: Product Bulletin 6 ZLINE
B6: The Z-Line Series HVXM and MR11XM
B7: HVXM | L7: MR11XM
B8: PART # | C8: 1 STD SIZES | D8: LIST PRICE | E8: 0.34 | I8: CTN QTY | J8: CTN WT | L8: PART # | M8: 1 STD SIZES | N8: LIST PRICE | O8: 0.34 | S8: CTN QTY | T8: CTN WT
B9: HVP10101XM | C9: 10x10x1 | D9: 9.6 | E9: =D9*$E$8 -> 3.264 | F9: =(E9/0.65)+0.3 -> 5.3215385 | G9: =(E9/0.7)+0.3 -> 4.9628571 | H9: =(E9/0.75)+0.3 -> 4.652 | I9: 12 | J9: 8 LB. | L9: M1110101XM | M9: 10x10x1 | N9: 14.34 | O9: =N9*$O$8 -> 4.8756 | P9: =(O9/0.65)+0.3 -> 7.8009231 | Q9: =(O9/0.7)+0.3 -> 7.2651429 | R9: =(O9/0.75)+0.3 -> 6.8008 | S9: 12 | T9: 8 LB.
B10: HVP10201XM | C10: 10x20x1 | D10: 10.11 | E10: =D10*$E$8 -> 3.4374 | F10: =(E10/0.65)+0.3 -> 5.5883077 | G10: =(E10/0.7)+0.3 -> 5.2105714 | H10: =(E10/0.75)+0.3 -> 4.8832 | I10: 12 | J10: 11 LB. | L10: M1110201XM | M10: 10x20x1 | N10: 15.09 | O10: =N10*$O$8 -> 5.1306 | P10: =(O10/0.65)+0.3 -> 8.1932308 | Q10: =(O10/0.7)+0.3 -> 7.6294286 | R10: =(O10/0.75)+0.3 -> 7.1408 | S10: 12 | T10: 11 LB.
B11: HVP10241XM | C11: 10x24x1 | D11: 17.31 | E11: =D11*$E$8 -> 5.8854 | F11: =(E11/0.65)+0.3 -> 9.3544615 | G11: =(E11/0.7)+0.3 -> 8.7077143 | H11: =(E11/0.75)+0.3 -> 8.1472 | I11: 12 | J11: 12 LB. | L11: M1110241XM | M11: 10x24x1 | N11: 22.04 | O11: =N11*$O$8 -> 7.4936 | P11: =(O11/0.65)+0.3 -> 11.828615 | Q11: =(O11/0.7)+0.3 -> 11.005143 | R11: =(O11/0.75)+0.3 -> 10.291467 | S11: 12 | T11: 12 LB.
B12: HVP10301XM | C12: 10x30x1 | D12: 17.69 | E12: =D12*$E$8 -> 6.0146 | F12: =(E12/0.65)+0.3 -> 9.5532308 | G12: =(E12/0.7)+0.3 -> 8.8922857 | H12: =(E12/0.75)+0.3 -> 8.3194667 | I12: 12 | J12: 12 LB. | L12: M1110301XM | M12: 10x30x1 | N12: 22.52 | O12: =N12*$O$8 -> 7.6568 | P12: =(O12/0.65)+0.3 -> 12.079692 | Q12: =(O12/0.7)+0.3 -> 11.238286 | R12: =(O12/0.75)+0.3 -> 10.509067 | S12: 12 | T12: 12 LB.
B13: HVP12121XM | C13: 12x12x1 | D13: 12.26 | E13: =D13*$E$8 -> 4.1684 | F13: =(E13/0.65)+0.3 -> 6.7129231 | G13: =(E13/0.7)+0.3 -> 6.2548571 | H13: =(E13/0.75)+0.3 -> 5.8578667 | I13: 12 | J13: 8 LB. | L13: M1112121XM | M13: 12x12x1 | N13: 16.31 | O13: =N13*$O$8 -> 5.5454 | P13: =(O13/0.65)+0.3 -> 8.8313846 | Q13: =(O13/0.7)+0.3 -> 8.222 | R13: =(O13/0.75)+0.3 -> 7.6938667 | S13: 12 | T13: 8 LB.
B14: HVP12201XM | C14: 12x20x1 | D14: 10.37 | E14: =D14*$E$8 -> 3.5258 | F14: =(E14/0.65)+0.3 -> 5.7243077 | G14: =(E14/0.7)+0.3 -> 5.3368571 | H14: =(E14/0.75)+0.3 -> 5.0010667 | I14: 12 | J14: 12 LB. | L14: M1112201XM | M14: 12x20x1 | N14: 15.58 | O14: =N14*$O$8 -> 5.2972 | P14: =(O14/0.65)+0.3 -> 8.4495385 | Q14: =(O14/0.7)+0.3 -> 7.8674286 | R14: =(O14/0.75)+0.3 -> 7.3629333 | S14: 12 | T14: 12 LB.
B15: HVP12241XM | C15: 12x24x1 | D15: 10.67 | E15: =D15*$E$8 -> 3.6278 | F15: =(E15/0.65)+0.3 -> 5.8812308 | G15: =(E15/0.7)+0.3 -> 5.4825714 | H15: =(E15/0.75)+0.3 -> 5.1370667 | I15: 12 | J15: 11 LB. | L15: M1112241XM | M15: 12x24x1 | N15: 14.18 | O15: =N15*$O$8 -> 4.8212 | P15: =(O15/0.65)+0.3 -> 7.7172308 | Q15: =(O15/0.7)+0.3 -> 7.1874286 | R15: =(O15/0.75)+0.3 -> 6.7282667 | S15: 12 | T15: 18 LB.
B16: HVP12251XM | C16: 12x25x1 | D16: 11.41 | E16: =D16*$E$8 -> 3.8794 | F16: =(E16/0.65)+0.3 -> 6.2683077 | G16: =(E16/0.7)+0.3 -> 5.842 | H16: =(E16/0.75)+0.3 -> 5.4725333 | I16: 12 | J16: 11 LB. | L16: M1112251XM | M16: 12x25x1 | N16: 15.2 | O16: =N16*$O$8 -> 5.168 | P16: =(O16/0.65)+0.3 -> 8.2507692 | Q16: =(O16/0.7)+0.3 -> 7.6828571 | R16: =(O16/0.75)+0.3 -> 7.1906667 | S16: 12 | T16: 18 LB.
B17: HVP12301XM | C17: 12x30x1 | D17: 17.69 | E17: =D17*$E$8 -> 6.0146 | F17: =(E17/0.65)+0.3 -> 9.5532308 | G17: =(E17/0.7)+0.3 -> 8.8922857 | H17: =(E17/0.75)+0.3 -> 8.3194667 | I17: 12 | J17: 12 LB. | L17: M1112301XM | M17: 12x30x1 | N17: 22.52 | O17: =N17*$O$8 -> 7.6568 | P17: =(O17/0.65)+0.3 -> 12.079692 | Q17: =(O17/0.7)+0.3 -> 11.238286 | R17: =(O17/0.75)+0.3 -> 10.509067 | S17: 12 | T17: 15 LB.
B18: HVP14141XM | C18: 14x14x1 | D18: 12.67 | E18: =D18*$E$8 -> 4.3078 | F18: =(E18/0.65)+0.3 -> 6.9273846 | G18: =(E18/0.7)+0.3 -> 6.454 | H18: =(E18/0.75)+0.3 -> 6.0437333 | I18: 12 | J18: 9 LB. | L18: M1114141XM | M18: 14x14x1 | N18: 16.18 | O18: =N18*$O$8 -> 5.5012 | P18: =(O18/0.65)+0.3 -> 8.7633846 | Q18: =(O18/0.7)+0.3 -> 8.1588571 | R18: =(O18/0.75)+0.3 -> 7.6349333 | S18: 12 | T18: 9 LB.
B19: HVP14201XM | C19: 14x20x1 | D19: 10.83 | E19: =D19*$E$8 -> 3.6822 | F19: =(E19/0.65)+0.3 -> 5.9649231 | G19: =(E19/0.7)+0.3 -> 5.5602857 | H19: =(E19/0.75)+0.3 -> 5.2096 | I19: 12 | J19: 11 LB. | L19: M1114201XM | M19: 14x20x1 | N19: 14.51 | O19: =N19*$O$8 -> 4.9334 | P19: =(O19/0.65)+0.3 -> 7.8898462 | Q19: =(O19/0.7)+0.3 -> 7.3477143 | R19: =(O19/0.75)+0.3 -> 6.8778667 | S19: 12 | T19: 12 LB.
B20: HVP14241XM | C20: 14x24x1 | D20: 17.55 | E20: =D20*$E$8 -> 5.967 | F20: =(E20/0.65)+0.3 -> 9.48 | G20: =(E20/0.7)+0.3 -> 8.8242857 | H20: =(E20/0.75)+0.3 -> 8.256 | I20: 12 | J20: 12 LB. | L20: M1114241XM | M20: 14x24x1 | N20: 23.35 | O20: =N20*$O$8 -> 7.939 | P20: =(O20/0.65)+0.3 -> 12.513846 | Q20: =(O20/0.7)+0.3 -> 11.641429 | R20: =(O20/0.75)+0.3 -> 10.885333 | S20: 12 | T20: 12 LB.
... B43: HVP25251XM | C43: 25x25x1 | D43: 16.19 | E43: =D43*$E$8 -> 5.5046 | F43: =(E43/0.65)+0.3 -> 8.7686154 | G43: =(E43/0.7)+0.3 -> 8.1637143 | H43: =(E43/0.75)+0.3 -> 7.6394667 | I43: 12 | J43: 23 LB. | L43: M1125251XM | M43: 25x25x1 | N43: 24.15 | O43: =N43*$O$8 -> 8.211 | P43: =(O43/0.65)+0.3 -> 12.932308 | Q43: =(O43/0.7)+0.3 -> 12.03 | R43: =(O43/0.75)+0.3 -> 11.248 | S43: 12 | T43: 23 LB.
B45: PART # | C45: 2 STD SIZES | D45: LIST PRICE | E45: 0.34 | I45: CTN QTY | J45: CTN WT | L45: PART # | M45: 2 STD SIZES | N45: LIST PRICE | O45: 0.34 | S45: CTN QTY | T45: CTN WT
B46: HVP10202XM | C46: 10x20x2 | D46: 11.9 | E46: =D46*$E$45 -> 4.046 | F46: =(E46/0.65)+0.3 -> 6.5246154 | G46: =(E46/0.7)+0.3 -> 6.08 | H46: =(E46/0.75)+0.3 -> 5.6946667 | I46: 12 | J46: 15 LB. | L46: M1110202XM | M46: 10x20x2 | N46: 15.54 | O46: =N46*$O$45 -> 5.2836 | P46: =(O46/0.65)+0.3 -> 8.4286154 | Q46: =(O46/0.7)+0.3 -> 7.848 | R46: =(O46/0.75)+0.3 -> 7.3448 | S46: 12 | T46: 16 LB.
B47: HVP12122XM | C47: 12x12x2 | D47: 12.46 | E47: =D47*$E$45 -> 4.2364 | F47: =(E47/0.65)+0.3 -> 6.8175385 | G47: =(E47/0.7)+0.3 -> 6.352 | H47: =(E47/0.75)+0.3 -> 5.9485333 | I47: 12 | J47: 13 LB. | L47: M1112122XM | M47: 12x12x2 | N47: 16.07 | O47: =N47*$O$45 -> 5.4638 | P47: =(O47/0.65)+0.3 -> 8.7058462 | Q47: =(O47/0.7)+0.3 -> 8.1054286 | R47: =(O47/0.75)+0.3 -> 7.5850667 | S47: 12 | T47: 14 LB.
B48: HVP12202XM | C48: 12x20x2 | D48: 12.61 | E48: =D48*$E$45 -> 4.2874 | F48: =(E48/0.65)+0.3 -> 6.896 | G48: =(E48/0.7)+0.3 -> 6.4248571 | H48: =(E48/0.75)+0.3 -> 6.0165333 | I48: 12 | J48: 17 LB. | L48: M1112202XM | M48: 12x20x2 | N48: 16.47 | O48: =N48*$O$45 -> 5.5998 | P48: =(O48/0.65)+0.3 -> 8.9150769 | Q48: =(O48/0.7)+0.3 -> 8.2997143 | R48: =(O48/0.75)+0.3 -> 7.7664 | S48: 12 | T48: 18 LB.
B49: HVP12242XM | C49: 12x24x2 | D49: 11.85 | E49: =D49*$E$45 -> 4.029 | F49: =(E49/0.65)+0.3 -> 6.4984615 | G49: =(E49/0.7)+0.3 -> 6.0557143 | H49: =(E49/0.75)+0.3 -> 5.672 | I49: 12 | J49: 15 LB. | L49: M1112242XM | M49: 12x24x2 | N49: 15.66 | O49: =N49*$O$45 -> 5.3244 | P49: =(O49/0.65)+0.3 -> 8.4913846 | Q49: =(O49/0.7)+0.3 -> 7.9062857 | R49: =(O49/0.75)+0.3 -> 7.3992 | S49: 12 | T49: 16 LB.
B50: HVP14202XM | C50: 14x20x2 | D50: 12.08 | E50: =D50*$E$45 -> 4.1072 | F50: =(E50/0.65)+0.3 -> 6.6187692 | G50: =(E50/0.7)+0.3 -> 6.1674286 | H50: =(E50/0.75)+0.3 -> 5.7762667 | I50: 12 | J50: 15 LB. | L50: M1114202XM | M50: 14x20x2 | N50: 16.07 | O50: =N50*$O$45 -> 5.4638 | P50: =(O50/0.65)+0.3 -> 8.7058462 | Q50: =(O50/0.7)+0.3 -> 8.1054286 | R50: =(O50/0.75)+0.3 -> 7.5850667 | S50: 12 | T50: 16 LB.
B51: HVP14252XM | C51: 14x25x2 | D51: 13.25 | E51: =D51*$E$45 -> 4.505 | F51: =(E51/0.65)+0.3 -> 7.2307692 | G51: =(E51/0.7)+0.3 -> 6.7357143 | H51: =(E51/0.75)+0.3 -> 6.3066667 | I51: 12 | J51: 20 LB. | L51: M1114252XM | M51: 14x25x2 | N51: 17.47 | O51: =N51*$O$45 -> 5.9398 | P51: =(O51/0.65)+0.3 -> 9.4381538 | Q51: =(O51/0.7)+0.3 -> 8.7854286 | R51: =(O51/0.75)+0.3 -> 8.2197333 | S51: 12 | T51: 21 LB.
B52: HVP15202XM | C52: 15x20x2 | D52: 12.53 | E52: =D52*$E$45 -> 4.2602 | F52: =(E52/0.65)+0.3 -> 6.8541538 | G52: =(E52/0.7)+0.3 -> 6.386 | H52: =(E52/0.75)+0.3 -> 5.9802667 | I52: 12 | J52: 17 LB. | L52: M1115202XM | M52: 15x20x2 | N52: 16.6 | O52: =N52*$O$45 -> 5.644 | P52: =(O52/0.65)+0.3 -> 8.9830769 | Q52: =(O52/0.7)+0.3 -> 8.3628571 | R52: =(O52/0.75)+0.3 -> 7.8253333 | S52: 12 | T52: 18 LB.
B53: HVP16162XM | C53: 16x16x2 | D53: 16.13 | E53: =D53*$E$45 -> 5.4842 | F53: =(E53/0.65)+0.3 -> 8.7372308 | G53: =(E53/0.7)+0.3 -> 8.1345714 | H53: =(E53/0.75)+0.3 -> 7.6122667 | I53: 12 | J53: 18 LB. | L53: M1116162XM | M53: 16x16x2 | N53: 21.27 | O53: =N53*$O$45 -> 7.2318 | P53: =(O53/0.65)+0.3 -> 11.425846 | Q53: =(O53/0.7)+0.3 -> 10.631143 | R53: =(O53/0.75)+0.3 -> 9.9424 | S53: 12 | T53: 19 LB.
B54: HVP16202XM | C54: 16x20x2 | D54: 12.06 | E54: =D54*$E$45 -> 4.1004 | F54: =(E54/0.65)+0.3 -> 6.6083077 | G54: =(E54/0.7)+0.3 -> 6.1577143 | H54: =(E54/0.75)+0.3 -> 5.7672 | I54: 12 | J54: 18 LB. | L54: M1116202XM | M54: 16x20x2 | N54: 15.94 | O54: =N54*$O$45 -> 5.4196 | P54: =(O54/0.65)+0.3 -> 8.6378462 | Q54: =(O54/0.7)+0.3 -> 8.0422857 | R54: =(O54/0.75)+0.3 -> 7.5261333 | S54: 12 | T54: 19 LB.
B55: HVP16242XM | C55: 16x24x2 | D55: 15.38 | E55: =D55*$E$45 -> 5.2292 | F55: =(E55/0.65)+0.3 -> 8.3449231 | G55: =(E55/0.7)+0.3 -> 7.7702857 | H55: =(E55/0.75)+0.3 -> 7.2722667 | I55: 12 | J55: 21 LB. | L55: M1116242XM | M55: 16x24x2 | N55: 20.42 | O55: =N55*$O$45 -> 6.9428 | P55: =(O55/0.65)+0.3 -> 10.981231 | Q55: =(O55/0.7)+0.3 -> 10.218286 | R55: =(O55/0.75)+0.3 -> 9.5570667 | S55: 12 | T55: 22 LB.
B56: HVP16252XM | C56: 16x25x2 | D56: 13.86 | E56: =D56*$E$45 -> 4.7124 | F56: =(E56/0.65)+0.3 -> 7.5498462 | G56: =(E56/0.7)+0.3 -> 7.032 | H56: =(E56/0.75)+0.3 -> 6.5832 | I56: 12 | J56: 21 LB. | L56: M1116252XM | M56: 16x25x2 | N56: 18.38 | O56: =N56*$O$45 -> 6.2492 | P56: =(O56/0.65)+0.3 -> 9.9141538 | Q56: =(O56/0.7)+0.3 -> 9.2274286 | R56: =(O56/0.75)+0.3 -> 8.6322667 | S56: 12 | T56: 22 LB.
B57: HVP18182XM | C57: 18x18x2 | D57: 19.97 | E57: =D57*$E$45 -> 6.7898 | F57: =(E57/0.65)+0.3 -> 10.745846 | G57: =(E57/0.7)+0.3 -> 9.9997143 | H57: =(E57/0.75)+0.3 -> 9.3530667 | I57: 12 | J57: 18 LB. | L57: M1118182XM | M57: 18x18x2 | N57: 25.76 | O57: =N57*$O$45 -> 8.7584 | P57: =(O57/0.65)+0.3 -> 13.774462 | Q57: =(O57/0.7)+0.3 -> 12.812 | R57: =(O57/0.75)+0.3 -> 11.977867 | S57: 12 | T57: 19 LB.
... B66: HVP25252XM | C66: 25x25x2 | D66: 21.75 | E66: =D66*$E$45 -> 7.395 | F66: =(E66/0.65)+0.3 -> 11.676923 | G66: =(E66/0.7)+0.3 -> 10.864286 | H66: =(E66/0.75)+0.3 -> 10.16 | I66: 12 | J66: 33 LB. | L66: M1125252XM | M66: 25x25x2 | N66: 28.42 | O66: =N66*$O$45 -> 9.6628 | P66: =(O66/0.65)+0.3 -> 15.165846 | Q66: =(O66/0.7)+0.3 -> 14.104 | R66: =(O66/0.75)+0.3 -> 13.183733 | S66: 12 | T66: 34 LB.
B68: PART # | C68: 4 STD SIZES | D68: LIST PRICE | E68: 0.34 | I68: CTN QTY | J68: CTN WT | L68: PART # | M68: 4 STD SIZES | N68: LIST PRICE | O68: 0.34 | S68: CTN QTY | T68: CTN WT
B69: HVP12244XM | C69: 12x24x4 | D69: 20.66 | E69: =D69*$E$68 -> 7.0244 | F69: =(E69/0.65)+0.3 -> 11.106769 | G69: =(E69/0.7)+0.3 -> 10.334857 | H69: =(E69/0.75)+0.3 -> 9.6658667 | I69: 6 | J69: 14 LB. | L69: M1112244XM | M69: 12x24x4 | N69: 28.36 | O69: =N69*$O$68 -> 9.6424 | P69: =(O69/0.65)+0.3 -> 15.134462 | Q69: =(O69/0.7)+0.3 -> 14.074857 | R69: =(O69/0.75)+0.3 -> 13.156533 | S69: 6 | T69: 15 LB.
B70: HVP16204XM | C70: 16x20x4 | D70: 20.64 | E70: =D70*$E$68 -> 7.0176 | F70: =(E70/0.65)+0.3 -> 11.096308 | G70: =(E70/0.7)+0.3 -> 10.325143 | H70: =(E70/0.75)+0.3 -> 9.6568 | I70: 6 | J70: 16 LB. | L70: M1116204XM | M70: 16x20x4 | N70: 27.76 | O70: =N70*$O$68 -> 9.4384 | P70: =(O70/0.65)+0.3 -> 14.820615 | Q70: =(O70/0.7)+0.3 -> 13.783429 | R70: =(O70/0.75)+0.3 -> 12.884533 | S70: 6 | T70: 17 LB.
B71: HVP16254XM | C71: 16x25x4 | D71: 24.04 | E71: =D71*$E$68 -> 8.1736 | F71: =(E71/0.65)+0.3 -> 12.874769 | G71: =(E71/0.7)+0.3 -> 11.976571 | H71: =(E71/0.75)+0.3 -> 11.198133 | I71: 6 | J71: 19 LB. | L71: M1116254XM | M71: 16x25x4 | N71: 32.37 | O71: =N71*$O$68 -> 11.0058 | P71: =(O71/0.65)+0.3 -> 17.232 | Q71: =(O71/0.7)+0.3 -> 16.022571 | R71: =(O71/0.75)+0.3 -> 14.9744 | S71: 6 | T71: 20 LB.
B72: HVP18244XM | C72: 18x24x4 | D72: 26.36 | E72: =D72*$E$68 -> 8.9624 | F72: =(E72/0.65)+0.3 -> 14.088308 | G72: =(E72/0.7)+0.3 -> 13.103429 | H72: =(E72/0.75)+0.3 -> 12.249867 | I72: 6 | J72: 21 LB. | L72: M1118244XM | M72: 18x24x4 | N72: 35.46 | O72: =N72*$O$68 -> 12.0564 | P72: =(O72/0.65)+0.3 -> 18.848308 | Q72: =(O72/0.7)+0.3 -> 17.523429 | R72: =(O72/0.75)+0.3 -> 16.3752 | S72: 6 | T72: 22 LB.
B73: HVP20204XM | C73: 20x20x4 | D73: 24.66 | E73: =D73*$E$68 -> 8.3844 | F73: =(E73/0.65)+0.3 -> 13.199077 | G73: =(E73/0.7)+0.3 -> 12.277714 | H73: =(E73/0.75)+0.3 -> 11.4792 | I73: 6 | J73: 17 LB. | L73: M1120204XM | M73: 20x20x4 | N73: 33.19 | O73: =N73*$O$68 -> 11.2846 | P73: =(O73/0.65)+0.3 -> 17.660923 | Q73: =(O73/0.7)+0.3 -> 16.420857 | R73: =(O73/0.75)+0.3 -> 15.346133 | S73: 6 | T73: 18 LB.
B74: HVP20244XM | C74: 20x24x4 | D74: 27.84 | E74: =D74*$E$68 -> 9.4656 | F74: =(E74/0.65)+0.3 -> 14.862462 | G74: =(E74/0.7)+0.3 -> 13.822286 | H74: =(E74/0.75)+0.3 -> 12.9208 | I74: 6 | J74: 22 LB. | L74: M1120244XM | M74: 20x24x4 | N74: 38.63 | O74: =N74*$O$68 -> 13.1342 | P74: =(O74/0.65)+0.3 -> 20.506462 | Q74: =(O74/0.7)+0.3 -> 19.063143 | R74: =(O74/0.75)+0.3 -> 17.812267 | S74: 6 | T74: 23 LB.
B75: HVP20254XM | C75: 20x25x4 | D75: 27.38 | E75: =D75*$E$68 -> 9.3092 | F75: =(E75/0.65)+0.3 -> 14.621846 | G75: =(E75/0.7)+0.3 -> 13.598857 | H75: =(E75/0.75)+0.3 -> 12.712267 | I75: 6 | J75: 21 LB. | L75: M1120254XM | M75: 20x25x4 | N75: 38.02 | O75: =N75*$O$68 -> 12.9268 | P75: =(O75/0.65)+0.3 -> 20.187385 | Q75: =(O75/0.7)+0.3 -> 18.766857 | R75: =(O75/0.75)+0.3 -> 17.535733 | S75: 6 | T75: 22 LB.
B76: HVP24244XM | C76: 24x24x4 | D76: 31.16 | E76: =D76*$E$68 -> 10.5944 | F76: =(E76/0.65)+0.3 -> 16.599077 | G76: =(E76/0.7)+0.3 -> 15.434857 | H76: =(E76/0.75)+0.3 -> 14.425867 | I76: 6 | J76: 25 LB. | L76: M1124244XM | M76: 24x24x4 | N76: 43.27 | O76: =N76*$O$68 -> 14.7118 | P76: =(O76/0.65)+0.3 -> 22.933538 | Q76: =(O76/0.7)+0.3 -> 21.316857 | R76: =(O76/0.75)+0.3 -> 19.915733 | S76: 6 | T76: 26 LB.

Sheet Excel BAG 2
C3: AFC COST | D3: 35% Margin | E3: 30% Margin | F3: 25% Margin
B6: EXCEL
B7: High Efficiency Synthetic Bag
B8: Nominal | C8: No. | D8: MERV 11 | L8: Nominal | M8: No. | N8: MERV 9
B9: Size | C9: of | D9: PART | E9: LIST | F9: Multiplier | J9: CTN. | L9: Size | M9: of | N9: PART | O9: LIST | P9: Multiplier | T9: CTN.
B10: W x H x D | C10: PKTS. | D10: NUMBER | E10: PRICE | F10: 0.34 | G10: 35% Margin | H10: 30% Margin | I10: 25% Margin | J10: QTY. | L10: W x H x D | M10: PKTS. | N10: NUMBER | O10: PRICE | P10: 0.364 | Q10: 35% Margin | R10: 30% Margin | S10: 25% Margin | T10: QTY.
B11: 24x24x15 | C11: 6 | D11: SBG24241566 | E11: 68.88 | F11: =E11*$F$10 -> 23.4192 | G11: =(F11/0.65)+0.3 -> 36.329538 | H11: =(F11/0.7)+0.3 -> 33.756 | I11: =(F11/0.75)+0.3 -> 31.5256 | J11: 6 | L11: 24x24x12 | M11: 6 | N11: SBG24241246 | O11: 59.37 | P11: =O11*$P$10 -> 21.61068 | Q11: =(P11/0.65)+0.3 -> 33.5472 | R11: =(P11/0.7)+0.3 -> 31.1724 | S11: =(P11/0.75)+0.3 -> 29.11424 | T11: 7
B12: 24x24x15 | C12: 7 | D12: SBG24241567 | E12: 77.09 | F12: =E12*$F$10 -> 26.2106 | G12: =(F12/0.65)+0.3 -> 40.624 | H12: =(F12/0.7)+0.3 -> 37.743714 | I12: =(F12/0.75)+0.3 -> 35.247467 | J12: 4 | L12: 24x24x15 | M12: 6 | N12: SBG24241546 | O12: 63.14 | P12: =O12*$P$10 -> 22.98296 | Q12: =(P12/0.65)+0.3 -> 35.6584 | R12: =(P12/0.7)+0.3 -> 33.1328 | S12: =(P12/0.75)+0.3 -> 30.943947 | T12: 6
B13: 24x24x15 | C13: 8 | D13: SBG24241568 | E13: 84.9 | F13: =E13*$F$10 -> 28.866 | G13: =(F13/0.65)+0.3 -> 44.709231 | H13: =(F13/0.7)+0.3 -> 41.537143 | I13: =(F13/0.75)+0.3 -> 38.788 | J13: 4 | L13: 24x24x15 | M13: 7 | N13: SBG24241547 | O13: 70.84 | P13: =O13*$P$10 -> 25.78576 | Q13: =(P13/0.65)+0.3 -> 39.9704 | R13: =(P13/0.7)+0.3 -> 37.1368 | S13: =(P13/0.75)+0.3 -> 34.681013 | T13: 5
B14: 24x24x15 | C14: 10 | D14: SBG242415610 | E14: 99 | F14: =E14*$F$10 -> 33.66 | G14: =(F14/0.65)+0.3 -> 52.084615 | H14: =(F14/0.7)+0.3 -> 48.385714 | I14: =(F14/0.75)+0.3 -> 45.18 | J14: 4 | L14: 24x24x15 | M14: 8 | N14: SBG24241548 | O14: 78.31 | P14: =O14*$P$10 -> 28.50484 | Q14: =(P14/0.65)+0.3 -> 44.1536 | R14: =(P14/0.7)+0.3 -> 41.0212 | S14: =(P14/0.75)+0.3 -> 38.306453 | T14: 5
B15: 24x24x15 | C15: 12 | D15: SBG242415612 | E15: 116.3 | F15: =E15*$F$10 -> 39.542 | G15: =(F15/0.65)+0.3 -> 61.133846 | H15: =(F15/0.7)+0.3 -> 56.788571 | I15: =(F15/0.75)+0.3 -> 53.022667 | J15: 3 | L15: 24x24x21 | M15: 6 | N15: SBG24242146 | O15: 70.84 | P15: =O15*$P$10 -> 25.78576 | Q15: =(P15/0.65)+0.3 -> 39.9704 | R15: =(P15/0.7)+0.3 -> 37.1368 | S15: =(P15/0.75)+0.3 -> 34.681013 | T15: 4
B16: 24x24x21 | C16: 6 | D16: SBG24242166 | E16: 78.71 | F16: =E16*$F$10 -> 26.7614 | G16: =(F16/0.65)+0.3 -> 41.471385 | H16: =(F16/0.7)+0.3 -> 38.530571 | I16: =(F16/0.75)+0.3 -> 35.981867 | J16: 5 | L16: 24x24x21 | M16: 7 | N16: SBG24242147 | O16: 79.56 | P16: =O16*$P$10 -> 28.95984 | Q16: =(P16/0.65)+0.3 -> 44.8536 | R16: =(P16/0.7)+0.3 -> 41.6712 | S16: =(P16/0.75)+0.3 -> 38.91312 | T16: 3
B17: 24x24x21 | C17: 8 | D17: SBG24242168 | E17: 93.34 | F17: =E17*$F$10 -> 31.7356 | G17: =(F17/0.65)+0.3 -> 49.124 | H17: =(F17/0.7)+0.3 -> 45.636571 | I17: =(F17/0.75)+0.3 -> 42.614133 | J17: 4 | L17: 24x24x21 | M17: 8 | N17: SBG24242148 | O17: 88.43 | P17: =O17*$P$10 -> 32.18852 | Q17: =(P17/0.65)+0.3 -> 49.8208 | R17: =(P17/0.7)+0.3 -> 46.2836 | S17: =(P17/0.75)+0.3 -> 43.218027 | T17: 3
B18: 24x24x21 | C18: 10 | D18: SBG242421610 | E18: 102.02 | F18: =E18*$F$10 -> 34.6868 | G18: =(F18/0.65)+0.3 -> 53.664308 | H18: =(F18/0.7)+0.3 -> 49.852571 | I18: =(F18/0.75)+0.3 -> 46.549067 | J18: 4 | L18: 20x24x12 | M18: 4 | N18: SBG20241244 | O18: 45.73 | P18: =O18*$P$10 -> 16.64572 | Q18: =(P18/0.65)+0.3 -> 25.9088 | R18: =(P18/0.7)+0.3 -> 24.0796 | S18: =(P18/0.75)+0.3 -> 22.494293 | T18: 7 | Y18: 9
B19: 24x24x25 | C19: 6 | D19: SBG24242566 | E19: 85.32 | F19: =E19*$F$10 -> 29.0088 | G19: =(F19/0.65)+0.3 -> 44.928923 | H19: =(F19/0.7)+0.3 -> 41.741143 | I19: =(F19/0.75)+0.3 -> 38.9784 | J19: 4 | L19: 20x24x12 | M19: 5 | N19: SBG20241245 | O19: 52.57 | P19: =O19*$P$10 -> 19.13548 | Q19: =(P19/0.65)+0.3 -> 29.7392 | R19: =(P19/0.7)+0.3 -> 27.6364 | S19: =(P19/0.75)+0.3 -> 25.813973 | T19: 7 | Y19: 18
B20: 24x24x25 | C20: 8 | D20: SBG24242568 | E20: 107.54 | F20: =E20*$F$10 -> 36.5636 | G20: =(F20/0.65)+0.3 -> 56.551692 | H20: =(F20/0.7)+0.3 -> 52.533714 | I20: =(F20/0.75)+0.3 -> 49.051467 | J20: 3 | L20: 20x24x12 | M20: 6 | N20: SBG20241246 | O20: 59.37 | P20: =O20*$P$10 -> 21.61068 | Q20: =(P20/0.65)+0.3 -> 33.5472 | R20: =(P20/0.7)+0.3 -> 31.1724 | S20: =(P20/0.75)+0.3 -> 29.11424 | T20: 7 | Y20: 9
B21: 24x24x25 | C21: 10 | D21: SBG242425610 | E21: 129.98 | F21: =E21*$F$10 -> 44.1932 | G21: =(F21/0.65)+0.3 -> 68.289538 | H21: =(F21/0.7)+0.3 -> 63.433143 | I21: =(F21/0.75)+0.3 -> 59.224267 | J21: 3 | L21: 20x24x15 | M21: 6 | N21: SBG20241546 | O21: 67.45 | P21: =O21*$P$10 -> 24.5518 | Q21: =(P21/0.65)+0.3 -> 38.072 | R21: =(P21/0.7)+0.3 -> 35.374 | S21: =(P21/0.75)+0.3 -> 33.035733 | T21: 6 | Y21: 18
B22: 24x24x29 | C22: 6 | D22: SBG24242966 | E22: 91.72 | F22: =E22*$F$10 -> 31.1848 | G22: =(F22/0.65)+0.3 -> 48.276615 | H22: =(F22/0.7)+0.3 -> 44.849714 | I22: =(F22/0.75)+0.3 -> 41.879733 | J22: 4 | L22: 20x24x15 | M22: 7 | N22: SBG20241547 | O22: 75.65 | P22: =O22*$P$10 -> 27.5366 | Q22: =(P22/0.65)+0.3 -> 42.664 | R22: =(P22/0.7)+0.3 -> 39.638 | S22: =(P22/0.75)+0.3 -> 37.015467 | T22: 5 | Y22: 3
B23: 24x24x29 | C23: 8 | D23: SBG24242968 | E23: 111.88 | F23: =E23*$F$10 -> 38.0392 | G23: =(F23/0.65)+0.3 -> 58.821846 | H23: =(F23/0.7)+0.3 -> 54.641714 | I23: =(F23/0.75)+0.3 -> 51.018933 | J23: 3 | L23: 20x24x15 | M23: 8 | N23: SBG20241548 | O23: 83.73 | P23: =O23*$P$10 -> 30.47772 | Q23: =(P23/0.65)+0.3 -> 47.1888 | R23: =(P23/0.7)+0.3 -> 43.8396 | S23: =(P23/0.75)+0.3 -> 40.93696 | T23: 5 | Y23: 12
B24: 24x24x29 | C24: 10 | D24: SBG242429610 | E24: 127.41 | F24: =E24*$F$10 -> 43.3194 | G24: =(F24/0.65)+0.3 -> 66.945231 | H24: =(F24/0.7)+0.3 -> 62.184857 | I24: =(F24/0.75)+0.3 -> 58.0592 | J24: 2 | L24: 20x24x21 | M24: 6 | N24: SBG20242146 | O24: 75.65 | P24: =O24*$P$10 -> 27.5366 | Q24: =(P24/0.65)+0.3 -> 42.664 | R24: =(P24/0.7)+0.3 -> 39.638 | S24: =(P24/0.75)+0.3 -> 37.015467 | T24: 4 | Y24: 3
B25: 24x24x36 | C25: 6 | D25: SBG24243666 | E25: 103.14 | F25: =E25*$F$10 -> 35.0676 | G25: =(F25/0.65)+0.3 -> 54.250154 | H25: =(F25/0.7)+0.3 -> 50.396571 | I25: =(F25/0.75)+0.3 -> 47.0568 | J25: 3 | L25: 20x24x21 | M25: 7 | N25: SBG20242147 | O25: 85.06 | P25: =O25*$P$10 -> 30.96184 | Q25: =(P25/0.65)+0.3 -> 47.9336 | R25: =(P25/0.7)+0.3 -> 44.5312 | S25: =(P25/0.75)+0.3 -> 41.582453 | T25: 3 | Y25: 12
B26: 24x24x36 | C26: 8 | D26: SBG24243668 | E26: 127.28 | F26: =E26*$F$10 -> 43.2752 | G26: =(F26/0.65)+0.3 -> 66.877231 | H26: =(F26/0.7)+0.3 -> 62.121714 | I26: =(F26/0.75)+0.3 -> 58.000267 | J26: 3 | L26: 20x24x21 | M26: 8 | N26: SBG20242148 | O26: 94.49 | P26: =O26*$P$10 -> 34.39436 | Q26: =(P26/0.65)+0.3 -> 53.2144 | R26: =(P26/0.7)+0.3 -> 49.4348 | S26: =(P26/0.75)+0.3 -> 46.159147 | T26: 3 | Y26: 3
B27: 24x24x36 | C27: 10 | D27: SBG242436610 | E27: 145.61 | F27: =E27*$F$10 -> 49.5074 | G27: =(F27/0.65)+0.3 -> 76.465231 | H27: =(F27/0.7)+0.3 -> 71.024857 | I27: =(F27/0.75)+0.3 -> 66.309867 | J27: 2 | L27: 20x20x12 | M27: 4 | N27: SBG20201244 | O27: 45.73 | P27: =O27*$P$10 -> 16.64572 | Q27: =(P27/0.65)+0.3 -> 25.9088 | R27: =(P27/0.7)+0.3 -> 24.0796 | S27: =(P27/0.75)+0.3 -> 22.494293 | T27: 7 | Y27: 12
B28: 20x24x15 | C28: 6 | D28: SBG20241566 | E28: 73.59 | F28: =E28*$F$10 -> 25.0206 | G28: =(F28/0.65)+0.3 -> 38.793231 | H28: =(F28/0.7)+0.3 -> 36.043714 | I28: =(F28/0.75)+0.3 -> 33.6608 | J28: 6 | L28: 20x20x12 | M28: 5 | N28: SBG20201245 | O28: 52.57 | P28: =O28*$P$10 -> 19.13548 | Q28: =(P28/0.65)+0.3 -> 29.7392 | R28: =(P28/0.7)+0.3 -> 27.6364 | S28: =(P28/0.75)+0.3 -> 25.813973 | T28: 7 | Y28: 3
B29: 20x24x15 | C29: 8 | D29: SBG20241568 | E29: 90.72 | F29: =E29*$F$10 -> 30.8448 | G29: =(F29/0.65)+0.3 -> 47.753538 | H29: =(F29/0.7)+0.3 -> 44.364 | I29: =(F29/0.75)+0.3 -> 41.4264 | J29: 4 | L29: 20x20x12 | M29: 6 | N29: SBG20201246 | O29: 59.37 | P29: =O29*$P$10 -> 21.61068 | Q29: =(P29/0.65)+0.3 -> 33.5472 | R29: =(P29/0.7)+0.3 -> 31.1724 | S29: =(P29/0.75)+0.3 -> 29.11424 | T29: 7 | Y29: 12
... B41: 20x24x36 | C41: 8 | D41: SBG20243668 | E41: 136 | F41: =E41*$F$10 -> 46.24 | G41: =(F41/0.65)+0.3 -> 71.438462 | H41: =(F41/0.7)+0.3 -> 66.357143 | I41: =(F41/0.75)+0.3 -> 61.953333 | J41: 2 | L41: 12x24x21 | M41: 6 | N41: SBG12242146 | O41: 70.84 | P41: =O41*$P$10 -> 25.78576 | Q41: =(P41/0.65)+0.3 -> 39.9704 | R41: =(P41/0.7)+0.3 -> 37.1368 | S41: =(P41/0.75)+0.3 -> 34.681013 | T41: 8 | Y41: 8
B42: 20x24x36 | C42: 10 | D42: SBG202436610 | E42: 155.62 | F42: =E42*$F$10 -> 52.9108 | G42: =(F42/0.65)+0.3 -> 81.701231 | H42: =(F42/0.7)+0.3 -> 75.886857 | I42: =(F42/0.75)+0.3 -> 70.847733 | J42: 2 | L42: OPTIONS: | Y42: 6
B43: 12x24x15 | C43: 3 | D43: SBG12241563 | E43: 46.83 | F43: =E43*$F$10 -> 15.9222 | G43: =(F43/0.65)+0.3 -> 24.795692 | H43: =(F43/0.7)+0.3 -> 23.046 | I43: =(F43/0.75)+0.3 -> 21.5296 | J43: 10 | L43: For pricing on 20 x 20 face dimension use 20 x 24 List Price | Y43: 8
B44: 12x24x15 | C44: 4 | D44: SBG12241564 | E44: 55.06 | F44: =E44*$F$10 -> 18.7204 | G44: =(F44/0.65)+0.3 -> 29.100615 | H44: =(F44/0.7)+0.3 -> 27.043429 | I44: =(F44/0.75)+0.3 -> 25.260533 | J44: 8 | L44: For pricing on standard size face dimension 22 depth use | Y44: 6
B45: 12x24x15 | C45: 5 | D45: SBG12241565 | E45: 62.27 | F45: =E45*$F$10 -> 21.1718 | G45: =(F45/0.65)+0.3 -> 32.872 | H45: =(F45/0.7)+0.3 -> 30.545429 | I45: =(F45/0.75)+0.3 -> 28.529067 | J45: 7 | L45: 21 List Price and for 30 use 29 List Price | Y45: 4
B46: 12x24x15 | C46: 6 | D46: SBG12241566 | E46: 68.88 | F46: =E46*$F$10 -> 23.4192 | G46: =(F46/0.65)+0.3 -> 36.329538 | H46: =(F46/0.7)+0.3 -> 33.756 | I46: =(F46/0.75)+0.3 -> 31.5256 | J46: 6 | L46: Other special Size Length Bags - Use Next Largest Depth Size | Y46: 12
B47: 12x24x21 | C47: 3 | D47: SBG12242163 | E47: 48.37 | F47: =E47*$F$10 -> 16.4458 | G47: =(F47/0.65)+0.3 -> 25.601231 | H47: =(F47/0.7)+0.3 -> 23.794 | I47: =(F47/0.75)+0.3 -> 22.227733 | J47: 8 | Y47: =SUM(Y18:Y46) -> 270
B48: 12x24x21 | C48: 4 | D48: SBG12242164 | E48: 58.5 | F48: =E48*$F$10 -> 19.89 | G48: =(F48/0.65)+0.3 -> 30.9 | H48: =(F48/0.7)+0.3 -> 28.714286 | I48: =(F48/0.75)+0.3 -> 26.82 | J48: 7 | L48: Reverse Dimension 24 x 12 Header use 24 x 24 List Price for
B49: 12x24x21 | C49: 5 | D49: SBG12242165 | E49: 68.61 | F49: =E49*$F$10 -> 23.3274 | G49: =(F49/0.65)+0.3 -> 36.188308 | H49: =(F49/0.7)+0.3 -> 33.624857 | I49: =(F49/0.75)+0.3 -> 31.4032 | J49: 6 | L49: the desired depth and pocket amount
B50: 12x24x25 | C50: 3 | D50: SBG12242563 | E50: 51.71 | F50: =E50*$F$10 -> 17.5814 | G50: =(F50/0.65)+0.3 -> 27.348308 | H50: =(F50/0.7)+0.3 -> 25.416286 | I50: =(F50/0.75)+0.3 -> 23.741867 | J50: 8 | L50: Reverse Dimension 24 x 20 Header use 24 x 24 List Price for
B51: 12x24x25 | C51: 4 | D51: SBG12242564 | E51: 62.9 | F51: =E51*$F$10 -> 21.386 | G51: =(F51/0.65)+0.3 -> 33.201538 | H51: =(F51/0.7)+0.3 -> 30.851429 | I51: =(F51/0.75)+0.3 -> 28.814667 | J51: 7 | L51: the desired depth and pocket amount and add +15%
B52: 12x24x25 | C52: 5 | D52: SBG12242565 | E52: 74.1 | F52: =E52*$F$10 -> 25.194 | G52: =(F52/0.65)+0.3 -> 39.06 | H52: =(F52/0.7)+0.3 -> 36.291429 | I52: =(F52/0.75)+0.3 -> 33.892 | J52: 6
B53: 12x24x29 | C53: 3 | D53: SBG12242963 | E53: 54.96 | F53: =E53*$F$10 -> 18.6864 | G53: =(F53/0.65)+0.3 -> 29.048308 | H53: =(F53/0.7)+0.3 -> 26.994857 | I53: =(F53/0.75)+0.3 -> 25.2152 | J53: 9 | L53: 1-1/8-inch Header Available - Add $8.00 to List Price
B54: 12x24x29 | C54: 4 | D54: SBG12242964 | E54: 67.3 | F54: =E54*$F$10 -> 22.882 | G54: =(F54/0.65)+0.3 -> 35.503077 | H54: =(F54/0.7)+0.3 -> 32.988571 | I54: =(F54/0.75)+0.3 -> 30.809333 | J54: 8 | L54: Please specify when ordering
B55: 12x24x29 | C55: 5 | D55: SBG12242965 | E55: 79.43 | F55: =E55*$F$10 -> 27.0062 | G55: =(F55/0.65)+0.3 -> 41.848 | H55: =(F55/0.7)+0.3 -> 38.880286 | I55: =(F55/0.75)+0.3 -> 36.308267 | J55: 7
B56: 12x24x36 | C56: 3 | D56: SBG12243663 | E56: 60.72 | F56: =E56*$F$10 -> 20.6448 | G56: =(F56/0.65)+0.3 -> 32.061231 | H56: =(F56/0.7)+0.3 -> 29.792571 | I56: =(F56/0.75)+0.3 -> 27.8264 | J56: 8 | M56: Hanger Loops available: | N56: Add $3.00 list per loop
B57: 12x24x36 | C57: 4 | D57: SBG12243664 | E57: 74.79 | F57: =E57*$F$10 -> 25.4286 | G57: =(F57/0.65)+0.3 -> 39.420923 | H57: =(F57/0.7)+0.3 -> 36.626571 | I57: =(F57/0.75)+0.3 -> 34.2048 | J57: 7 | M57: Gasket available: | N57: Add $7.00 List for 4 sides
B58: 12x24x36 | C58: 5 | D58: SBG12243665 | E58: 88.82 | F58: =E58*$F$10 -> 30.1988 | G58: =(F58/0.65)+0.3 -> 46.759692 | H58: =(F58/0.7)+0.3 -> 43.441143 | I58: =(F58/0.75)+0.3 -> 40.565067 | J58: 5 | N58: Add $6.00 List for 2 sides
N59: Add $4.75 List for 1 side
B61: Special Header Size Excel Bags-Use Next Largest Size + 30% Added to List Price
B62: Special size Excel Bags are non-returnable

Sheet Sheet1
A1: id | B1: part_number | C1: description | D1: PRICE | E1: on_hand | F1: Physical Count
A2: 28338 | B2: 004DN025BN4HC | C2: 004DN025BN4HC ..Hydac Replacement Pressure Filter Element, 25 Micron, NBR Seal | D2: AFC | E2: 0
A3: 28339 | B3: 0060R005ON-Hydac | C3: Hydac Filter Element 1262932 | D3: AFC | E3: 0
A4: 27008 | B4: 012-100093-MIGTEST | C4: Down Stream Gasketing, Neoprene | D4: AFC | E4: 0
A5: 27025 | B5: 1010-2ply | C5: 10x10 2-Ply Poly Panel | D5: 3.32 | E5: 205
A6: 27026 | B6: 1010-3ply | C6: 10x10 3-Ply Poly Panel | D6: 3.99 | E6: 100
A7: 27027 | B7: 1012-3ply | C7: 10x12 3-Ply Poly Panel | E7: 0
A8: 27028 | B8: 1020-2ply | C8: 10x20 2-Ply Poly Panel | D8: 3.7 | E8: 7
A9: 27029 | B9: 1020-3ply | C9: 10x20 3-Ply Poly Panel | D9: 4.43 | E9: 104
A10: 27030 | B10: 1025-3ply | C10: 10x25 3-Ply Poly Panel | E10: 0
A11: 27036 | B11: 1030-3ply | C11: 10x30 3-Ply Poly Panel | E11: 0
A12: 27031 | B12: 1040-2ply | C12: 10x40 2-Ply Poly Panel | D12: AFC | E12: 3
A13: 27034 | B13: 1080-2ply | C13: 10x80 2-Ply Poly Panel | D13: AFC | E13: 7
A14: 27032 | B14: 1142-2ply | C14: 11x42 MZP 2-Ply Poly Panel | D14: 6.74 | E14: 144
A15: 27033 | B15: 12.24.2 Nova Pleat | C15: 12x24x2 NovaPleat No Wire | E15: 0
A16: 27035 | B16: 1212-2Ply | C16: 12x12 2-Ply Panel | D16: 3.17 | E16: 248
A17: 27037 | B17: 1212-3Ply | C17: 12x12 3-Ply Panel | D17: 3.67 | E17: 1
A18: 27039 | B18: 12120-2ply | C18: 12x120 2-Ply Poly Panel | D18: AFC | E18: 1
A19: 27038 | B19: 12120-3ply | C19: 12x120 3-Ply Poly Panel | E19: 0
A20: 27040 | B20: 1212W-2Ply-P | C20: 12" x 12" 2 Ply Panel Filter | E20: 0
A21: 27041 | B21: 12144-2PLY-6L | C21: 12x144 2 Ply Poly Panel | D21: AFC | E21: 13
A22: 27042 | B22: 12144-3PLY-6L | C22: 12x144 3 Ply Poly Panel | E22: 0
A23: 27043 | B23: 1218-2ply | C23: 12x18 2-Ply Poly Panel | E23: 0
A24: 27044 | B24: 1218-3ply | C24: 12x18 3-Ply Poly Panel | E24: 0
A25: 27047 | B25: 1218-5050WW-P | C25: 12x18 2-Ply Panel | E25: 0
A26: 27046 | B26: 1220-2ply | C26: 12x20 2-Ply Poly Panel | E26: 0
A27: 27045 | B27: 1220-3ply | C27: 12x20 3-Ply Poly Panel | D27: 4.35 | E27: 312
A28: 27048 | B28: 1224-2ply | C28: 12x24 2-Ply Poly Panel | D28: 4.32 | E28: 1006
A29: 27049 | B29: 1224-3ply | C29: 12x24 3-Ply Poly Panel | D29: AFC | E29: 518
A30: 28398 | B30: 1224-SPORAX | C30: 12x24 Rigid Pad w/Sporax | E30: 0
A31: 27056 | B31: 1224W-3PLY-P | C31: 12x24 3 Ply Poly Panel | D31: AFC | E31: 50
A32: 28401 | B32: 1230-2Ply | C32: 12x30 2-Ply Panel | D32: 5.93 | E32: 12
A33: 27055 | B33: 1238-2ply | C33: 12x38 2-Ply Poly Panel | D33: AFC | E33: 12
A34: 27050 | B34: 1243-2ply | C34: 12x43 2-Ply Poly Panel | D34: 8.36 | E34: 70
A35: 27054 | B35: 1243-3ply | C35: 12x43 3-Ply Poly Panel | E35: 0
A36: 27057 | B36: 1248W-2PLY-P | C36: 12x48 2 Ply Poly Panel | D36: AFC | E36: 24
A37: 27052 | B37: 1248W-3PLY-P | C37: 12x48 3 Ply Poly Panel | E37: 0
A38: 27051 | B38: 1272-2Ply | C38: 12x72 2-Ply Poly Panel | D38: AFC | E38: 30
A39: 27053 | B39: 1272-3Ply | C39: 12x72 3-Ply Poly Panel Special | E39: 0
A40: 28407 | B40: 1280-2ply | C40: 12x80 2-Ply Poly Link | D40: 14.22 | E40: 1
A41: 28408 | B41: 1280-3-Ply | C41: 12x80 3-Ply Poly Panel | D41: AFC | E41: 3
A42: 27059 | B42: 1296-2ply | C42: 12x96 2-Ply Poly Panel Special | D42: AFC | E42: 19
A43: 27058 | B43: 1296-3Ply | C43: 12x96 3-Ply Poly Panel Special | E43: 0
A44: 27060 | B44: 1321-2ply | C44: 13x21 2-Ply Poly Panel | D44: 3.74 | E44: 50
A45: 27061 | B45: 1321-3ply | C45: 13x21 3-Ply Poly Panel | D45: 4.49 | E45: 108
A46: 27062 | B46: 1322-2ply | C46: 13x22 2-Ply Poly Panel | D46: 3.74 | E46: 49
A47: 27064 | B47: 1322-3ply | C47: 13x22 3-Ply Poly Panel | E47: 0
A48: 27063 | B48: 1324-2ply | C48: 13x24-3/4 2-Ply Poly Panel | E48: 0
A49: 27065 | B49: 14.20.2 Nova Pleat | C49: 14x20x2 NovaPleat No Wire | E49: 0
A50: 27066 | B50: 14.25.1 Nova Pleat | C50: 14x25x1 NovaPleat No Wire | E50: 0
A51: 27067 | B51: 1414-2ply | C51: 14x14 2-Ply Poly Panel | D51: 3.69 | E51: 279
A52: 27068 | B52: 1414-3ply | C52: 14x14 3-Ply Poly Panel | D52: 3.56 | E52: 25
A53: 27069 | B53: 1419-2ply | C53: 14x19 2-Ply Poly Panel | D53: 3.6 | E53: 79
A54: 27074 | B54: 1419-3ply | C54: 14x19 3-Ply Poly Panel | E54: 0
A55: 27070 | B55: 1420-2ply | C55: 14x20 2-Ply Poly Panel | D55: 4.11 | E55: 44
A56: 27072 | B56: 1420-3ply | C56: 14x20 3-Ply Poly Panel | D56: 4.43 | E56: 271
A57: 27071 | B57: 1420-5050WW-P | C57: 14x20 Poly Panel 2 Ply | E57: 0
A58: 27073 | B58: 1424-2ply | C58: 14x24 2-Ply Poly Panel | D58: 4.4 | E58: 84
A59: 27075 | B59: 1424-3ply | C59: 14x24 3-Ply Poly Panel | D59: AFC | E59: 230
A60: 27076 | B60: 1425-2ply | C60: 14x25 2-Ply Poly Panel | D60: 4.76 | E60: 180
A61: 27077 | B61: 1425-3ply | C61: 14x25 3-Ply Poly Panel | E61: 0
A62: 27078 | B62: 1428-2ply | C62: 14x28 2-Ply Poly Panel | D62: 4.9 | E62: 100
A63: 27079 | B63: 1428-3ply | C63: 14x28 3-Ply Poly Panel | D63: AFC | E63: 2
A64: 28410 | B64: 1430-2ply | C64: 14x30 2-Ply Poly Panel | D64: 5.08 | E64: 132
A65: 27080 | B65: 1430-3Ply | C65: 14x30 3-Ply Poly Panel | D65: 5.95 | E65: 201
A66: 27081 | B66: 1438-2ply | C66: 14x38 2-Ply Poly Panel | D66: 7.3 | E66: 71
A67: 27082 | B67: 1438-3ply | C67: 14x38 3-Ply Poly Panel | D67: AFC | E67: 5
A68: 27083 | B68: 1444-2ply | C68: 14x44 2-Ply Poly Panel | D68: 9.46 | E68: 111
A69: 27085 | B69: 1444-3ply | C69: 14x44 3-Ply Poly Panel | E69: 0
A70: 27084 | B70: 1520-2ply | C70: 15x20 2-Ply Poly Panel | D70: 3.83 | E70: 198
A71: 27086 | B71: 1520-3ply | C71: 15x20 3-Ply Poly Panel | D71: 4.96 | E71: 1
A72: 27090 | B72: 1520-5050WW-P | C72: 15x20 2-Ply Panel | E72: 0
A73: 27088 | B73: 1525-3ply | C73: 15x25 3-Ply Poly Panel | E73: 0
A74: 27087 | B74: 1530-2Ply | C74: 15x30 2-Ply Poly Panel | D74: 6.41 | E74: 195
A75: 27089 | B75: 1530-3Ply | C75: 15x30 3-Ply Poly Panel | D75: 6.04 | E75: 150
A76: 27091 | B76: 1530-5050WW-P | C76: 15x30 2-Ply Panel | E76: 0
A77: 27093 | B77: 15305/8-2Ply | C77: 15x30 5/8 2-Ply Poly Panel | D77: 5.09 | E77: 50
A78: 27092 | B78: 15305/8-3Ply | C78: 15x30 -5/8 3-Ply Poly Panel | E78: 0
A79: 27094 | B79: 1530W-2PLY P | C79: 15"x30" 2 PLY PANEL FILTER | E79: 0
A80: 27096 | B80: 1531-3Ply | C80: 15x31 3-Ply Poly Panel | E80: 0
A81: 27095 | B81: 1534-2ply | C81: 15x34 2-Ply Poly Panel | D81: 6.46 | E81: 1
A82: 27097 | B82: 16.20.1 Nova Pleat | C82: 16x20x1 NovaPleat No Wire | E82: 0
A83: 27098 | B83: 16.20.2 Nova Pleat | C83: 16x20x2 NovaPleat No Wire | E83: 0
A84: 27099 | B84: 16.25.1 Nova Pleat | C84: 16x25x1 NovaPleat No Wire | E84: 0
A85: 27100 | B85: 16.25.2 Nova Pleat | C85: 16x25x2 NovaPleat No Wire | E85: 0
A86: 27101 | B86: 16100-2Ply | C86: 16x100 2-Ply Poly Panel | D86: AFC | E86: 14
A87: 27102 | B87: 16120-2ply | C87: 16" X 120" 2 PLY LINK FILTER | E87: 0
A88: 27103 | B88: 16120W - 3PLY - 5L | C88: 16" X 120" 3 PLY LINK FILTER | E88: 0
A89: 27104 | B89: 1616-2Ply | C89: 16x16 2-Ply Poly Panel | D89: 3.91 | E89: 217
A90: 27105 | B90: 1616-3Ply | C90: 16x16 3-Ply Poly Panel | D90: 3.78 | E90: 48
A91: 27107 | B91: 1618-3Ply | C91: 16x18 3-Ply Poly Panel | E91: 0
A92: 27106 | B92: 1618-5050WW-P | C92: 16x18 Poly Panels 2 ply | E92: 0
A93: 27108 | B93: 1620-2Ply | C93: 16x20 2-Ply Poly Panels | D93: 3.83 | E93: 87
A94: 27109 | B94: 1620-2Ply FB Gold Panel | C94: 16x20 2-Ply Gold Panel | E94: 0
A95: 27110 | B95: 1620-3Ply | C95: 16x20 3-Ply Poly Panel | D95: 5.08 | E95: 451
A96: 27112 | B96: 1620-5050WW-P | C96: 16x20 2-Ply Panel | E96: 0
A97: 27111 | B97: 1622-2Ply | C97: 16x22 2-Ply Poly Panel | D97: 3.97 | E97: 217
A98: 27113 | B98: 1622-3Ply | C98: 16x22 3-Ply Poly Panel | D98: AFC | E98: 10
A99: 27115 | B99: 1622-5050WW-P | C99: 16x22 2-Ply Panel | E99: 0
A100: 27114 | B100: 1624-2ply | C100: 16x24 2-Ply Poly Panel | D100: 4.55 | E100: 394
...

Sheet Excel BAG 1
R1: List Price Sheet 8EX-T
M2: 46143
C3: AFC COST | D3: 35% Margin | E3: 30% Margin | F3: 25% Margin | R3: Section 8
R4: Product Bulletin 8 Bag
B5: EXCEL
B6: High Efficiency Synthetic Bag
B8: Nominal | C8: No. | E8: MERV 15 | L8: MERV 13
B9: Size | C9: of | E9: PART | F9: LIST | G9: Multiplier | L9: PART | M9: LIST | N9: Multiplier | R9: CTN.
B10: W x H x D | C10: PKTS. | E10: NUMBER | F10: PRICE | G10: 0.34 | H10: 35% Margin | I10: 30% Margin | J10: 25% Margin | L10: NUMBER | M10: PRICE | N10: 0.34 | O10: 35% Margin | P10: 30% Margin | Q10: 25% Margin | R10: QTY.
B11: 24x24x15 | C11: 6 | E11: SBG24241596 | F11: 77.14 | G11: =F11*$G$10 -> 26.2276 | H11: =(G11/0.65)+0.3 -> 40.650154 | I11: =(G11/0.7)+0.3 -> 37.768 | J11: =(G11/0.75)+0.3 -> 35.270133 | L11: SBG24241586 | M11: 72.79 | N11: =M11*$N$10 -> 24.7486 | O11: =(N11/0.65)+0.3 -> 38.374769 | P11: =(N11/0.7)+0.3 -> 35.655143 | Q11: =(N11/0.75)+0.3 -> 33.298133 | R11: 6
B12: 24x24x15 | C12: 7 | E12: SBG24241597 | F12: 86.67 | G12: =F12*$G$10 -> 29.4678 | H12: =(G12/0.65)+0.3 -> 45.635077 | I12: =(G12/0.7)+0.3 -> 42.396857 | J12: =(G12/0.75)+0.3 -> 39.5904 | L12: SBG24241587 | M12: 81.55 | N12: =M12*$N$10 -> 27.727 | O12: =(N12/0.65)+0.3 -> 42.956923 | P12: =(N12/0.7)+0.3 -> 39.91 | Q12: =(N12/0.75)+0.3 -> 37.269333 | R12: 4
B13: 24x24x15 | C13: 8 | E13: SBG24241598 | F13: 95.87 | G13: =F13*$G$10 -> 32.5958 | H13: =(G13/0.65)+0.3 -> 50.447385 | I13: =(G13/0.7)+0.3 -> 46.865429 | J13: =(G13/0.75)+0.3 -> 43.761067 | L13: SBG24241588 | M13: 90.04 | N13: =M13*$N$10 -> 30.6136 | O13: =(N13/0.65)+0.3 -> 47.397846 | P13: =(N13/0.7)+0.3 -> 44.033714 | Q13: =(N13/0.75)+0.3 -> 41.118133 | R13: 4
B14: 24x24x15 | C14: 10 | E14: SBG242415910 | F14: 115.79 | G14: =F14*$G$10 -> 39.3686 | H14: =(G14/0.65)+0.3 -> 60.867077 | I14: =(G14/0.7)+0.3 -> 56.540857 | J14: =(G14/0.75)+0.3 -> 52.791467 | L14: SBG242415810 | M14: 108.56 | N14: =M14*$N$10 -> 36.9104 | O14: =(N14/0.65)+0.3 -> 57.085231 | P14: =(N14/0.7)+0.3 -> 53.029143 | Q14: =(N14/0.75)+0.3 -> 49.513867 | R14: 4
B15: 24x24x15 | C15: 12 | E15: SBG242415912 | F15: 132.8 | G15: =F15*$G$10 -> 45.152 | H15: =(G15/0.65)+0.3 -> 69.764615 | I15: =(G15/0.7)+0.3 -> 64.802857 | J15: =(G15/0.75)+0.3 -> 60.502667 | L15: SBG242415812 | M15: 123.96 | N15: =M15*$N$10 -> 42.1464 | O15: =(N15/0.65)+0.3 -> 65.140615 | P15: =(N15/0.7)+0.3 -> 60.509143 | Q15: =(N15/0.75)+0.3 -> 56.4952 | R15: 3
B16: 24x24x21 | C16: 6 | E16: SBG24242196 | F16: 89.41 | G16: =F16*$G$10 -> 30.3994 | H16: =(G16/0.65)+0.3 -> 47.068308 | I16: =(G16/0.7)+0.3 -> 43.727714 | J16: =(G16/0.75)+0.3 -> 40.832533 | L16: SBG24242186 | M16: 84.49 | N16: =M16*$N$10 -> 28.7266 | O16: =(N16/0.65)+0.3 -> 44.494769 | P16: =(N16/0.7)+0.3 -> 41.338 | Q16: =(N16/0.75)+0.3 -> 38.602133 | R16: 5
B17: 24x24x21 | C17: 8 | E17: SBG24242198 | F17: 112.8 | G17: =F17*$G$10 -> 38.352 | H17: =(G17/0.65)+0.3 -> 59.303077 | I17: =(G17/0.7)+0.3 -> 55.088571 | J17: =(G17/0.75)+0.3 -> 51.436 | L17: SBG24242188 | M17: 106.41 | N17: =M17*$N$10 -> 36.1794 | O17: =(N17/0.65)+0.3 -> 55.960615 | P17: =(N17/0.7)+0.3 -> 51.984857 | Q17: =(N17/0.75)+0.3 -> 48.5392 | R17: 4
B18: 24x24x21 | C18: 10 | E18: SBG242421910 | F18: 142.29 | G18: =F18*$G$10 -> 48.3786 | H18: =(G18/0.65)+0.3 -> 74.728615 | I18: =(G18/0.7)+0.3 -> 69.412286 | J18: =(G18/0.75)+0.3 -> 64.8048 | L18: SBG242421810 | M18: 132.57 | N18: =M18*$N$10 -> 45.0738 | O18: =(N18/0.65)+0.3 -> 69.644308 | P18: =(N18/0.7)+0.3 -> 64.691143 | Q18: =(N18/0.75)+0.3 -> 60.3984 | R18: 4
B19: 24x24x25 | C19: 6 | E19: SBG24242596 | F19: 96.54 | G19: =F19*$G$10 -> 32.8236 | H19: =(G19/0.65)+0.3 -> 50.797846 | I19: =(G19/0.7)+0.3 -> 47.190857 | J19: =(G19/0.75)+0.3 -> 44.0648 | L19: SBG24242586 | M19: 90.37 | N19: =M19*$N$10 -> 30.7258 | O19: =(N19/0.65)+0.3 -> 47.570462 | P19: =(N19/0.7)+0.3 -> 44.194 | Q19: =(N19/0.75)+0.3 -> 41.267733 | R19: 4
B20: 24x24x25 | C20: 8 | E20: SBG24242598 | F20: 122.27 | G20: =F20*$G$10 -> 41.5718 | H20: =(G20/0.65)+0.3 -> 64.256615 | I20: =(G20/0.7)+0.3 -> 59.688286 | J20: =(G20/0.75)+0.3 -> 55.729067 | L20: SBG24242588 | M20: 113.26 | N20: =M20*$N$10 -> 38.5084 | O20: =(N20/0.65)+0.3 -> 59.543692 | P20: =(N20/0.7)+0.3 -> 55.312 | Q20: =(N20/0.75)+0.3 -> 51.644533 | R20: 3
B21: 24x24x25 | C21: 10 | E21: SBG242425910 | F21: 152.42 | G21: =F21*$G$10 -> 51.8228 | H21: =(G21/0.65)+0.3 -> 80.027385 | I21: =(G21/0.7)+0.3 -> 74.332571 | J21: =(G21/0.75)+0.3 -> 69.397067 | L21: SBG242425810 | M21: 139.68 | N21: =M21*$N$10 -> 47.4912 | O21: =(N21/0.65)+0.3 -> 73.363385 | P21: =(N21/0.7)+0.3 -> 68.144571 | Q21: =(N21/0.75)+0.3 -> 63.6216 | R21: 3
B22: 24x24x29 | C22: 6 | E22: SBG24242996 | F22: 108.28 | G22: =F22*$G$10 -> 36.8152 | H22: =(G22/0.65)+0.3 -> 56.938769 | I22: =(G22/0.7)+0.3 -> 52.893143 | J22: =(G22/0.75)+0.3 -> 49.386933 | L22: SBG24242986 | M22: 101.01 | N22: =M22*$N$10 -> 34.3434 | O22: =(N22/0.65)+0.3 -> 53.136 | P22: =(N22/0.7)+0.3 -> 49.362 | Q22: =(N22/0.75)+0.3 -> 46.0912 | R22: 4
... B60: 12x24x36 | C60: 5 | E60: SBG12243695 | F60: 102.19 | G60: =F60*$G$10 -> 34.7446 | H60: =(G60/0.65)+0.3 -> 53.753231 | I60: =(G60/0.7)+0.3 -> 49.935143 | J60: =(G60/0.75)+0.3 -> 46.626133 | L60: SBG12243685 | M60: 98.87 | N60: =M60*$N$10 -> 33.6158 | O60: =(N60/0.65)+0.3 -> 52.016615 | P60: =(N60/0.7)+0.3 -> 48.322571 | Q60: =(N60/0.75)+0.3 -> 45.121067 | R60: 6

Sheet Purapak
X1: List Price Sheet 8PK-U
T2: 46143
C3: AFC COST | D3: 35% Margin | E3: 30% Margin | F3: 25% Margin | X3: Section 8
X4: Product Bulletin 8 Bag
A6: PURAPAK
A7: High Efficiency Fiberglass Bag
A9: Nominal | B9: No. | D9: MERV 15 (90-95%) | J9: MERV 13 (80-85%) | P9: MERV 15 & 13 | R9: MERV 11 (60-65%) | X9: MERV 11
A10: Size | B10: of | D10: PART | E10: LIST | F10: Multiplier | J10: PART | K10: LIST | L10: Multiplier | P10: CTN. | R10: PART | S10: LIST | T10: Multiplier | X10: CTN.
A11: W x H x D | B11: PKTS. | D11: NUMBER | E11: PRICE | F11: 0.36 | J11: NUMBER | K11: PRICE | L11: 0.36 | P11: QTY. | R11: NUMBER | S11: PRICE | T11: 0.36 | X11: QTY.
A12: 24x24x15 | B12: 6 | D12: PBG24241596 | E12: 89.54 | F12: =E12*$F$11 -> 32.2344 | G12: =(F12/0.65)+0.3 -> 49.891385 | H12: =(F12/0.7)+0.3 -> 46.349143 | I12: =(F12/0.75)+0.3 -> 43.2792 | J12: PBG24241586 | K12: 84.6 | L12: =K12*$L$11 -> 30.456 | M12: =(L12/0.65)+0.3 -> 47.155385 | N12: =(L12/0.7)+0.3 -> 43.808571 | O12: =(L12/0.75)+0.3 -> 40.908 | P12: 6 | R12: PBG24241566 | S12: 80.01 | T12: =S12*$T$11 -> 28.8036 | U12: =(T12/0.65)+0.3 -> 44.613231 | V12: =(T12/0.7)+0.3 -> 41.448 | W12: =(T12/0.75)+0.3 -> 38.7048 | X12: 6
A13: 24x24x15 | B13: 7 | D13: PBG24241597 | E13: 100.63 | F13: =E13*$F$11 -> 36.2268 | G13: =(F13/0.65)+0.3 -> 56.033538 | H13: =(F13/0.7)+0.3 -> 52.052571 | I13: =(F13/0.75)+0.3 -> 48.6024 | J13: PBG24241587 | K13: 94.75 | L13: =K13*$L$11 -> 34.11 | M13: =(L13/0.65)+0.3 -> 52.776923 | N13: =(L13/0.7)+0.3 -> 49.028571 | O13: =(L13/0.75)+0.3 -> 45.78 | P13: 4 | R13: PBG24241567 | S13: 89.51 | T13: =S13*$T$11 -> 32.2236 | U13: =(T13/0.65)+0.3 -> 49.874769 | V13: =(T13/0.7)+0.3 -> 46.333714 | W13: =(T13/0.75)+0.3 -> 43.2648 | X13: 4
A14: 24x24x15 | B14: 8 | D14: PBG24241598 | E14: 111.38 | F14: =E14*$F$11 -> 40.0968 | G14: =(F14/0.65)+0.3 -> 61.987385 | H14: =(F14/0.7)+0.3 -> 57.581143 | I14: =(F14/0.75)+0.3 -> 53.7624 | J14: PBG24241588 | K14: 104.58 | L14: =K14*$L$11 -> 37.6488 | M14: =(L14/0.65)+0.3 -> 58.221231 | N14: =(L14/0.7)+0.3 -> 54.084 | O14: =(L14/0.75)+0.3 -> 50.4984 | P14: 4 | R14: PBG24241568 | S14: 98.59 | T14: =S14*$T$11 -> 35.4924 | U14: =(T14/0.65)+0.3 -> 54.903692 | V14: =(T14/0.7)+0.3 -> 51.003429 | W14: =(T14/0.75)+0.3 -> 47.6232 | X14: 4
A15: 24x24x15 | B15: 10 | D15: PBG242415910 | E15: 134.53 | F15: =E15*$F$11 -> 48.4308 | G15: =(F15/0.65)+0.3 -> 74.808923 | H15: =(F15/0.7)+0.3 -> 69.486857 | I15: =(F15/0.75)+0.3 -> 64.8744 | J15: PBG242415810 | K15: 126.05 | L15: =K15*$L$11 -> 45.378 | M15: =(L15/0.65)+0.3 -> 70.112308 | N15: =(L15/0.7)+0.3 -> 65.125714 | O15: =(L15/0.75)+0.3 -> 60.804 | P15: 3 | R15: PBG242415610 | S15: 114.95 | T15: =S15*$T$11 -> 41.382 | U15: =(T15/0.65)+0.3 -> 63.964615 | V15: =(T15/0.7)+0.3 -> 59.417143 | W15: =(T15/0.75)+0.3 -> 55.476 | X15: 3
A16: 24x24x15 | B16: 12 | D16: PBG242415912 | E16: 154.18 | F16: =E16*$F$11 -> 55.5048 | G16: =(F16/0.65)+0.3 -> 85.692 | H16: =(F16/0.7)+0.3 -> 79.592571 | I16: =(F16/0.75)+0.3 -> 74.3064 | J16: PBG242415812 | K16: 143.95 | L16: =K16*$L$11 -> 51.822 | M16: =(L16/0.65)+0.3 -> 80.026154 | N16: =(L16/0.7)+0.3 -> 74.331429 | O16: =(L16/0.75)+0.3 -> 69.396 | P16: 2 | R16: PBG242415612 | S16: 135.04 | T16: =S16*$T$11 -> 48.6144 | U16: =(T16/0.65)+0.3 -> 75.091385 | V16: =(T16/0.7)+0.3 -> 69.749143 | W16: =(T16/0.75)+0.3 -> 65.1192 | X16: 2
A17: 24x24x21 | B17: 6 | D17: PBG24242196 | E17: 103.9 | F17: =E17*$F$11 -> 37.404 | G17: =(F17/0.65)+0.3 -> 57.844615 | H17: =(F17/0.7)+0.3 -> 53.734286 | I17: =(F17/0.75)+0.3 -> 50.172 | J17: PBG24242186 | K17: 98.12 | L17: =K17*$L$11 -> 35.3232 | M17: =(L17/0.65)+0.3 -> 54.643385 | N17: =(L17/0.7)+0.3 -> 50.761714 | O17: =(L17/0.75)+0.3 -> 47.3976 | P17: 4 | R17: PBG24242166 | S17: 91.45 | T17: =S17*$T$11 -> 32.922 | U17: =(T17/0.65)+0.3 -> 50.949231 | V17: =(T17/0.7)+0.3 -> 47.331429 | W17: =(T17/0.75)+0.3 -> 44.196 | X17: 4
A18: 24x24x21 | B18: 8 | D18: PBG24242198 | E18: 130.98 | F18: =E18*$F$11 -> 47.1528 | G18: =(F18/0.65)+0.3 -> 72.842769 | H18: =(F18/0.7)+0.3 -> 67.661143 | I18: =(F18/0.75)+0.3 -> 63.1704 | J18: PBG24242188 | K18: 123.56 | L18: =K18*$L$11 -> 44.4816 | M18: =(L18/0.65)+0.3 -> 68.733231 | N18: =(L18/0.7)+0.3 -> 63.845143 | O18: =(L18/0.75)+0.3 -> 59.6088 | P18: 3 | R18: PBG24242168 | S18: 108.36 | T18: =S18*$T$11 -> 39.0096 | U18: =(T18/0.65)+0.3 -> 60.314769 | V18: =(T18/0.7)+0.3 -> 56.028 | W18: =(T18/0.75)+0.3 -> 52.3128 | X18: 3
A19: 24x24x21 | B19: 10 | D19: PBG242421910 | E19: 165.23 | F19: =E19*$F$11 -> 59.4828 | G19: =(F19/0.65)+0.3 -> 91.812 | H19: =(F19/0.7)+0.3 -> 85.275429 | I19: =(F19/0.75)+0.3 -> 79.6104 | J19: PBG242421810 | K19: 154 | L19: =K19*$L$11 -> 55.44 | M19: =(L19/0.65)+0.3 -> 85.592308 | N19: =(L19/0.7)+0.3 -> 79.5 | O19: =(L19/0.75)+0.3 -> 74.22 | P19: 3 | R19: PBG242421610 | S19: 118.5 | T19: =S19*$T$11 -> 42.66 | U19: =(T19/0.65)+0.3 -> 65.930769 | V19: =(T19/0.7)+0.3 -> 61.242857 | W19: =(T19/0.75)+0.3 -> 57.18 | X19: 3
A20: 24x24x25 | B20: 6 | D20: PBG24242596 | E20: 112.08 | F20: =E20*$F$11 -> 40.3488 | G20: =(F20/0.65)+0.3 -> 62.375077 | H20: =(F20/0.7)+0.3 -> 57.941143 | I20: =(F20/0.75)+0.3 -> 54.0984 | J20: PBG24242586 | K20: 104.96 | L20: =K20*$L$11 -> 37.7856 | M20: =(L20/0.65)+0.3 -> 58.431692 | N20: =(L20/0.7)+0.3 -> 54.279429 | O20: =(L20/0.75)+0.3 -> 50.6808 | P20: 4 | R20: PBG24242566 | S20: 99.1 | T20: =S20*$T$11 -> 35.676 | U20: =(T20/0.65)+0.3 -> 55.186154 | V20: =(T20/0.7)+0.3 -> 51.265714 | W20: =(T20/0.75)+0.3 -> 47.868 | X20: 4
A21: 24x24x25 | B21: 8 | D21: PBG24242598 | E21: 141.93 | F21: =E21*$F$11 -> 51.0948 | G21: =(F21/0.65)+0.3 -> 78.907385 | H21: =(F21/0.7)+0.3 -> 73.292571 | I21: =(F21/0.75)+0.3 -> 68.4264 | J21: PBG24242588 | K21: 131.55 | L21: =K21*$L$11 -> 47.358 | M21: =(L21/0.65)+0.3 -> 73.158462 | N21: =(L21/0.7)+0.3 -> 67.954286 | O21: =(L21/0.75)+0.3 -> 63.444 | P21: 3 | R21: PBG24242568 | S21: 124.91 | T21: =S21*$T$11 -> 44.9676 | U21: =(T21/0.65)+0.3 -> 69.480923 | V21: =(T21/0.7)+0.3 -> 64.539429 | W21: =(T21/0.75)+0.3 -> 60.2568 | X21: 3
A22: 24x24x25 | B22: 10 | D22: PBG242425910 | E22: 176.95 | F22: =E22*$F$11 -> 63.702 | G22: =(F22/0.65)+0.3 -> 98.303077 | H22: =(F22/0.7)+0.3 -> 91.302857 | I22: =(F22/0.75)+0.3 -> 85.236 | J22: PBG242425810 | K22: 162.21 | L22: =K22*$L$11 -> 58.3956 | M22: =(L22/0.65)+0.3 -> 90.139385 | N22: =(L22/0.7)+0.3 -> 83.722286 | O22: =(L22/0.75)+0.3 -> 78.1608 | P22: 3 | R22: PBG242425610 | S22: 150.97 | T22: =S22*$T$11 -> 54.3492 | U22: =(T22/0.65)+0.3 -> 83.914154 | V22: =(T22/0.7)+0.3 -> 77.941714 | W22: =(T22/0.75)+0.3 -> 72.7656 | X22: 3
A23: 24x24x29 | B23: 6 | D23: PBG24242996 | E23: 125.81 | F23: =E23*$F$11 -> 45.2916 | G23: =(F23/0.65)+0.3 -> 69.979385 | H23: =(F23/0.7)+0.3 -> 65.002286 | I23: =(F23/0.75)+0.3 -> 60.6888 | J23: PBG24242986 | K23: 117.29 | L23: =K23*$L$11 -> 42.2244 | M23: =(L23/0.65)+0.3 -> 65.260615 | N23: =(L23/0.7)+0.3 -> 60.620571 | O23: =(L23/0.75)+0.3 -> 56.5992 | P23: 3 | R23: PBG24242966 | S23: 106.58 | T23: =S23*$T$11 -> 38.3688 | U23: =(T23/0.65)+0.3 -> 59.328923 | V23: =(T23/0.7)+0.3 -> 55.112571 | W23: =(T23/0.75)+0.3 -> 51.4584 | X23: 3
... A61: 12x24x36 | B61: 5 | D61: PBG12243695 | E61: 118.66 | F61: =E61*$F$11 -> 42.7176 | G61: =(F61/0.65)+0.3 -> 66.019385 | H61: =(F61/0.7)+0.3 -> 61.325143 | I61: =(F61/0.75)+0.3 -> 57.2568 | J61: PBG12243685 | K61: 114.83 | L61: =K61*$L$11 -> 41.3388 | M61: =(L61/0.65)+0.3 -> 63.898154 | N61: =(L61/0.7)+0.3 -> 59.355429 | O61: =(L61/0.75)+0.3 -> 55.4184 | P61: 6 | R61: PBG12243665 | S61: 103.22 | T61: =S61*$T$11 -> 37.1592 | U61: =(T61/0.65)+0.3 -> 57.468 | V61: =(T61/0.7)+0.3 -> 53.384571 | W61: =(T61/0.75)+0.3 -> 49.8456 | X61: 5
A63: OPTIONS:
A64: For pricing on 20 x 20 face dimension use 20 x 24 List Price | K64: Reverse Dimension 24 x 12 Header use 24 x 24 List Price for
A65: For pricing on standard size face dimension 22 depth use | K65: the desired depth and pocket amount
A66: 21 List Price and for 30 use 29 List Price | K66: Reverse Dimension 24 x 20 Header use 24 x 24 List Price for
A67: Other special Size Length Bags - Use Next Largest Depth Size | K67: the desired depth and pocket amount and add +15%
A69: 1-1/8-inch Header Available - Add $8.00 to List Price | K69: Hanger Loops Available: Add $3.00 per loop to list
A70: Please specify when ordering | K70: Gasket Available: | P70: Add $7.00 List for (4) sides
P71: Add $6.00 List for (2) sides
P72: Add $4.75 List for (1) side

Sheet Zpak1
AB1: List Price Sheet 9PK-T
X2: 46143
C3: AFC COST | D3: 35% Margin | E3: 30% Margin | F3: 25% Margin | AB3: Section 9
AB4: Product Bulletin 9 ZPAK
F6: Z-PAK SERIES S
F7: Synthetic Media
F8: Rigid High Efficiency Air Filter
F10: Base Part | G10: Standard Size | H10: EFFICIENCY | AB10: Approx. Unit
F11: Number | G11: W x H x D | H11: MERV 9 | I11: 0.34 | J11: 35% Margin | K11: 30% Margin | L11: 25% Margin | M11: MERV 11 | N11: 0.34 | O11: 35% Margin | P11: 30% Margin | Q11: 25% Margin | R11: MERV 13 | S11: 0.34 | T11: 35% Margin | U11: 30% Margin | V11: 25% Margin | W11: MERV 14 | X11: 0.34 | AB11: Weight lb.
A12: ZPS242412M9 | B12: ZPS242412M11 | C12: ZPS242412M13 | D12: ZPS242412M14 | F12: ZPS242412 | G12: 24 x 24 x 12 | H12: 197.2 | I12: =H12*$I$11 -> 67.048 | J12: =(I12/0.65)+0.3 -> 103.45077 | K12: =(I12/0.7)+0.3 -> 96.082857 | L12: =(I12/0.75)+0.3 -> 89.697333 | M12: 203.37 | N12: =M12*$N$11 -> 69.1458 | O12: =(N12/0.65)+0.3 -> 106.67815 | P12: =(N12/0.7)+0.3 -> 99.079714 | Q12: =(N12/0.75)+0.3 -> 92.4944 | R12: 209.62 | S12: =R12*$S$11 -> 71.2708 | T12: =(S12/0.65)+0.3 -> 109.94738 | U12: =(S12/0.7)+0.3 -> 102.11543 | V12: =(S12/0.75)+0.3 -> 95.327733 | W12: 215.9 | X12: =W12*$X$11 -> 73.406 | AB12: 14
A13: ZPS122412M9 | B13: ZPS122412M11 | C13: ZPS122412M13 | D13: ZPS122412M14 | F13: ZPS122412 | G13: 12 x 24 x 12 | H13: 141.11 | I13: =H13*$I$11 -> 47.9774 | J13: =(I13/0.65)+0.3 -> 74.111385 | K13: =(I13/0.7)+0.3 -> 68.839143 | L13: =(I13/0.75)+0.3 -> 64.269867 | M13: 145.49 | N13: =M13*$N$11 -> 49.4666 | O13: =(N13/0.65)+0.3 -> 76.402462 | P13: =(N13/0.7)+0.3 -> 70.966571 | Q13: =(N13/0.75)+0.3 -> 66.255467 | R13: 149.66 | S13: =R13*$S$11 -> 50.8844 | T13: =(S13/0.65)+0.3 -> 78.583692 | U13: =(S13/0.7)+0.3 -> 72.992 | V13: =(S13/0.75)+0.3 -> 68.145867 | W13: 153.27 | X13: =W13*$X$11 -> 52.1118 | AB13: 9
A14: ZPS202012M9 | B14: ZPS202012M11 | C14: ZPS202012M13 | D14: ZPS202012M14 | F14: ZPS202012 | G14: 20 x 20 x 12 | H14: 169.96 | I14: =H14*$I$11 -> 57.7864 | J14: =(I14/0.65)+0.3 -> 89.202154 | K14: =(I14/0.7)+0.3 -> 82.852 | L14: =(I14/0.75)+0.3 -> 77.348533 | M14: 175.25 | N14: =M14*$N$11 -> 59.585 | O14: =(N14/0.65)+0.3 -> 91.969231 | P14: =(N14/0.7)+0.3 -> 85.421429 | Q14: =(N14/0.75)+0.3 -> 79.746667 | R14: 181.48 | S14: =R14*$S$11 -> 61.7032 | T14: =(S14/0.65)+0.3 -> 95.228 | U14: =(S14/0.7)+0.3 -> 88.447429 | V14: =(S14/0.75)+0.3 -> 82.570933 | W14: 187.75 | X14: =W14*$X$11 -> 63.835 | AB14: 12
A15: ZPS202412M9 | B15: ZPS202412M11 | C15: ZPS202412M13 | D15: ZPS202412M14 | F15: ZPS202412 | G15: 20 x 24 x 12 | H15: 188.2 | I15: =H15*$I$11 -> 63.988 | J15: =(I15/0.65)+0.3 -> 98.743077 | K15: =(I15/0.7)+0.3 -> 91.711429 | L15: =(I15/0.75)+0.3 -> 85.617333 | M15: 194.03 | N15: =M15*$N$11 -> 65.9702 | O15: =(N15/0.65)+0.3 -> 101.79262 | P15: =(N15/0.7)+0.3 -> 94.543143 | Q15: =(N15/0.75)+0.3 -> 88.260267 | R15: 200.24 | S15: =R15*$S$11 -> 68.0816 | T15: =(S15/0.65)+0.3 -> 105.04092 | U15: =(S15/0.7)+0.3 -> 97.559429 | V15: =(S15/0.75)+0.3 -> 91.075467 | W15: 206.52 | X15: =W15*$X$11 -> 70.2168 | AB15: 13
A16: ZPS252012M9 | B16: ZPS252012M11 | C16: ZPS252012M13 | D16: ZPS252012M14 | F16: ZPS252012 | G16: 25 x 20 x 12 | H16: 188.2 | I16: =H16*$I$11 -> 63.988 | J16: =(I16/0.65)+0.3 -> 98.743077 | K16: =(I16/0.7)+0.3 -> 91.711429 | L16: =(I16/0.75)+0.3 -> 85.617333 | M16: 194.03 | N16: =M16*$N$11 -> 65.9702 | O16: =(N16/0.65)+0.3 -> 101.79262 | P16: =(N16/0.7)+0.3 -> 94.543143 | Q16: =(N16/0.75)+0.3 -> 88.260267 | R16: 200.24 | S16: =R16*$S$11 -> 68.0816 | T16: =(S16/0.65)+0.3 -> 105.04092 | U16: =(S16/0.7)+0.3 -> 97.559429 | V16: =(S16/0.75)+0.3 -> 91.075467 | W16: 206.52 | X16: =W16*$X$11 -> 70.2168 | AB16: 13
F18: Base Part | G18: Standard Size | H18: EFFICIENCY | AB18: Approx. Unit
F19: Number | G19: W x H x D | H19: MERV 9 | M19: MERV 11 | R19: MERV 13 | W19: MERV 14 | AB19: Weight lb.
A20: ZPS24246M | B20: ZPS24246M11 | C20: ZPS24246M13 | D20: ZPS24246M14 | F20: ZPS24246 | G20: 24 x 24 x 6 | H20: 132.74 | I20: =H20*$I$11 -> 45.1316 | J20: =(I20/0.65)+0.3 -> 69.733231 | K20: =(I20/0.7)+0.3 -> 64.773714 | L20: =(I20/0.75)+0.3 -> 60.475467 | M20: 136.87 | N20: =M20*$N$11 -> 46.5358 | O20: =(N20/0.65)+0.3 -> 71.893538 | P20: =(N20/0.7)+0.3 -> 66.779714 | Q20: =(N20/0.75)+0.3 -> 62.347733 | R20: 140.72 | S20: =R20*$S$11 -> 47.8448 | T20: =(S20/0.65)+0.3 -> 73.907385 | U20: =(S20/0.7)+0.3 -> 68.649714 | V20: =(S20/0.75)+0.3 -> 64.093067 | W20: 148.52 | X20: =W20*$X$11 -> 50.4968 | AB20: 8
A21: ZPS12246M | B21: ZPS12246M11 | C21: ZPS12246M13 | D21: ZPS12246M14 | F21: ZPS12246 | G21: 12 x 24 x 6 | H21: 91.02 | I21: =H21*$I$11 -> 30.9468 | J21: =(I21/0.65)+0.3 -> 47.910462 | K21: =(I21/0.7)+0.3 -> 44.509714 | L21: =(I21/0.75)+0.3 -> 41.5624 | M21: 93.79 | N21: =M21*$N$11 -> 31.8886 | O21: =(N21/0.65)+0.3 -> 49.359385 | P21: =(N21/0.7)+0.3 -> 45.855143 | Q21: =(N21/0.75)+0.3 -> 42.818133 | R21: 96.96 | S21: =R21*$S$11 -> 32.9664 | T21: =(S21/0.65)+0.3 -> 51.017538 | U21: =(S21/0.7)+0.3 -> 47.394857 | V21: =(S21/0.75)+0.3 -> 44.2552 | W21: 100.84 | X21: =W21*$X$11 -> 34.2856 | AB21: 5
A22: ZPS20206M | B22: ZPS20206M11 | C22: ZPS20206M13 | D22: ZPS20206M14 | F22: ZPS20206 | G22: 20 x 20 x 6 | H22: 113.75 | I22: =H22*$I$11 -> 38.675 | J22: =(I22/0.65)+0.3 -> 59.8 | K22: =(I22/0.7)+0.3 -> 55.55 | L22: =(I22/0.75)+0.3 -> 51.866667 | M22: 117.3 | N22: =M22*$N$11 -> 39.882 | O22: =(N22/0.65)+0.3 -> 61.656923 | P22: =(N22/0.7)+0.3 -> 57.274286 | Q22: =(N22/0.75)+0.3 -> 53.476 | R22: 120.41 | S22: =R22*$S$11 -> 40.9394 | T22: =(S22/0.65)+0.3 -> 63.283692 | U22: =(S22/0.7)+0.3 -> 58.784857 | V22: =(S22/0.75)+0.3 -> 54.885867 | W22: 134.09 | X22: =W22*$X$11 -> 45.5906 | AB22: 6
A23: ZPS20246M | B23: ZPS20246M11 | C23: ZPS20246M13 | D23: ZPS20246M14 | F23: ZPS20246 | G23: 20 x 24 x 6 | H23: 122.55 | I23: =H23*$I$11 -> 41.667 | J23: =(I23/0.65)+0.3 -> 64.403077 | K23: =(I23/0.7)+0.3 -> 59.824286 | L23: =(I23/0.75)+0.3 -> 55.856 | M23: 129 | N23: =M23*$N$11 -> 43.86 | O23: =(N23/0.65)+0.3 -> 67.776923 | P23: =(N23/0.7)+0.3 -> 62.957143 | Q23: =(N23/0.75)+0.3 -> 58.78 | R23: 131.35 | S23: =R23*$S$11 -> 44.659 | T23: =(S23/0.65)+0.3 -> 69.006154 | U23: =(S23/0.7)+0.3 -> 64.098571 | V23: =(S23/0.75)+0.3 -> 59.845333 | W23: 136.86 | X23: =W23*$X$11 -> 46.5324 | AB23: 7
A24: ZPS25206M | B24: ZPS25206M11 | C24: ZPS25206M13 | D24: ZPS25206M14 | F24: ZPS25206 | G24: 25 x 20 x 6 | H24: 122.55 | I24: =H24*$I$11 -> 41.667 | J24: =(I24/0.65)+0.3 -> 64.403077 | K24: =(I24/0.7)+0.3 -> 59.824286 | L24: =(I24/0.75)+0.3 -> 55.856 | M24: 129 | N24: =M24*$N$11 -> 43.86 | O24: =(N24/0.65)+0.3 -> 67.776923 | P24: =(N24/0.7)+0.3 -> 62.957143 | Q24: =(N24/0.75)+0.3 -> 58.78 | R24: 131.35 | S24: =R24*$S$11 -> 44.659 | T24: =(S24/0.65)+0.3 -> 69.006154 | U24: =(S24/0.7)+0.3 -> 64.098571 | V24: =(S24/0.75)+0.3 -> 59.845333 | W24: 136.86 | X24: =W24*$X$11 -> 46.5324 | AB24: 7
F25: NOTE: The following Sizes & Part Numbers are normally in Stock for Quick Shipment
H26: Size & Description | M26: Part Number
H27: 24 x 24 x 12 MERV 14 Header | M27: ZPS24241295HO
H28: 24 x 24 x 12 MERV 14 Box | M28: ZPS24241295BO
H29: 12 x 24 x 12 MERV 14 Header | M29: ZPS12241295HO
H30: 12 x 24 x 12 MERV 14 Box | M30: ZPS12241295BO
F31: To insure that Z-Paks are fabricated to meet job requirements, order by the exact Part Number requirement.
G32: Example: 24x24x12 MERV 14 Single Header with Side Load Gasket.
G33: Part Number = ZPS24241295HJ
G34: ZPS242412 | I34: 95 | M34: H | N34: J
G36: Base | I36: Filter | M36: Frame | N36: * Gasket Location
G37: Part Number | I37: Efficiency | M37: Style | N37: (Number = sides)
G38: Select the Character | I38: 45 = MERV 9 | M38: B = Box | N38: O = No Gasket (0)
G39: Base Part Number for Desired Size | N39: Box Style
I40: 65 = MERV 11 | M40: H = Header | N40: A = Air Exit (4)
C41: GFLOSS | G41: or | N41: B = Air Entry (4)
I42: 85 = MERV 13 | M42: DH = Double | N42: C = Air Exit/Entry (8)
G43: Insert Exact Size and Efficiency | M43: Header | N43: D = Side Load (2)
G44: For Special Size Z-Pak Series S. | I44: 95 = MERV 14 | N44: Single Header
N45: E = Air Entry/Exit (8)
G46: (Contact Factory for availability | N46: F = Air Entry (4)
G47: on Special Sizes) | N47: H = Air Exit (4)
N48: J = Side Load (2)
N49: S = Side Load (1)
N50: Double Header
N51: K = Air Entry/ Exit (8)
N52: M = Air Entry (4)
N53: P = Air Exit (4)
N54: Q = Side Load (2)
N55: * Foam Gasketing is optional on Z-Pak Filters:
G56: Special Size Z-Paks used next largest size and add | N56: Add $12.50 to List for (8) sides
G57: + 30% to List Price. Maximum height = 24 nominal | N57: Add $7.00 List for 4 sides
N58: Add $6.00 List for 2 sides
G59: NOTE: Z-Pak GT (Gas Turbine Series) add +20% to List Price | N59: Add $4.75 List for 1 side
G60: Z-Pak GT Available in 24x24 & 12x24 Face Dimensions

Sheet Zpak2
C3: AFC COST | D3: 35% Margin | E3: 30% Margin | F3: 25% Margin
F6: Z-Pak
F8: Fiberglass Media
F9: Rigid High Efficiency Air Filter
F11: Base Part | G11: Standard Size | H11: EFFICIENCY | W11: Approx. Unit
F12: Number | G12: W x H x D | H12: MERV 11 | I12: 0.36 | M12: MERV 13 | N12: 0.36 | R12: MERV 15 | S12: 0.36 | W12: Weight lb.
A13: ZPK242412M9 | B13: ZPK242412M1 | C13: ZPK242412M13 | D13: ZPK242412M15 | F13: ZPK242412 | G13: 24 x 24 x 12 | H13: 222.03 | I13: =H13*$I$12 -> 79.9308 | J13: =(I13/0.65)+0.3 -> 123.27046 | K13: =(I13/0.7)+0.3 -> 114.48686 | L13: =(I13/0.75)+0.3 -> 106.8744 | M13: 228.82 | N13: =M13*$N$12 -> 82.3752 | O13: =(N13/0.65)+0.3 -> 127.03108 | P13: =(N13/0.7)+0.3 -> 117.97886 | Q13: =(N13/0.75)+0.3 -> 110.1336 | R13: 235.66 | S13: =R13*$S$12 -> 84.8376 | T13: =(S13/0.65)+0.3 -> 130.81938 | U13: =(S13/0.7)+0.3 -> 121.49657 | V13: =(S13/0.75)+0.3 -> 113.4168 | W13: 14
A14: ZPK122412M9 | B14: ZPK122412M1 | C14: ZPK122412M13 | D14: ZPK122412M15 | F14: ZPK122412 | G14: 12 x 24 x 12 | H14: 158.82 | I14: =H14*$I$12 -> 57.1752 | J14: =(I14/0.65)+0.3 -> 88.261846 | K14: =(I14/0.7)+0.3 -> 81.978857 | L14: =(I14/0.75)+0.3 -> 76.5336 | M14: 160.53 | N14: =M14*$N$12 -> 57.7908 | O14: =(N14/0.65)+0.3 -> 89.208923 | P14: =(N14/0.7)+0.3 -> 82.858286 | Q14: =(N14/0.75)+0.3 -> 77.3544 | R14: 167.38 | S14: =R14*$S$12 -> 60.2568 | T14: =(S14/0.65)+0.3 -> 93.002769 | U14: =(S14/0.7)+0.3 -> 86.381143 | V14: =(S14/0.75)+0.3 -> 80.6424 | W14: 9
A15: ZPK202012M9 | B15: ZPK202012M1 | C15: ZPK202012M13 | D15: ZPK202012M15 | F15: ZPK202012 | G15: 20 x 20 x 12 | H15: 191.26 | I15: =H15*$I$12 -> 68.8536 | J15: =(I15/0.65)+0.3 -> 106.22862 | K15: =(I15/0.7)+0.3 -> 98.662286 | L15: =(I15/0.75)+0.3 -> 92.1048 | M15: 198.09 | N15: =M15*$N$12 -> 71.3124 | O15: =(N15/0.65)+0.3 -> 110.01138 | P15: =(N15/0.7)+0.3 -> 102.17486 | Q15: =(N15/0.75)+0.3 -> 95.3832 | R15: 204.94 | S15: =R15*$S$12 -> 73.7784 | T15: =(S15/0.65)+0.3 -> 113.80523 | U15: =(S15/0.7)+0.3 -> 105.69771 | V15: =(S15/0.75)+0.3 -> 98.6712 | W15: 12
A16: ZPK202412M9 | B16: ZPK202412M1 | C16: ZPK202412M13 | D16: ZPK202412M15 | F16: ZPK202412 | G16: 20 x 24 x 12 | H16: 211.82 | I16: =H16*$I$12 -> 76.2552 | J16: =(I16/0.65)+0.3 -> 117.61569 | K16: =(I16/0.7)+0.3 -> 109.236 | L16: =(I16/0.75)+0.3 -> 101.9736 | M16: 218.58 | N16: =M16*$N$12 -> 78.6888 | O16: =(N16/0.65)+0.3 -> 121.35969 | P16: =(N16/0.7)+0.3 -> 112.71257 | Q16: =(N16/0.75)+0.3 -> 105.2184 | R16: 225.44 | S16: =R16*$S$12 -> 81.1584 | T16: =(S16/0.65)+0.3 -> 125.15908 | U16: =(S16/0.7)+0.3 -> 116.24057 | V16: =(S16/0.75)+0.3 -> 108.5112 | W16: 13
A17: ZPK252012M9 | B17: ZPK252012M1 | C17: ZPK252012M13 | D17: ZPK252012M15 | F17: ZPK252012 | G17: 25 x 20 x 12 | H17: 211.82 | I17: =H17*$I$12 -> 76.2552 | J17: =(I17/0.65)+0.3 -> 117.61569 | K17: =(I17/0.7)+0.3 -> 109.236 | L17: =(I17/0.75)+0.3 -> 101.9736 | M17: 218.58 | N17: =M17*$N$12 -> 78.6888 | O17: =(N17/0.65)+0.3 -> 121.35969 | P17: =(N17/0.7)+0.3 -> 112.71257 | Q17: =(N17/0.75)+0.3 -> 105.2184 | R17: 225.44 | S17: =R17*$S$12 -> 81.1584 | T17: =(S17/0.65)+0.3 -> 125.15908 | U17: =(S17/0.7)+0.3 -> 116.24057 | V17: =(S17/0.75)+0.3 -> 108.5112 | W17: 13
F19: Base Part | G19: Standard Size | H19: EFFICIENCY | W19: Approx. Unit
F20: Number | G20: W x H x D | H20: MERV 11 | M20: MERV 13 | R20: MERV 15 | W20: Weight lb.
A21: ZPK24246M9 | B21: ZPK24246M1 | C21: ZPK24246M13 | D21: ZPK24246M15 | F21: ZPK24246 | G21: 24 x 24 x 6 | H21: 149.41 | I21: =H21*$I$12 -> 53.7876 | J21: =(I21/0.65)+0.3 -> 83.050154 | K21: =(I21/0.7)+0.3 -> 77.139429 | L21: =(I21/0.75)+0.3 -> 72.0168 | M21: 153.62 | N21: =M21*$N$12 -> 55.3032 | O21: =(N21/0.65)+0.3 -> 85.381846 | P21: =(N21/0.7)+0.3 -> 79.304571 | Q21: =(N21/0.75)+0.3 -> 74.0376 | R21: 162.13 | S21: =R21*$S$12 -> 58.3668 | T21: =(S21/0.65)+0.3 -> 90.095077 | U21: =(S21/0.7)+0.3 -> 83.681143 | V21: =(S21/0.75)+0.3 -> 78.1224 | W21: 8
A22: ZPK12246M9 | B22: ZPK12246M1 | C22: ZPK12246M13 | D22: ZPK12246M15 | F22: ZPK12246 | G22: 12 x 24 x 6 | H22: 102.36 | I22: =H22*$I$12 -> 36.8496 | J22: =(I22/0.65)+0.3 -> 56.991692 | K22: =(I22/0.7)+0.3 -> 52.942286 | L22: =(I22/0.75)+0.3 -> 49.4328 | M22: 106.41 | N22: =M22*$N$12 -> 38.3076 | O22: =(N22/0.65)+0.3 -> 59.234769 | P22: =(N22/0.7)+0.3 -> 55.025143 | Q22: =(N22/0.75)+0.3 -> 51.3768 | R22: 110.13 | S22: =R22*$S$12 -> 39.6468 | T22: =(S22/0.65)+0.3 -> 61.295077 | U22: =(S22/0.7)+0.3 -> 56.938286 | V22: =(S22/0.75)+0.3 -> 53.1624 | W22: 5
A23: ZPK20206M9 | B23: ZPK20206M1 | C23: ZPK20206M13 | D23: ZPK20206M15 | F23: ZPK20206 | G23: 20 x 20 x 6 | H23: 128.04 | I23: =H23*$I$12 -> 46.0944 | J23: =(I23/0.65)+0.3 -> 71.214462 | K23: =(I23/0.7)+0.3 -> 66.149143 | L23: =(I23/0.75)+0.3 -> 61.7592 | M23: 131.39 | N23: =M23*$N$12 -> 47.3004 | O23: =(N23/0.65)+0.3 -> 73.069846 | P23: =(N23/0.7)+0.3 -> 67.872 | Q23: =(N23/0.75)+0.3 -> 63.3672 | R23: 144.59 | S23: =R23*$S$12 -> 52.0524 | T23: =(S23/0.65)+0.3 -> 80.380615 | U23: =(S23/0.7)+0.3 -> 74.660571 | V23: =(S23/0.75)+0.3 -> 69.7032 | W23: 6
A24: ZPK20246M9 | B24: ZPK20246M1 | C24: ZPK20246M13 | D24: ZPK20246M15 | F24: ZPK20246 | G24: 20 x 24 x 6 | H24: 140.8 | I24: =H24*$I$12 -> 50.688 | J24: =(I24/0.65)+0.3 -> 78.281538 | K24: =(I24/0.7)+0.3 -> 72.711429 | L24: =(I24/0.75)+0.3 -> 67.884 | M24: 143.42 | N24: =M24*$N$12 -> 51.6312 | O24: =(N24/0.65)+0.3 -> 79.732615 | P24: =(N24/0.7)+0.3 -> 74.058857 | Q24: =(N24/0.75)+0.3 -> 69.1416 | R24: 149.41 | S24: =R24*$S$12 -> 53.7876 | T24: =(S24/0.65)+0.3 -> 83.050154 | U24: =(S24/0.7)+0.3 -> 77.139429 | V24: =(S24/0.75)+0.3 -> 72.0168 | W24: 7
A25: ZPK25206M9 | B25: ZPK25206M1 | C25: ZPK25206M13 | D25: ZPK25206M15 | F25: ZPK25206 | G25: 25 x 20 x 6 | H25: 140.8 | I25: =H25*$I$12 -> 50.688 | J25: =(I25/0.65)+0.3 -> 78.281538 | K25: =(I25/0.7)+0.3 -> 72.711429 | L25: =(I25/0.75)+0.3 -> 67.884 | M25: 143.42 | N25: =M25*$N$12 -> 51.6312 | O25: =(N25/0.65)+0.3 -> 79.732615 | P25: =(N25/0.7)+0.3 -> 74.058857 | Q25: =(N25/0.75)+0.3 -> 69.1416 | R25: 149.41 | S25: =R25*$S$12 -> 53.7876 | T25: =(S25/0.65)+0.3 -> 83.050154 | U25: =(S25/0.7)+0.3 -> 77.139429 | V25: =(S25/0.75)+0.3 -> 72.0168 | W25: 7
F26: To insure that Z-Paks are fabricated to meet job requirements, order by the exact Part Number requirement.
F27: Example: 24x24x12 MERV 14 Single Header with Side Load Gasket.
F28: Part Number = ZPK24241295HJ
G30: ZPK242412 | I30: 95 | M30: H | N30: J
G32: Base | I32: Filter | M32: Frame | N32: * Gasket Location
G33: Part Number | I33: Efficiency | M33: Style | N33: (Number = sides)
G34: Select the Character | I34: 65 = MERV 11 | M34: B = Box | N34: O = No Gasket (0)
G35: Base Part Number for Desired Size | N35: Box Style
I36: 85 = MERV 13 | M36: H = Header | N36: A = Air Exit (4)
G37: or | N37: B = Air Entry (4)
I38: 95 = MERV 15 | M38: DH = Double | N38: C = Air Exit/Entry (8)
G39: Insert Exact Size and Efficiency | M39: Header | N39: D = Side Load (2)
G40: For Special Size Z-Pak. | N40: Single Header
N41: E = Air Entry/Exit (8)
G42: (Contact Factory for availability | N42: F = Air Entry (4)
G43: on Special Sizes) | N43: H = Air Exit (4)
N44: J = Side Load (2)
N45: S = Side Load (1)
N46: Double Header
N47: K = Air Entry/ Exit (8)
N48: M = Air Entry (4)
N49: P = Air Exit (4)
N50: Q = Side Load (2)
W51: * Foam Gasketing is optional on Z-Pak Filters:
W52: Add $12.50 to List for (8) sides
W53: Add $7.00 List for 4 sides
G54: Special Size Z-Paks used next largest size and add | W54: Add $6.00 List for 2 sides
G55: + 30% to List Price. Maximum height = 24 nominal. | W55: Add $4.75 List for 1 side

Sheet Puracell IILR
Q1: List Price Sheet 11PURIILR-B
O2: 46143
C3: AFC COST | D3: 35% Margin | E3: 30% Margin | F3: 25% Margin | Q3: Section 11
Q4: Product Bulletin 11 PURIILR
B7: PURACELL® II LR
B8: 4 BEVERAGE BOARD FRAME SYNTHETIC MEDIA
B9: Plastic Media Separators
B10: MERV 15
B11: PART | C11: NOMINAL | D11: ACTUAL | F11: UNIT | I11: CASE | N11: APPROX.
B12: NUMBER | C12: SIZE | D12: SIZE | F12: PRICE | H12: Multiplier | I12: QTY. | N12: CASE
C13: W X H X D | D13: W X H X D | H13: 0.32 | N13: WEIGHT
B14: PURSLR2424495 | C14: 24 x 24 x 4 | D14: 23 3/8 x 23 3/8 x 3 3/4 | F14: 121.83 | H14: =F14*$H$13 -> 38.9856 | I14: 3 | N14: 19 LB.
B15: PURSLR2520495 | C15: 25 x 20 x 4 | D15: 24 1/2” x 19 1/2 x 3 3/4 | F15: 138.22 | H15: =F15*$H$13 -> 44.2304 | I15: 3 | N15: 16 LB.
B16: PURSLR2024495 | C16: 20 x 24 x 4 | D16: 19 3/8 x 23 3/8 x 3 3/4 | F16: 135.72 | H16: =F16*$H$13 -> 43.4304 | I16: 3 | N16: 16 LB.
B17: PURSLR2020495 | C17: 20 x 20 x 4 | D17: 19 1/2 x 19 1/2 x 3 3/4 | F17: 113.61 | H17: =F17*$H$13 -> 36.3552 | I17: 3 | N17: 13 LB.
B18: PURSLR1824495 | C18: 18 x 24 x 4 | D18: 17 1/2 x 23 1/2 x 3 3/4 | F18: 137.58 | H18: =F18*$H$13 -> 44.0256 | I18: 3 | N18: 14 LB.
B19: PURSLR2516495 | C19: 25 x 16 x 4 | D19: 24 1/2” x 15 1/2 x 3 3/4 | F19: 127.96 | H19: =F19*$H$13 -> 40.9472 | I19: 3 | N19: 13 LB.
B20: PURSLR1620495 | C20: 16 x 20 x 4 | D20: 15 1/2 x 19 1/2 x 3 3/4 | F20: 113.61 | H20: =F20*$H$13 -> 36.3552 | I20: 3 | N20: 10 LB.
B21: PURSLR1224495 | C21: 12 x 24 x 4 | D21: 11 3/8 x 23 3/8 x 3 3/4 | F21: 89.08 | H21: =F21*$H$13 -> 28.5056 | I21: 6 | N21: 9 LB.
B24: PURACELL® II P-LR & PH-LR
B25: 4 PLASTIC FRAME SYNTHETIC MEDIA
B26: Plastic Media Separators
B27: MERV 15
B28: BASE | C28: NOMINAL | D28: ACTUAL | F28: UNIT PRICE | N28: CASE | O28: APPROX
B29: MODEL | C29: SIZE | D29: SIZE | F29: BOX (B) | G29: Multiplier | H29: HEADER (H) | I29: Multiplier | N29: QTY. | O29: CTN WT. (LB)
B30: NUMBER | C30: W X H X D | D30: W X H X D | F30: STYLE | G30: 0.29 | H30: STYLE | I30: 0.29 | O30: BOX | P30: HDR
B31: Standard Sizes | J31: 0.35 | K31: 0.3 | L31: 0.25 | M31: 0.2
B32: 242449 | C32: 24x24x4 | D32: 23 3/8 x 23 3/8 x 3 3/4 | F32: 164.53 | G32: =F32*$G$30 -> 47.7137 | H32: 170.7 | I32: =H32*$I$30 -> 49.503 | J32: =(I32/0.65)+0.3 -> 76.458462 | K32: =(I32/0.7)+0.3 -> 71.018571 | L32: =(I32/0.75)+0.3 -> 66.304 | M32: =(I32/0.8)+0.3 -> 62.17875 | N32: 3 | O32: 14 | P32: 15
B33: * 202549 | C33: 20x25x4 | D33: 19 1/2 x 24 1/2” x 3 3/4 | F33: 186.13 | G33: =F33*$G$30 -> 53.9777 | H33: 192.25 | I33: =H33*$I$30 -> 55.7525 | J33: =(I33/0.65)+0.3 -> 86.073077 | K33: =(I33/0.7)+0.3 -> 79.946429 | L33: =(I33/0.75)+0.3 -> 74.636667 | M33: =(I33/0.8)+0.3 -> 69.990625 | N33: 3 | O33: 12 | P33: 13
B34: 202449 | C34: 20x24x4 | D34: 19 3/8 x 23 3/8 x 3 3/4 | F34: 182.48 | G34: =F34*$G$30 -> 52.9192 | H34: 188.6 | I34: =H34*$I$30 -> 54.694 | J34: =(I34/0.65)+0.3 -> 84.444615 | K34: =(I34/0.7)+0.3 -> 78.434286 | L34: =(I34/0.75)+0.3 -> 73.225333 | M34: =(I34/0.8)+0.3 -> 68.6675 | N34: 3 | O34: 11 | P34: 13
B35: 202049 | C35: 20x20x4 | D35: 19 1/2 x 19 1/2 x 3 3/4 | F35: 140.4 | G35: =F35*$G$30 -> 40.716 | H35: 146.5 | I35: =H35*$I$30 -> 42.485 | J35: =(I35/0.65)+0.3 -> 65.661538 | K35: =(I35/0.7)+0.3 -> 60.992857 | L35: =(I35/0.75)+0.3 -> 56.946667 | M35: =(I35/0.8)+0.3 -> 53.40625 | N35: 3 | O35: 9 | P35: 11
B36: 182449 | C36: 18x24x4 | D36: 17 1/2 x 23 1/2 x 3 3/4 | F36: 185.81 | G36: =F36*$G$30 -> 53.8849 | H36: 191.92 | I36: =H36*$I$30 -> 55.6568 | J36: =(I36/0.65)+0.3 -> 85.925846 | K36: =(I36/0.7)+0.3 -> 79.809714 | L36: =(I36/0.75)+0.3 -> 74.509067 | M36: =(I36/0.8)+0.3 -> 69.871 | N36: 3 | O36: 10 | P36: 12
B37: * 162549 | C37: 16x25x4 | D37: 15 1/2 x 24 1/2” x 3 3/4 | F37: 167.67 | G37: =F37*$G$30 -> 48.6243 | H37: 173.8 | I37: =H37*$I$30 -> 50.402 | J37: =(I37/0.65)+0.3 -> 77.841538 | K37: =(I37/0.7)+0.3 -> 72.302857 | L37: =(I37/0.75)+0.3 -> 67.502667 | M37: =(I37/0.8)+0.3 -> 63.3025 | N37: 3 | O37: 9 | P37: 11
B38: 162049 | C38: 16x20x4 | D38: 15 1/2 x 19 1/2 x 3 3/4 | F38: 140.4 | G38: =F38*$G$30 -> 40.716 | H38: 146.5 | I38: =H38*$I$30 -> 42.485 | J38: =(I38/0.65)+0.3 -> 65.661538 | K38: =(I38/0.7)+0.3 -> 60.992857 | L38: =(I38/0.75)+0.3 -> 56.946667 | M38: =(I38/0.8)+0.3 -> 53.40625 | N38: 3 | O38: 8 | P38: 9
B39: 122449 | C39: 12x24x4 | D39: 11 3/8 x 23 3/8 x 3 3/4 | F39: 129.99 | G39: =F39*$G$30 -> 37.6971 | H39: 136.09 | I39: =H39*$I$30 -> 39.4661 | J39: =(I39/0.65)+0.3 -> 61.017077 | K39: =(I39/0.7)+0.3 -> 56.680143 | L39: =(I39/0.75)+0.3 -> 52.921467 | M39: =(I39/0.8)+0.3 -> 49.632625 | N39: 6 | O39: 14 | P39: 15
B40: * Model Number Size Configuration may be produced as 20x25 or 25x20 and 16x25 or 25x16.
B41: Foam Gasket is optional: Add $12.50 to List for (8) sides.
B42: Add $7.00 to List for (4) sides.
B43: Add $6.00 to List for (2) sides.
B44: Add $4.75 to List for (1) sides.
B46: Puracell LR P & PH | C46: Frame | D46: Base | F46: *Gasket Location
B47: Prefix ID | C47: Style | D47: Part Number | F47: (Number = Sides)
B48: PUPSLR | C48: B = Box | D48: Select the Base | F48: O = No Gasket (0)
D49: Part Number for Desired Size | F49: Box Style
C50: H = Single Header | D50: and Efficiency | F50: A = Air Exit (4)
F51: B = Air Entry (4)
F52: C = Air Exit/Entry (8)
F53: D = Side Load (2)
F54: Single Header
F55: E = Air Exit/Entry (8)
F56: F = Air Entry (4)
F57: H = Air Exit (4)
F58: J = Side Load (2)
F59: *S = Side Load (1)
N76: 48413.19 | O76: 12103.298
N77: =N76-O76 -> 36309.893 | O77: 12103.298
N78: =N77-O77 -> 24206.595 | O78: 12103.298
N79: =N78-O78 -> 12103.298 | O79: 12103.298
N83: 36885.85 | O83: 9221.4625
N84: =N83-O83 -> 27664.387 | O84: 9221.4625
N85: =N84-O84 -> 18442.925 | O85: 9221.4625
N86: =N85-O85 -> 9221.4625 | O86: 9221.4625
N89: 13798.51 | O89: 3449.6275
N90: =N89-O89 -> 10348.882 | O90: 3449.6275
N91: =N90-O90 -> 6899.255 | O91: 3449.6275
N92: =N91-O91 -> 3449.6275 | O92: 3449.6275
N94: 11939.98 | O94: 2984.995
N95: =N94-O94 -> 8954.985 | O95: 2984.995
N96: =N95-O95 -> 5969.99 | O96: 2984.995
N97: =N96-O96 -> 2984.995 | O97: 2984.995
N100: 17697.5 | O100: 4424.375
N101: =N100-O100 -> 13273.125 | O101: 4424.375
C102: Childrens Hospital of Los Angeles | N102: =N101-O101 -> 8848.75 | O102: 4424.375
C103: Glendale Adventist Medical Center | N103: =N102-O102 -> 4424.375 | O103: 4424.375
C104: Emanate Health:Queen of the Valley
C105: Emanate Health:Inter-Community Campus | N105: 14415.47 | O105: =N105/4 -> 3603.8675
C106: Emanate Health:Foothill Presbyterian Hospital | N106: =N105-O105 -> 10811.602 | O106: 3603.8675
C107: Placentia-Linda Hospital | N107: =N106-O106 -> 7207.735 | O107: 3603.8675
C108: Providence Tarzana Medical Center | N108: =N107-O107 -> 3603.8675 | O108: 3603.8675
C109: CHOC Children's Hospital
C110: Providence Saint Joseph - MAIN Burbank | N110: 48766.21 | O110: 12191.552
C111: Providence Little Co. of Mary- San Pedro | N111: =N110-O110 -> 36574.658 | O111: 12191.552
C112: Cedars-Sinai Marina Hospital | N112: =N111-O111 -> 24383.105 | O112: 12191.552
C113: St Joseph Hospital – Orange | N113: =N112-O112 -> 12191.553 | O113: 12191.552
C114: Garden Grove Hospital and Medical Center | P114: GG
C115: Huntington Beach Hospital | P115: 35974.86 | Q115: 8993.715
C116: Centinela Hospital Medical Center | P116: =P115-Q115 -> 26981.145 | Q116: 8993.715
C117: City of Hope National Medical Center – IRVINE | P117: =P116-Q116 -> 17987.43 | Q117: 8993.715
C118: City of Hope National Medical Center – DUARTE | K118: HVP24242 | M118: 672 | P118: =P117-Q117 -> 8993.715 | Q118: 8993.715
C119: Pepperdine University | K119: HVP12242 | M119: 76 | P119: HBH
C120: Palmdale Regional Medical Center | K120: F8V4-2424-GWB | M120: 107 | P120: 43880 | Q120: 10970
C121: Valley Presbyterian Hospital | K121: F8V4-1224-GWB | M121: 24 | P121: =P120-Q120 -> 32910 | Q121: 10970
C122: Aerojet RocketDyne | K122: 0 | M122: 0 | P122: =P121-Q121 -> 21940 | Q122: 10970
C123: St. Francis Medical Center | K123: HVP24244 | M123: 220 | P123: =P122-Q122 -> 10970 | Q123: 10970
C124: La Palma Intercommunity Hospital | K124: F8-08BAG242422 | M124: 90
C125: Encino Hospital Medical Center | K125: HVP16202 | M125: 152 | P125: CENTINELA
C126: West Anaheim Medical Center | K126: HVP16252 | M126: 56 | P126: 78486.53 | Q126: 19621.632
C127: Sherman Oaks Hospital | K127: HVP20202 | M127: 168 | P127: =P126-Q126 -> 58864.897 | Q127: 19621.632
C128: Chino Valley Medical Center | K128: F8V3-2020-GWB | M128: 10 | P128: =P127-Q127 -> 39243.265 | Q128: 19621.632
C129: White Memorial Montebello | K129: 1224-2ply | M129: 108 | P129: =P128-Q128 -> 19621.632 | Q129: 19621.632
...

Sheet DISTRIBUTOR MULTIPLIER SHEET
A1: DISTRIBUTOR MULTIPLIER SHEET
A2: PRICES SUBJECT TO CHANGE WITHOUT NOTICE
A3: Search Date: 4/9/2025 | G3: Section | H3: Product | I3: Price | J3: Sheet | K3: Listed | L3: Quantity | M3: Discount | N3: Multiplier
A4: Page 1 of 3 | G4: 1
A5: Discount Code Effective Date | H5: DISPOSABLE FILTERS:
A6: DVNCF-D2014 Mar 01, 2014 | H6: 1" GDS DISPOSABLE 1GDS-B | L6: Case Quantity | M6: 0.579 | N6: 0.421
A7: Freight Terms | H7: 2" GDS DISPOSABLE 1GDS-B | L7: Case Quantity | M7: 0.579 | N7: 0.421
A8: Consolidated to Full Truckload Prepaid | H8: GTA MADE-TO-ORDER DISPOSABLE 1FG | L8: Any Quantity | M8: 0.612 | N8: 0.388
A9: P.O. BOX 80759 | G9: 2
A10: RCHO STA MARG, CA 92688-0759 | H10: PADS & BULK MEDIA:
A11: United States | H11: FIBERGLASS PRE-CUT PADS 2PD | L11: Case Quantity | M11: 0.292 | N11: 0.708
A12: ADVANCED FILTRATION CONC | H12: POLYESTER PRE-CUT PADS 2PD | L12: Case Quantity | M12: 0.292 | N12: 0.708
A13: Customer No: DVNCF | H13: HOGSHAIR PRECUT PADS 2PD | L13: Case Quantity | M13: 0.292 | N13: 0.708
A14: Section Product Price Sheet Listed Quantity Discount Multiplier | H14: SERVICE ROLLS FIBERGLASS 2BK | L14: Any Quantity | M14: 0.231 | N14: 0.769
H15: SERVICE ROLLS SYNTHETIC 2BK | L15: Any Quantity | M15: 0.287 | N15: 0.713
H16: FIBERGLASS BULK MEDIA 2BK | L16: Any Quantity | M16: 0.355 | N16: 0.645
H17: POLYESTER BULK ROLL 2BK | L17: Any Quantity | M17: 0.355 | N17: 0.645
H18: U TRIM FOAM 2BK | L18: Any Quantity | M18: 0.241 | N18: 0.759
H19: HOGGHAIR MEDIA 2BK | L19: Any Quantity | M19: 0.072 | N19: 0.928
G20: 3
H21: PADS & BULK MEDIA:
H22: EC II FG AUTOMATIC ROLL FILTER 3AR | L22: Any Quantity | M22: 0.172 | N22: 0.828
H23: 1250 POLY AUTOMATIC ROLL FILTER 3AR | L23: Any Quantity | M23: 0.229 | N23: 0.771
H24: PHOENIX SERIES - SYNTHETIC 3AR | L24: Any Quantity | M24: 0.285 | N24: 0.715
G25: 4
H26: POLY RINGS, SLEEVES, & LINKS:
H27: POLY-RING/SLEEVES/LINKS 4PR | L27: Case Quantity | M27: 0.418 | N27: 0.582
H28: SPECIAL POLY RINGS/LINKS/SLEEVES 4PR | L28: Any Quantity | M28: 0.418 | N28: 0.582
H29: POLY-SLEEVE SERVICE ROLLS 4PR | L29: Any Quantity | M29: 0.418 | N29: 0.582
G30: 5
H31: AIR CLEANER REPLACEMENT FILTERS:
H32: Z-LINE 700 SG/700 SGX SERIES 5AC | L32: Case Quantity | M32: 0.547 | N32: 0.453
H33: Z-LINE 300/500 AB SERIES 5AC | L33: Case Quantity | M33: 0.383 | N33: 0.617
H34: Z-LINE 400 HW 5AC | L34: Case Quantity | M34: 0.547 | N34: 0.453
G35: 6
H36: Z-LINE PLEATED FILTERS:
H37: ZPM PLEATED MEDIA INSERTS 6SB | L37: Case Quantity | M37: 0.348 | N37: 0.652
H38: ZL 1" PLEAT 6ZL | L38: Case Quantity | M38: 0.6 | N38: 0.4
H39: ZL 2" PLEAT 6ZL | L39: Case Quantity | M39: 0.62 | N39: 0.38
H40: ZL 4" PLEAT 6ZL | L40: Case Quantity | M40: 0.6 | N40: 0.4
H41: 1" ZL MADE-TO-ORDER 6ZL | L41: Any Quantity | M41: 0.55 | N41: 0.45
H42: 2" ZL MADE-TO-ORDER 6ZL | L42: Any Quantity | M42: 0.55 | N42: 0.45
H43: 4" ZL MADE-TO-ORDER 6ZL | L43: Any Quantity | M43: 0.55 | N43: 0.45
H44: HV 1" PLEATS 6HV | L44: Case Quantity | M44: 0.66 | N44: 0.34
H45: HV 2" PLEATS 6HV | L45: Case Quantity | M45: 0.66 | N45: 0.34
H46: HV 4" PLEATS 6HV | L46: Case Quantity | M46: 0.66 | N46: 0.34
H47: HV - MADE-TO-ORDER 6HV | L47: Any Quantity | M47: 0.55 | N47: 0.45
H48: MR-11 STANDARD SIZE 1" 6MR11 | L48: Case Quantity | M48: 0.66 | N48: 0.34
... H55: MR-13 PLEAT - MADE-TO-ORDER 6MR13-B | L55: Any Quantity | M55: 0.65 | N55: 0.35
H57: 6CR | M57: 0.543 | N57: 0.457
H58: CARBOTRON PLEATED FILTER 6CR | L58: Case Quantity | M58: 0.69 | N58: 0.31
H59: Z-LINE 1000 SERIES 6UL | L59: Case Quantity | M59: 0.431 | N59: 0.569
G60: 7
H61: CUBES & CARTRIDGE FILTERS:
H62: QUAD 440 / 420 POLYESTER BAG 7QC | L62: Any Quantity | M62: 0.231 | N62: 0.769
H63: POLY-CUBE FILTERS 7QC | L63: Any Quantity | M63: 0.218 | N63: 0.782
H64: K-PAK FILTERS 7QC | L64: Any Quantity | M64: 0.16 | N64: 0.84
G65: 8
H66: BAG FILTERS:
H67: EXCEL SYNTHETIC BAG 8EX | L67: Any Quantity | M67: 0.636 | N67: 0.364
H68: PURAPAK FIBERGLASS BAG 8PK | L68: Any Quantity | M68: 0.64 | N68: 0.36
H69: OIL MIST BAG 8PK | L69: Any Quantity | M69: 0.517 | N69: 0.483
G70: 9
H71: Z-PAK RIGID CELL FILTERS:
H72: FIBERGLASS Z-PAK RIGID FILTER 9ZK | L72: Any Quantity | M72: 0.64 | N72: 0.36
H73: SYNTHETIC Z-PAK RIGID FILTER 9ZK | L73: Any Quantity | M73: 0.66 | N73: 0.34
G74: 10
H75: MAGNA RIGID CELL FILTERS:
H76: MAGNA 600, 800, 900 SERIES & MAGNA | L76: 900 SERIES &
H77: HT SERIES
H78: 10MAG -
H79: 10MAGHT
H80: Any Quantity | M80: 0.42 | N80: 0.58
H81: MAGNA 600, 800, 900 SERIES & MAGNA | L81: 900 SERIES &
H82: HT SERIES
H83: 10MAG -
H84: 10MAGHT
H85: Any Quantity | M85: 0.42 | N85: 0.58
H86: MAGNA 950, 1000, 1100 SERIES 10MAG | L86: Any Quantity | M86: 0.42 | N86: 0.58
H87: MAGNA TURBINE 10MAG | L87: Any Quantity | M87: 0.247 | N87: 0.753
G88: 11
H89: PURACELL MINI-PLEAT FILTERS:
H90: PURACELL II MINI-PLEAT SERIES - PUR 11PUR | L90: Any Quantity | M90: 0.45 | N90: 0.55
H91: PURACELL II M / MH MINI-PLT SERIES - | L91: MH MINI-PLT S
H92: PUG
H93: 11PUG | L93: Any Quantity | M93: 0.45 | N93: 0.55
H94: PURACELL II M / MH SYN MINI-PLT | L94: / MH SYN MINI
H95: SERIES - PUGS
H96: 11PUG | L96: Any Quantity | M96: 0.45 | N96: 0.55
H97: PURACELL II P / PH MINI-PLT SERIES - | L97: PH MINI-PLT S
H98: PUPF
H99: 11PUR-P | L99: Any Quantity | M99: 0.6 | N99: 0.4
H100: PURACELL II PS / PHS SYN MINI-PLT | L100: / PHS SYN MIN
H101: SERIES - PURPS
H102: 12PURVPSVPXS | L102: Any Quantity | M102: 0.6 | N102: 0.4
H103: PURACELL II 2" P-S Synthetic Mini-Pleat | L103: 2" P-S Synthe
H104: Series - PURPS2
H105: 11PUR | L105: Any Quantity | M105: 0.58 | N105: 0.42
H106: PURACELL II LR Bev Board Frame, | L106: LR Bev Board
H107: PURSLR
...
